Workbook

Sheet ACTIVOS
AR1: Código: F-DM-45
AR2: Versión: 02 | AT2: Pág.: 1 de 1
AR3: Fecha emisión: 1/03/2017
AR4: Última revisión: 25/05/2024
B6: FECHA DE ACTUALIZACION | C6: 46099
V7: RUNT POR PLACA Y CEDULA DE PROPIETARIO | AG7: RUNT POR CEDULA | AN7: SIMIT
T8: PROPIETARIO ACTUAL | AC8: RTM | AE8: SOAT | AG8: LICENCIA DE CONDUCCIÓN | AN8: INFRACCIONES | AU8: VALIDACIÓN RETIRO
B9: CEDULA | C9: NOMBRE | D9: ESTADO ACTUAL (La fecha es el dia del retiro) | E9: FECHA DE INGRESO | F9: FECHA DE NACIMIENTO | G9: EDAD | H9: GÉNERO | I9: ESTADO CIVIL | J9: ESCOLARIDAD | K9: CORREO CORPORATIVO | L9: CARGO | M9: AREA | N9: DEPARTAMENTO | O9: ES CONDUCTOR LABORAL | P9: RODAMIENTO | Q9: TIPO | R9: PLACA | S9: ¿ES PROPIETARIO? | T9: NOMBRE | U9: IDENTIFICACIÓN | V9: NUMERO VIN | W9: NUMERO MOTOR | X9: MODELO | Y9: MARCA | Z9: CILINDRAJE | AA9: KILOMETRAJE | AB9: FECHA DE MATRICULA | AC9: ESTADO ACTUAL | AD9: FECHA VENCIMIENTO | AE9: ESTADO ACTUAL | AF9: FECHA VENCIMIENTO | AG9: CATEGORIA DE LICENCIA PARA LA LABOR | AH9: CATEGORIA ACTUAL | AI9: FECHA VENCIMIENTO DE LICENCIA PARA LA LABOR | AJ9: ESTADO ACTUAL | AK9: RESTRICCIONES | AL9: CUMPLIMIENTO (3 CUMPLE TOTALMENTE) | AM9: REPORTE DE SINIESTROS VIALES | AN9: CODIGO | AO9: DESCRIPCION | AP9: FECHA | AQ9: ESTADO | AR9: ESTADO DE PAGO | AS9: FECHA DE REVISION DEL SIMIT Y RUNT POR CC Y PLCA | AT9: OBSERVACIONES

Sheet EGRESOS
A1: CEDULA | B1: NOMBRE INTEGRANTE | C1: FECHA DE RETIRO
A2: 1151941400 | B2: ESPINOSA PANCHO CARMENZA | C2: 45381
A3: 1089514916 | B3: CABEZAS TENORIO JERSON DANIEL | C3: 45383
A4: 14638890 | B4: GARCIA LIMA CESAR FELIPE | C4: 45383
A5: 1130660013 | B5: LOPEZ ZAPATA VANESSA | C5: 45383
A6: 1112480811 | B6: RAMOS HOYOS MIGUEL ESNEIDER | C6: 45383
A7: 1002620679 | B7: DIAZ SALAZAR LUISA MARIA | C7: 45386
A8: 1112491890 | B8: MARULANDA PERDIGON DIEGO ALEJANDRO | C8: 45386
A9: 1151960974 | B9: MARTINEZ CASTILLO LINA VANESA | C9: 45387
A10: 1113653077 | B10: NARANJO MONTALVO JOHN JAIRO | C10: 45388
A11: 1144139543 | B11: ORREGO HERNANDEZ MARIA ELSURY | C11: 45388
A12: 1144076253 | B12: ZUNIGA HOLGUIN CHRISTIAN EFREN | C12: 45388
A13: 31574426 | B13: GONZALEZ MURIEL IVETTE CATHERINE | C13: 45389
... A28: 1143964853 | B28: GALLEGO PALMA CAROLINA | C28: 45407
A29: #VALUE! | B29: GIRALDO RICAURTE GLORIA STEPHANY | C29: 45407
A30: #VALUE! | B30: HOLGUIN RESPTREPO DIANA PATRICIA | C30: 45407
A31: 1125251112 | B31: LENIS OBANDO LEIDY MARCELA | C31: 45407
A32: 1112221668 | B32: QUIÑONES PARRA PAOLA ANDREA | C32: 45407
A33: 1005874043 | B33: TASCON BASTIDAS JESSICA | C33: 45407
A34: 1006166997 | B34: NICOLE HENAO STACEY | C34: 45408
A35: 1060879942 | B35: MONTENEGRO IBARRA ANGELICA | C35: 45408
A36: #VALUE! | B36: AGUIRRE ORTIZ HOFMMAN RODOLFO | C36: 45412
A37: 67043152 | B37: CABRERA GUEGIA ANA MIREYA | C37: 45412
A38: 1151954224 | B38: CASTRO MONTEZUMA DANIEL ANDRES | C38: 45412
A39: #VALUE! | B39: JIMENEZ GARCIA YAMILETH | C39: 45412
A40: 1007850898 | B40: MONTANO BONILLA NAIROBY | C40: 45412
A41: 66781921 | B41: PEREZ MARTINEZ ERICA MARIA | C41: 45412
A42: 38671318 | B42: SANCHEZ LEON MYRIAM | C42: 45412
A43: 1130621193 | B43: VELASQUEZ SERNA CHRISTIAN | C43: 45413
A44: 1144149748 | B44: LUCUMI LOPEZ FABER ALBERTO | C44: 45413
A45: 1007850898 | B45: MONTANO BONILLA NAIROBY | C45: 45413
A46: 1144075120 | B46: LEMOS FLOREZ JENNIFER | C46: 45415
A47: 1087111419 | B47: RINCON ANGULO JAIME IVAN | C47: 45415
A48: 1143859721 | B48: ROSERO MINA LINA MARCELA | C48: 45418
A49: 1006295430 | B49: LOPEZ DUQUE DAISY JOHANA | C49: 45418
A50: 1143990472 | B50: AGUIRRE CORREA WILLIAM | C50: 45419
A51: 14635479 | B51: CALDERON SOTO DIEGO ALEJANDRO | C51: 45427
... A351: 1107074876 | B351: Sebastian Ospina Figueroa | C351: 45769
A352: #VALUE! | B352: Darly Yurani Hinestroza Mosquera | C352: 45769
A353: 1006235611 | B353: LEMUS CASTANEDA JHOAN SEBASTIAN | C353: 45769
A354: 1151941634 | B354: RIASCOS MESIAS YULY VANESSA | C354: 45769
A355: 1130637298 | B355: RUANO CADENA CINDY VANEZA | C355: 45771
A356: 1130655473 | B356: GONZALEZ NINO RICARDO | C356: 45771
A357: 1144175605 | B357: VELAZCO VELEZ YULI FERNANDA | C357: 45773
A358: 60448756 | B358: DELGADO ARISMENDI SANDY LORENA | C358: 45777
A359: 1151961234 | B359: MIGUEL ANGEL MUÑOZ RIVERA | C359: 45777
A360: 1006228843 | B360: LAINES POTES YULI VANESA | C360: 45779
A361: 31309224 | B361: LIDUENA MARTINEZ MARLLURY | C361: 45779
A362: 1005706794 | B362: PORTILLO MICOLTA BRASLY LICETH | C362: 45779
A363: 1107097892 | B363: SANDOVAL GONGORA KAREN DAYANA | C363: 45779
A364: 1107507170 | B364: TORRES CRUZ ANGIE LICET | C364: 45779
... A621: 38604210 | B621: DORA PATRICIA COLORADO RAMÍREZ | C621: 46101

Sheet LISTADO DE INFRACCIONES
A1: NUMERO DE INFRACCIONES INTEGRANTES REDCOLSA | B1: CÓDIGO | C1: DESCRIPCIÓN INFRACCIÓN | D1: MULTA / 2026 | E1: 50% Día 1°Hasta Día 5° Hábil | F1: 75% Día 6° HastaDía 20 Hábil
A2: =COUNTIF(ACTIVOS!AN10:$AN$768,B2) -> 0 | B2: A01 | C2: No transitar por la derecha de la via. | D2: 168900 | E2: 84450 | F2: 126675 | G2: INFRACCIÓN PARA CONDUCTORES DE VEHÍCULO NO AUTOMOTOR O DE TRACCIÓN ANIMAL | I2: COMPARENDO | J2: ACUERDO DE PAGO
A3: =COUNTIF(ACTIVOS!AN11:$AN$768,B3) -> 0 | B3: A02 | C3: Agarrarse de otro vehículo en circulación. | D3: 168900 | E3: 84450 | F3: 126675 | I3: MULTA | J3: SIN ACUERDO DE PAGO
A4: =COUNTIF(ACTIVOS!AN12:$AN$768,B4) -> 0 | B4: A03 | C4: Transportar personas o cosas que disminuyan su visibilidad e incomoden la conducción. | D4: 168900 | E4: 84450 | F4: 126675 | J4: CANCELADO
A5: =COUNTIF(ACTIVOS!AN13:$AN$768,B5) -> 0 | B5: A04 | C5: Transitar por andenes y demás lugares destinados al tránsito de peatones. | D5: 168900 | E5: 84450 | F5: 126675
A6: =COUNTIF(ACTIVOS!AN14:$AN$768,B6) -> 0 | B6: A05 | C6: No respetar las señales de tránsito. | D6: 168900 | E6: 84450 | F6: 126675
A7: =COUNTIF(ACTIVOS!AN15:$AN$768,B7) -> 0 | B7: A06 | C7: Transitar sin los dispositivos luminosos requeridos. | D7: 168900 | E7: 84450 | F7: 126675
A8: =COUNTIF(ACTIVOS!AN16:$AN$768,B8) -> 0 | B8: A07 | C8: Transitar sin dispositivos que permitan la parada inmediata o con ellos, pero en estado defectuoso. | D8: 168900 | E8: 84450 | F8: 126675
A9: =COUNTIF(ACTIVOS!AN17:$AN$768,B9) -> 0 | B9: A08 | C9: Transitar por zonas prohibidas o, por aquellas vías en donde las autoridades competentes lo prohíban o, conducir por vías diferentes a aquellas especialmente diseñadas para ello cuando las hubiere | D9: 168900 | E9: 84450 | F9: 126675
A10: =COUNTIF(ACTIVOS!AN18:$AN$768,B10) -> 0 | B10: A09 | C10: Adelantar entre dos (2) vehículos automotores que estén en sus respectivos carriles. | D10: 168900 | E10: 84450 | F10: 126675
A11: =COUNTIF(ACTIVOS!AN19:$AN$768,B11) -> 0 | B11: A10 | C11: Conducir por la vía férrea o por zonas de protección y seguridad. | D11: 168900 | E11: 84450 | F11: 126675
A12: =COUNTIF(ACTIVOS!AN20:$AN$768,B12) -> 0 | B12: A11 | C12: Transitar por zonas restringidas o por vías de alta velocidad como autopistas y arterias, en este caso el vehículo no automotor será inmovilizado. | D12: 168900 | E12: 84450 | F12: 126675
A13: =COUNTIF(ACTIVOS!AN21:$AN$768,B13) -> 0 | B13: A12 | C13: Prestar servicio público con este tipo de vehículos. Además, el vehículo será inmovilizado por primera vez, por el término de cinco días, por segunda vez veinte dias y por tercera vez cuarenta dias. | D13: 168900 | E13: 84450 | F13: 126675
A14: =COUNTIF(ACTIVOS!AN22:$AN$768,B14) -> 0 | B14: B01 | C14: Conducir un vehículo sin llevar consigo la licencia de conducción. | D14: 337400 | E14: 168700 | F14: 253050 | G14: CONDUCTOR DE UN VEHÍCULO AUTOMOTOR
A15: =COUNTIF(ACTIVOS!AN23:$AN$768,B15) -> 0 | B15: B02 | C15: Conducir un vehículo con la licencia de conducción vencida, de acuerdo a los siguientes casos: a) El conductor de servicio público que no refrende su licencia de conducción cada tres (3) años; b) El conductor de servicio público mayor de sesenta años (60) que no refrende su licencia de conducción anualmente; c) El conductor de servicio diferente al público que a partir de los sesenta y cinco (65) años de edad, no refrende su licencia de conducción cada tres (3) años; d) El conductor de servicio diferente al público, que no refrende su licencia de conducción cada cinco (5) años. INMOVILIZACIÓN: SI | D15: 337400 | E15: 168700 | F15: 253050
A16: =COUNTIF(ACTIVOS!AN24:$AN$768,B16) -> 0 | B16: B03 | C16: Conducir un vehículo sin placas, no portarlas en el extremo delantero o trasero, portarlas con obstáculos o en condiciones que dificulten su plena identificación, portar en el lugar destinado a las placas, distintivos similares a estas o que la imiten, o que correspondan a placas de otros países o, sin el permiso vigente expedido por autoridad de tránsito. Realizar cambio en las características que identifican un vehículo automotor. Cambiar, modificar o adulterar los números de identificación del motor, chasis o serie de un vehículo.) INMOVILIZACIÓN: SI | D16: 337400 | E16: 168700 | F16: 253050
A17: =COUNTIF(ACTIVOS!AN25:$AN$768,B17) -> 0 | B17: B04 | C17: Conducir un vehículo con placas adulteradas, retocadas o alteradas. INMOVILIZACIÓN: SI | D17: 337400 | E17: 168700 | F17: 253050
A18: =COUNTIF(ACTIVOS!AN26:$AN$768,B18) -> 0 | B18: B05 | C18: Conducir un vehículo con una sola placa, o sin el permiso vigente expedido por autoridad de tránsito. INMOVILIZACIÓN: SI | D18: 337400 | E18: 168700 | F18: 253050
A19: =COUNTIF(ACTIVOS!AN27:$AN$768,B19) -> 0 | B19: B06 | C19: Conducir un vehículo con placas falsas. En los casos B1, B2, B3, B4, B5 y B6 los vehículos serán inmovilizados. INMOVILIZACIÓN: SI | D19: 337400 | E19: 168700 | F19: 253050
A20: =COUNTIF(ACTIVOS!AN28:$AN$768,B20) -> 0 | B20: B07 | C20: No informar a la autoridad de tránsito competente el cambio de motor o color de un vehículo. En ambos casos, el vehículo será inmovilizado. INMOVILIZACIÓN: SI | D20: 337400 | E20: 168700 | F20: 253050
A21: =COUNTIF(ACTIVOS!AN29:$AN$768,B21) -> 0 | B21: B08 | C21: No pagar el peaje en los sitios establecidos. | D21: 337400 | E21: 168700 | F21: 253050
A22: =COUNTIF(ACTIVOS!AN30:$AN$768,B22) -> 0 | B22: B09 | C22: Utilizar equipos de sonido a volúmenes que incomoden a los pasajeros de un vehículo de servicio público. | D22: 337400 | E22: 168700 | F22: 253050
A23: =COUNTIF(ACTIVOS!AN31:$AN$768,B23) -> 0 | B23: B10 | C23: Conducir un vehículo con vidrios polarizados, entintados u oscurecidos, sin portar el permiso respectivo, de acuerdo a la reglamentación existente sobre la materia o, no llevar el vehículo de servicio público colectivo urbano todos los vidrios transparentes. | D23: 337400 | E23: 168700 | F23: 253050
A24: =COUNTIF(ACTIVOS!AN32:$AN$768,B24) -> 0 | B24: B11 | C24: Conducir un vehículo con propaganda, publicidad o adhesivos en sus vidrios que obstaculicen la visibilidad. | D24: 337400 | E24: 168700 | F24: 253050
A25: =COUNTIF(ACTIVOS!AN33:$AN$768,B25) -> 0 | B25: B12 | C25: No respetar las normas establecidas por la autoridad competente para el tránsito de cortejos fúnebres. | D25: 337400 | E25: 168700 | F25: 253050
A26: =COUNTIF(ACTIVOS!AN34:$AN$768,B26) -> 0 | B26: B13 | C26: No respetar las formaciones de tropas, la marcha de desfiles, procesiones, entierros, filas estudiantiles y las manifestaciones públicas y actividades deportivas, debidamente autorizadas por las autoridades de tránsito. | D26: 337400 | E26: 168700 | F26: 253050
... A36: =COUNTIF(ACTIVOS!AN44:$AN$768,B36) -> 0 | B36: B23 | C36: Utilizar radios, equipos de sonido o de amplificación a volúmenes que superen los decibeles máximos establecidos por las autoridades ambientales. De igual forma utilizar pantallas, proyectores de imagen o similares en la parte delantera de los vehículos, mientras esté en movimiento. | D36: 337400 | E36: 168700 | F36: 253050
A37: =COUNTIF(ACTIVOS!AN45:$AN$768,B37) -> 0 | B37: C01 | C37: Presentar licencia de conducción adulterada o ajena, lo cual dará lugar a la inmovilización del vehículo. (Si procede la inmobilización del vehículo) INMOVILIZACIÓN: SI | D37: 633200 | E37: 316600 | F37: 474900 | G37: CONDUCTOR DE VEHÍCULO AUTOMOTOR
A38: =COUNTIF(ACTIVOS!AN46:$AN$768,B38) -> 0 | B38: C02 | C38: Estacionar un vehículo en los siguientes sitios prohibidos: a) Sobre andenes, zonas verdes o sobre espacio público destinado para peatones, recreación o conservación; b) En vías arterias, autopistas, zonas de seguridad, o dentro de un cruce; c) En vías principales y colectoras en las cuales expresamente se indique la prohibición o la restricción en relación con horarios o tipos de vehículos; d) En puentes, viaductos, túneles, pasos bajos, estructuras elevadas o en cualquiera de los accesos a estos; e) En zonas expresamente destinadas para estacionamiento o parada de cierto tipo de vehículos, incluyendo las paradas de vehículos de servicio público, o para limitados físicos; f) En carriles dedicados al transporte masivo sin autorización; g) A una distancia mayor de treinta (30) centímetros de la acera o mayor a cinco (5) metros de la intersección; h) En doble fila de vehículos estacionados, o frente a hidrantes y entradas de garajes; i) En curvas; j) Donde interfiera con la salida de vehículos estacionados; k) Donde las autoridades de tránsito lo prohíban; l) En zona de seguridad y de protección de la vía férrea, en la vía principal, vías secundarias, apartaderos, estaciones y anexidades férreas; m) En los lugares de comercio u obras de construcción de los perímetros urbanos con el objeto de cargar o descargar, fuera de las zonas y horarios determinados para tal fin. INMOVILIZACIÓN: SI Solamente si este ha sido abandonado, de conformidad con el artículo 127 de la Ley 769 de 2002 | D38: 633200 | E38: 316600 | F38: 474900
A39: =COUNTIF(ACTIVOS!AN47:$AN$768,B39) -> 0 | B39: C03 | C39: Bloquear una calzada o intersección con un vehículo, salvo cuando el bloqueo obedezca a la ocurrencia de un accidente de tránsito. | D39: 633200 | E39: 316600 | F39: 474900
A40: =COUNTIF(ACTIVOS!AN48:$AN$768,B40) -> 0 | B40: C04 | C40: Estacionar un vehículo sin tomar las siguientes precauciones: a) En vías urbanas donde está permitido el estacionamiento, no realizarse lo más cercano posible al andén o al límite lateral de la calzada, esto es no menos de treinta (30) centímetros del andén y a una distancia mínima de cinco (5) metros de intersección;b) En autopistas y zonas rurales, estacionarse dentro de la vía cuando se cuenta con espacios para estacionar por fuera de esta;c) No colocar las señales reflectivas de peligro si es de día o las luces de estacionamiento y señales luminosas de peligro si es de noche;d) En caso de reparaciones en vía pública, en los perímetros rurales, no colocar las señales de peligro a distancia entre cincuenta (50) y cien (100) metros adelante y atrás del vehículo;e) En las zonas de estacionamiento prohibido, permanecer por un tiempo superior a 30 minutos, tiempo necesario para su remolque. | D40: 633200 | E40: 316600 | F40: 474900
A41: =COUNTIF(ACTIVOS!AN49:$AN$768,B41) -> 0 | B41: C05 | C41: No reducir la velocidad a treinta (30) kilómetros por hora en los siguientes casos: a) En lugares de concentración de personas y en zonas residenciales;b) En las zonas escolares en los horarios y días de funcionamiento de la institución educativa;c) Cuando se reduzcan las condiciones de visibilidad;d) Cuando las señales de tránsito así lo ordenen;e) En proximidad a una intersección;f) Cuando transite por cruces de hospitales o terminales de pasajeros. | D41: 633200 | E41: 316600 | F41: 474900
A42: =COUNTIF(ACTIVOS!AN50:$AN$768,B42) -> 0 | B42: C06 | C42: No utilizar el cinturón de seguridad por parte de los ocupantes del vehículo y los cinturones de seguridad en los asientos traseros en los vehículos fabricados a partir del año 2004. | D42: 633200 | E42: 316600 | F42: 474900
A43: =COUNTIF(ACTIVOS!AN51:$AN$768,B43) -> 0 | B43: C07 | C43: Dejar de señalizar: a) Con las luces direccionales la maniobra de giro o de cambio de carril;b) Mediante señales manuales, solo en caso de emergencia, y ante la imposibilidad de utilizar las señales direccionales, para cruzar a la izquierda o cambio de carril, para lo cual sacará el brazo izquierdo y lo extenderá horizontalmente;c) Mediante señales manuales, solo en caso de emergencia, y ante la imposibilidad de utilizar las señales direccionales para indicar cruce a la derecha, cambio de carril, para lo cual sacará el brazo izquierdo formando escuadra con la mano hacia arriba;d) Mediante señales manuales, solo en caso de emergencia, y ante la imposibilidad de utilizar las señales direccionales para indicar reducción de velocidad o detención del vehículo, para lo cual sacará el brazo izquierdo formando escuadra con la mano hacia abajo;e) En carreteras o vías rápidas, la indicación intermitente de la señal direccional por lo menos con sesenta (60) metros de antelación al giro, y en zonas urbanas, por lo menos con treinta (30) metros de antelación;f) Mediante señales manuales al peatón que tiene preferencia al paso de la vía, una vez detenido el vehículo y siempre y cuando esté cruzando por una zona demarcada en vías de baja velocidad. | D43: 633200 | E43: 316600 | F43: 474900
A44: =COUNTIF(ACTIVOS!AN52:$AN$768,B44) -> 0 | B44: C08 | C44: Transitar sin los dispositivos luminosos requeridos; no llevar los vehículos de servicio público y oficial, un aviso visible tanto en el interior como en el exterior en el que se señale el número telefónico del centro de llamadas contratado por la Superintendencia de Puertos y Transporte o los vehículos de servicio público no llevar además marcado en los costados y en el techo el número de la placa o los demás elementos determinados en este código. | D44: 633200 | E44: 316600 | F44: 474900
A45: =COUNTIF(ACTIVOS!AN53:$AN$768,B45) -> 0 | B45: C09 | C45: No respetar las señales de detención en el cruce de una línea férrea a una distancia mínima de cinco (5) metros de la vía férrea o conducir por la vía férrea o por las zonas de protección y seguridad de ella. | D45: 633200 | E45: 316600 | F45: 474900
A46: =COUNTIF(ACTIVOS!AN54:$AN$768,B46) -> 0 | B46: C10 | C46: Conducir un vehículo con una o varias puertas abiertas. | D46: 633200 | E46: 316600 | F46: 474900
A47: =COUNTIF(ACTIVOS!AN55:$AN$768,B47) -> 0 | B47: C11 | C47: No portar como mínimo el siguiente equipo de prevención y seguridad: a) Un gato con capacidad para elevar el vehículo;b) Una cruceta;c) Dos señales de carretera en forma de triángulo en material reflectivo y provistas de soportes para ser colocadas en forma vertical o lámparas de señal de luz amarilla intermitentes o de destello;d) Un botiquín de primeros auxilios;e) Un extintor;f) Dos tacos para bloquear el vehículo;g) Caja de herramienta básica que como mínimo deberá contener: Alicate, destornilladores, llave de expansión y llaves fijas;h) Llanta de repuesto;i) Linterna. | D47: 633200 | E47: 316600 | F47: 474900
A48: =COUNTIF(ACTIVOS!AN56:$AN$768,B48) -> 0 | B48: C12 | C48: Proveer de combustible un vehículo automotor con el motor encendido, con pasajeros a bordo cuando el vehículo es de servicio público de radio de acción nacional, transporte especial y escolar o proveer de combustible un vehículo de radio de acción metropolitano, distrital o municipal mientras que estén prestando el servicio | D48: 633200 | E48: 316600 | F48: 474900
A49: =COUNTIF(ACTIVOS!AN57:$AN$768,B49) -> 0 | B49: C13 | C49: Conducir un vehículo automotor sin las adaptaciones pertinentes, cuando el conductor padece de limitación física. | D49: 633200 | E49: 316600 | F49: 474900
... A76: =COUNTIF(ACTIVOS!AN84:$AN$768,B76) -> 0 | B76: C40 | C76: Los conductores con movilidad normal que estacionen sus vehículos en lugares públicos de estacionamiento, específicamente demarcados con el símbolo internacional de accesibilidad para los automotores que transporten o sean conducidos por personas con movilidad reducida o vehículos para centros de educación especial o de rehabilitación, incurrirán en sanción de multa de quince (15) salarios mínimos legales diarios vigentes. | D76: 633200 | E76: 316600 | F76: 474900
A77: =COUNTIF(ACTIVOS!AN85:$AN$768,B77) -> 0 | B77: D01 | C77: Guiar un vehículo sin haber obtenido la licencia de conducción correspondiente. Además, el vehículo será inmovilizado en el lugar de los hechos, hasta que este sea retirado por una persona autorizada por el infractor con licencia de conducción. INMOVILIZACIÓN: SI | D77: 1266100 | E77: 633050 | F77: 949575 | G77: CONDUCTOR DE VEHÍCULO AUTOMOTOR
A78: =COUNTIF(ACTIVOS!AN86:$AN$768,B78) -> 0 | B78: D02 | C78: Conducir sin portar el Seguro Obligatorio de Accidentes de Tránsito ordenado por la ley. Además, el vehículo será inmovilizado. INMOVILIZACIÓN: SI | D78: 1266100 | E78: 633050 | F78: 949575
A79: =COUNTIF(ACTIVOS!AN87:$AN$768,B79) -> 0 | B79: D03 | C79: Transitar en sentido contrario al estipulado para la vía, calzada o carril. En el caso de motocicletas se procederá a su inmovilización hasta tanto no se pague el valor de la multa o la autoridad competente decida sobre su imposición en los términos de los artículos 135 y 136 del Código Nacional de Tránsito. INMOVILIZACIÓN: SI | D79: 1266100 | E79: 633050 | F79: 949575
A80: =COUNTIF(ACTIVOS!AN88:$AN$768,B80) -> 0 | B80: D04 | C80: No detenerse ante una luz roja o amarilla de semáforo, una señal de "PARE" o un semáforo intermitente en rojo. En el caso de motocicletas se procederá a su inmovilización hasta tanto no se pague el valor de la multa o la autoridad competente decida sobre su imposición en los términos de los artículos 135 y 136 del Código Nacional de Tránsito. INMOVILIZACIÓN: SI | D80: 1266100 | E80: 633050 | F80: 949575
A81: =COUNTIF(ACTIVOS!AN89:$AN$768,B81) -> 0 | B81: D05 | C81: Conducir un vehículo sobre aceras, plazas, vías peatonales, separadores, bermas, demarcaciones de canalización, zonas verdes o vías especiales para vehículos no motorizados. En el caso de motocicletas se procederá a su inmovilización hasta tanto no se pague el valor de la multa o la autoridad competente decida sobre su imposición en los términos de los artículos 135 y 136 del Código Nacional de Tránsito. INMOVILIZACIÓN: SI | D81: 1266100 | E81: 633050 | F81: 949575
A82: =COUNTIF(ACTIVOS!AN90:$AN$768,B82) -> 0 | B82: D06 | C82: Adelantar a otro vehículo en berma, túnel, puente, curva, pasos a nivel y cruces no regulados o al aproximarse a la cima de una cuesta o donde la señal de tránsito correspondiente lo indique. En el caso de motocicletas se procederá a su inmovilización hasta tanto no se pague el valor de la multa o la autoridad competente decida sobre su imposición en los términos de los artículos 135 y 136 del Código Nacional de Tránsito. INMOVILIZACIÓN: SI | D82: 1266100 | E82: 633050 | F82: 949575
A83: =COUNTIF(ACTIVOS!AN91:$AN$768,B83) -> 0 | B83: D07 | C83: Conducir realizando maniobras altamente peligrosas, siempre y cuando la maniobra viole las normas de tránsito que pongan en peligro a las personas o las cosas y que constituyan conductas dolosas o altamente imprudentes. En el caso de motocicletas se procederá a su inmovilización hasta tanto no se pague el valor de la multa o la autoridad competente decida sobre su imposición en los términos de los artículos 135 y 136 del Código Nacional de Tránsito. INMOVILIZACIÓN: SI | D83: 1266100 | E83: 633050 | F83: 949575
A84: =COUNTIF(ACTIVOS!AN92:$AN$768,B84) -> 0 | B84: D08 | C84: Conducir un vehículo sin luces o sin los dispositivos luminosos de posición, direccionales o de freno, o con alguna de ellas dañada, en las horas o circunstancias señaladas a continuación, además, el vehículo será inmovilizado, cuando no le funcionen dos (2) o más de estas luces. a) No tener encendidas las luces exteriores a partir de las dieciocho (18) horas hasta las seis (6) horas del día siguiente, y cuando las condiciones de visibilidad sean adversas o en los horarios de excepción que fijen las autoridades de tránsito;b) No tener encendidas dentro del perímetro urbano la luz media, y hacer uso de luces exploradoras sin estar orientadas sólo hacia la superficie de la vía, cuando estas estén colocadas por debajo de las defensas del vehículo o cuando se trate de unidades integradas por el fabricante en el conjunto de luces frontales del vehículo;c) Usar la luz plena o alta, fuera del perímetro urbano, cuando se aproxime un vehículo en sentido contrario o cuando la autoridad lo indique mediante la señal de tránsito correspondiente, o cuando la luz plena alcance un vehículo que transite adelante y pueda perturbar su conducción;d) No utilizar las señales direccionales de su vehículo para dar un giro o para cambiar de carril. En caso de emergencia, y ante la imposibilidad de utilizar las señales direccionales no utilizar señales manuales;e) No utilizar la señal luminosa intermitente que corresponda, al detener su vehículo en la vía pública, no orillarse al lado derecho de la vía y efectuar maniobras que pongan en peligro a las personas o a otros vehículos.INMOVILIZACIÓN: SI | D84: 1266100 | E84: 633050 | F84: 949575
A85: =COUNTIF(ACTIVOS!AN93:$AN$768,B85) -> 0 | B85: D09 | C85: No permitir el paso de los vehículos de emergencia, esto es, ambulancias, vehículos de cuerpo de bomberos, vehículos de socorro o emergencia y de la policía o ejército. El conductor debe orillarse al costado derecho de la calzada o carril y detener el movimiento del vehículo, cuando anuncien su presencia por medio de luces, sirenas, campanas o cualquier señal óptica o audible. | D85: 1266100 | E85: 633050 | F85: 949575
A86: =COUNTIF(ACTIVOS!AN94:$AN$768,B86) -> 0 | B86: D10 | C86: Conducir un vehículo para transporte escolar con exceso de velocidad. En las vías urbanas, la velocidad no podrá ser superior a sesenta (60) kilómetros por hora y siempre y cuando se encuentre debidamente señalizada. En las carreteras nacionales y departamentales en ningún caso la velocidad podrá ser superior a ochenta (80) kilómetros por hora y siempre y cuando se encuentre debidamente señalizada. | D86: 1266100 | E86: 633050 | F86: 949575
A87: =COUNTIF(ACTIVOS!AN95:$AN$768,B87) -> 0 | B87: D11 | C87: Permitir el servicio público de pasajeros que no tenga la salida de emergencia en cada uno de sus costados adicionalmente a las puertas de ascenso de pasajeros. En este caso, la multa se impondrá solidariamente a la empresa a la cual esté afiliado y al propietario. Si se tratare de vehículo particular, se impondrá la sanción solidariamente al propietario. | D87: 1266100 | E87: 633050 | F87: 949575
A88: =COUNTIF(ACTIVOS!AN96:$AN$768,B88) -> 0 | B88: D12 | C88: Conducir un vehículo que, sin la debida autorización, se destine a un servicio diferente de aquel para el cual tiene licencia de tránsito. Además, el vehículo será inmovilizado por primera vez, por el término de cinco días, por segunda vez veinte días y por tercera vez cuarenta días. INMOVILIZACIÓN: SI | D88: 1266100 | E88: 633050 | F88: 949575
A89: =COUNTIF(ACTIVOS!AN97:$AN$768,B89) -> 0 | B89: D13 | C89: En caso de transportar carga con peso superior al autorizado el vehículo será inmovilizado y el exceso deberá ser transbordado. INMOVILIZACIÓN: SI | D89: 1266100 | E89: 633050 | F89: 949575
... A93: =COUNTIF(ACTIVOS!AN101:$AN$768,B93) -> 0 | B93: D17 | C93: Cuando se detecte o advierta una infracción a las normas de emisión contaminantes o de generación de ruido por vehículos automotores. | D93: 1266100 | E93: 633050 | F93: 949575
A94: =COUNTIF(ACTIVOS!AN102:$AN$768,B94) -> 0 | B94: E01 | C94: Proveer combustible a vehículos de servicio público con pasajeros a bordo. | D94: 1899300 | E94: 949650 | F94: 1424475 | G94: CONDUCTOR DE VEHÍCULO AUTOMOTOR
A95: =COUNTIF(ACTIVOS!AN103:$AN$768,B95) -> 0 | B95: E02 | C95: Negarse a prestar el servicio público sin causa justificada, siempre que dicha negativa cause alteración del orden público. | D95: 1899300 | E95: 949650 | F95: 1424475
A96: =COUNTIF(ACTIVOS!AN104:$AN$768,B96) -> 0 | B96: E04 | C96: Transportar en el mismo vehículo y al mismo tiempo personas y sustancias peligrosas como explosivos, tóxicos, radiactivos, combustibles no autorizados, etc. En estos casos se suspenderá la licencia por un (1) año y por dos (2) años cada vez que reincida. El vehículo será inmovilizado por un (1) año cada vez. INMOVILIZACIÓN: SI | D96: 1899300 | E96: 949650 | F96: 1424475
A97: =COUNTIF(ACTIVOS!AN105:$AN$768,B97) -> 0 | B97: E05 Revisar | C97: Conducir un vehículo sobre aceras, plazas, vías peatonales, separadores, bermas, demarcaciones de canalización, zonas verdes o vías especiales para vehículos no motorizados. En el caso de motocicletas se procederá a su inmovilización hasta tanto no se pague el valor de la multa o la autoridad competente decida sobre su imposición en los términos de los artículos 135 y 136 del Código Nacional de Tránsito. | D97: 1899300 | E97: 949650 | F97: 1424475
A98: =COUNTIF(ACTIVOS!AN106:$AN$768,B98) -> 0 | B98: F01 | C98: Invadir la zona destinada al tránsito de vehículos, transitar en esta en patines, monopatines, patinetas o similares. | D98: 42400 | E98: 21200 | F98: 31800 | G98: INFRACCIONES EN QUE INCURREN LOS PEATONES
A99: =COUNTIF(ACTIVOS!AN107:$AN$768,B99) -> 0 | B99: F02 | C99: Llevar, sin las debidas precauciones, elementos que puedan obstaculizar o afectar el tránsito. | D99: 42400 | E99: 21200 | F99: 31800
A100: =COUNTIF(ACTIVOS!AN108:$AN$768,B100) -> 0 | B100: F03 | C100: Cruzar por sitios no permitidos o transitar sobre el guardavías del ferrocarril. | D100: 42400 | E100: 21200 | F100: 31800
A101: =COUNTIF(ACTIVOS!AN109:$AN$768,B101) -> 0 | B101: F04 | C101: Colocarse delante o detrás de un vehículo que tenga el motor encendido. | D101: 42400 | E101: 21200 | F101: 31800
A102: =COUNTIF(ACTIVOS!AN110:$AN$768,B102) -> 0 | B102: F05 | C102: Remolcarse de vehículos en movimiento. | D102: 42400 | E102: 21200 | F102: 31800
A103: =COUNTIF(ACTIVOS!AN111:$AN$768,B103) -> 0 | B103: F06 | C103: Actuar de manera que ponga en peligro su integridad física. | D103: 42400 | E103: 21200 | F103: 31800
A104: =COUNTIF(ACTIVOS!AN112:$AN$768,B104) -> 0 | B104: F07 | C104: Cruzar la vía atravesando el tráfico vehicular en lugares en donde existen pasos peatonales. | D104: 42400 | E104: 21200 | F104: 31800
A105: =COUNTIF(ACTIVOS!AN113:$AN$768,B105) -> 0 | B105: F08 | C105: Ocupar la zona de seguridad y protección de la vía férrea, la cual se establece a una distancia no menor de doce (12) metros a lado y lado del eje de la vía férrea. | D105: 42400 | E105: 21200 | F105: 31800
A106: =COUNTIF(ACTIVOS!AN114:$AN$768,B106) -> 0 | B106: F09 | C106: Subirse o bajarse de los vehículos, estando estos en movimiento, cualquiera que sea la operación o maniobra que estén realizando. | D106: 42400 | E106: 21200 | F106: 31800
A107: =COUNTIF(ACTIVOS!AN115:$AN$768,B107) -> 0 | B107: F10 | C107: Transitar por los túneles, puentes y viaductos de las vías férreas. | D107: 42400 | E107: 21200 | F107: 31800
A108: =COUNTIF(ACTIVOS!AN116:$AN$768,B108) -> 0 | B108: F11 | C108: En relación con el STTMP, estos no deben ocupar la zona de seguridad y corredores de tránsito de los vehículos del STTMP, fuera de los lugares expresamente autorizados y habilitados para ello. | D108: 42400 | E108: 21200 | F108: 31800
A109: =COUNTIF(ACTIVOS!AN117:$AN$768,B109) -> 0 | B109: F12 | C109: Dentro del perímetro urbano, el cruce debe hacerse solo por las zonas autorizadas, como los puentes peatonales, los pasos peatonales y las bocacalles. | D109: 42400 | E109: 21200 | F109: 31800
A110: =COUNTIF(ACTIVOS!AN118:$AN$768,B110) -> 0 | B110: G01 | C110: El pasajero que sea sorprendido fumando en un vehículo de servicio público, será obligado a abandonar el automotor y deberá asistir a un curso de seguridad vial. | D110: Curso Educación Víal | E110: / $211.100 | G110: LAS SIGUIENTES INFRACCIONES SERÁN SANCIONADAS CON LA IMPOSICIÓN DE COMPARENDOS EDUCATIVOS. La infracción G se convierte en pecuniaria si al día 30 no se ha efectuado el respectivo curso
A111: =COUNTIF(ACTIVOS!AN119:$AN$768,B111) -> 0 | B111: G02 | C111: Los peatones y ciclistas que no cumplan con las disposiciones de este código, serán amonestados por la autoridad de tránsito competente y deberán asistir a un curso formativo dictado por las autoridades de tránsito. | D111: Curso Educación Víal | E111: / $211.100
A112: =COUNTIF(ACTIVOS!AN120:$AN$768,B112) -> 0 | B112: H01 | C112: Circular portando defensas rígidas diferentes de las instaladas originalmente por el fabricante. Además el vehículo será inmovilizado preventivamente hasta que sean retiradas. INMOVILIZACIÓN: SI | D112: Curso Educación Víal | E112: / $211.100 | G112: LAS SIGUIENTES INFRACCIONES EN QUE INCURRAN EL CONDUCTOR, EL PASAJERO O EL PEATÓN SERÁN SANCIONADOS CON AMONESTACIONES, ESTO ES LA OBLIGACIÓN DE ASISTIR A UN CURSO DE EDUCACIÓN VIAL SO PENA DE SER SANCIONADOS CON UNA MULTA EQUIVALENTE A CINCO (5) SALARIOS MÍNIMOS LEGALES DIARIOS VIGENTES (SMLDV) CONVERTIDAS EN UVB
A113: =COUNTIF(ACTIVOS!AN121:$AN$768,B113) -> 0 | B113: H02 | C113: El conductor que no porte la licencia de tránsito, además el vehículo será inmovilizado. INMOVILIZACIÓN: SI | D113: Curso Educación Víal | E113: / $211.100
A114: =COUNTIF(ACTIVOS!AN122:$AN$768,B114) -> 0 | B114: H03 | C114: El conductor, pasajero o peatón, que obstaculice, perjudique o ponga en riesgo a las demás personas o que no cumpla las normas y señales de tránsito que le sean aplicables o no obedezca las indicaciones que les den las autoridades de tránsito. | D114: Curso Educación Víal‬‬ | E114: / $211.100
A115: =COUNTIF(ACTIVOS!AN123:$AN$768,B115) -> 0 | B115: H04 | C115: El conductor que no respete los derechos e integridad de los peatones. | D115: Curso Educación Víal | E115: / $211.100
A116: =COUNTIF(ACTIVOS!AN124:$AN$768,B116) -> 0 | B116: H05 | C116: El conductor que no respete la prelación de paso en intersecciones o giros o según la clasificación de las vías. | D116: Curso Educación Víal | E116: / $211.100
A117: =COUNTIF(ACTIVOS!AN125:$AN$768,B117) -> 0 | B117: H06 | C117: El conductor que no tome las medidas necesarias para evitar el movimiento de vehículo estacionado. En vehículo de tracción animal no bloquear las ruedas para evitar su movimiento. | D117: Curso Educación Víal | E117: / $211.100
A118: =COUNTIF(ACTIVOS!AN126:$AN$768,B118) -> 0 | B118: H07 | C118: El conductor que lleve pasajeros en la parte exterior del vehículo, fuera de la cabina o en los estribos de los mismos. Además el vehículo será inmovilizado preventivamente hasta que se subsane dicha situación. INMOVILIZACIÓN: SI | D118: Curso Educación Víal | E118: / $211.100
A119: =COUNTIF(ACTIVOS!AN127:$AN$768,B119) -> 0 | B119: H08 | C119: El conductor que porte luces exploradoras en la parte posterior del vehículo. Además el vehículo será inmovilizado preventivamente hasta que sean retiradas. INMOVILIZACIÓN: SI | D119: Curso Educación Víal | E119: / $211.100
A120: =COUNTIF(ACTIVOS!AN128:$AN$768,B120) -> 0 | B120: H09 | C120: El pasajero que profiera expresiones injuriosas o groseras, promueva riñas o cause cualquier molestia a los demás pasajeros, además la orden de abandonar el vehículo, sin perjuicio de las sanciones a que haya lugar. | D120: Curso Educación Víal‬‬‬‬ | E120: / $211.100
A121: =COUNTIF(ACTIVOS!AN129:$AN$768,B121) -> 0 | B121: H10 | C121: Los conductores de vehículos no automotores que incurran en las siguientes infracciones: a) Transitar a una distancia mayor de un (1) metro de la acera u orilla o utilizar las vías exclusivas para servicio público colectivo;b) Cuando transiten en grupo, y no lo hagan uno detrás de otro;c) No respetar las señales, normas de tránsito y límites de velocidad;d) Adelantar a otros vehículos por la derecha o no utilizar el carril libre a la izquierda del vehículo a sobrepasar;e) No usar las señales manuales detalladas en el artículo 69 de este código;f) Cuando circulen en horas nocturnas, no llevar dispositivos en la parte delantera que proyecten luz blanca, y en la parte trasera que reflecte luz roja;g) No utilizar el casco de seguridad cuando corresponda dará lugar a la inmovilización del vehículo;h) Llevar acompañante, excepto mediante el uso de dispositivos diseñados especialmente para ello, o transportar objetos que disminuyan la visibilidad o que los incomoden en la conducción;i) No vestir chalecos o chaquetas reflectivas de identificación, los conductores de estos tipos de vehículos y sus acompañantes entre las 18:00 y las 6:00 horas del día siguiente, y siempre que la visibilidad sea escasa;j) No respetar las indicaciones del agente de tránsito. | D121: Curso Educación Víal‬‬ | E121: / $211.100
A122: =COUNTIF(ACTIVOS!AN130:$AN$768,B122) -> 0 | B122: H11 | C122: Viajar los menores de dos (2) años solos en el asiento posterior sin hacer uso de una silla que garantice su seguridad y que permita su fijación a él, siempre y cuando el menor viaje únicamente en compañía del conductor. | D122: Curso Educación Víal | E122: / $211.100
A123: =COUNTIF(ACTIVOS!AN131:$AN$768,B123) -> 0 | B123: H12 | C123: Transitar en vehículos de alto tonelaje por las vías de sitios que estén declarados o se declaren como monumentos de conservación histórica. | D123: Curso Educación Víal‬ | E123: / $211.100
A124: =COUNTIF(ACTIVOS!AN132:$AN$768,B124) -> 0 | B124: H13 | C124: Las demás conductas que constituyan infracción a las normas de tránsito y que no se encuentren descritas en este acto administrativo. | D124: Curso Educación Víal‬‬‬ | E124: / $211.100
A125: =COUNTIF(ACTIVOS!AN133:$AN$768,B125) -> 0 | B125: I01 | C125: El conductor que sea sorprendido fumando mientras conduce, dará lugar a la imposición de diez (10) salarios mínimos legales diarios vigentes. Si se tratare de un conductor de servicio público, además deberá asistir a un curso de seguridad vial. | D125: 422200 | E125: 211100 | F125: 316650 | G125: INFRACCIONES DE TRÁNSITO QUE DAN LUGAR A LA IMPOSICIÓN DE SANCIONES PECUNIARIAS DE DIFERENTE MONTO
A126: =COUNTIF(ACTIVOS!AN134:$AN$768,B126) -> 0 | B126: I02 | C126: Quien incumpla la obligación consagrada en el artículo 21 de este código, y se le compruebe que en caso de un accidente la deficiencia de carácter orgánico o funcional fue su causa, el conductor se hará acreedor a una multa de hasta cien (100) salarios mínimos diarios legales vigentes y a la suspensión de la licencia de conducción hasta por cinco (5) años. ** Artículo 21. Limitados físicos (Código Nacional de Tránsito Terrestre)Quien padezca una limitación física parcial podrá obtener la licencia de conducción si, además del cumplimiento de los requisitos que en este Código se señalan, demuestra durante el examen indicado en el parágrafo único del artículo 18, que se encuentra habilitado y adiestrado para conducir con dicha limitación.Cuando se requiera el empleo de instrumentos ortopédicos y el vehículo esté provisto de mecanismos u otros medios auxiliares que previa demostración y constatación le capaciten para el ejercicio de la conducción, bajo su propia responsabilidad, también podrá obtener la licencia para manejar vehículos de servicio público, pero únicamente de servicio individual.PARÁGRAFO. Para el caso de limitaciones físicas progresivas, la vigencia de la licencia de conducción será determinada mediante la práctica de un examen médico especial. | D126: $4.220.300‬ | E126: 2110150 | F126: 3165225
A127: =COUNTIF(ACTIVOS!AN135:$AN$768,B127) -> 0 | B127: J01 | C127: El particular u organismo estatal que dañe, retire o modifique las señales u otros elementos reguladores o indicadores del tráfico en las ciudades, será sancionado con multa equivalente a tres (3) salarios mínimos legales mensuales vigentes | D127: 3798544 | G127: OTRAS INFRACCIONES DE COMPETENCIA DE LAS AUTORIDADES DE TRANSITO
A128: =COUNTIF(ACTIVOS!AN136:$AN$768,B128) -> 0 | B128: J02 | C128: En caso de inmovilización de vehículos de servicio público, el incumplimiento del compromiso suscrito por el propietario o infractor de subsanar la falta en un plazo no mayor a cinco (5) días, dará lugar a una multa de veinte (20) salarios mínimos legales mensuales vigentes a cargo del propietario | D128: 25358340
A129: =COUNTIF(ACTIVOS!AN137:$AN$768,B129) -> 0 | B129: J03 | C129: Serán sancionados con multa equivalente a mil (1.000) salarios mínimos legales diarios vigentes por cada unidad y a la cancelación de su registro, las ensambladoras o fabricantes de vehículos, carrocerías, remolques, semirremolques y similares, que los vendan sin el respectivo mecanismo de identificación | D129: 42263900
A130: =COUNTIF(ACTIVOS!AN138:$AN$768,B130) -> 0 | B130: J04 | C130: Será sancionado con multa equivalente a cien (100) salarios mínimos legales diarios vigentes el propietario de expendio que provea de combustible a un vehículo automotor de servicio público con el motor encendido y pasajeros a bordo | D130: 4226390
A131: =COUNTIF(ACTIVOS!AN139:$AN$768,B131) -> 0 | B131: J05 | C131: El propietario o administrador del parqueadero autorizado para materializar la inmovilización de un vehículo, que permita la salida de un vehículo inmovilizado por infracción a las normas de tránsito, sin orden de la autoridad competente, incurrirá en multa de cincuenta (50) salarios mínimos legales mensuales vigentes. Si se tratare de parqueadero autorizado no oficial, incurrirá además en suspensión o cancelación de la autorización del patio, parqueadero autorizado de acuerdo con la gravedad de la falta | D131: 63395850
A132: =COUNTIF(ACTIVOS!AN140:$AN$768,B132) -> 0 | B132: J06 | C132: El propietario o administrador del parqueadero autorizado que no entregue los elementos contenidos en el vehículo y relacionados en el inventario, así como las condiciones del estado exterior descritas a su recibo, será sancionado con una multa de veinte (20) salarios mínimos legales mensuales vigentes y adicionalmente, deberá responder por los elementos extraviados, dañados o averiados del vehículo | D132: 25358340
A133: =COUNTIF(ACTIVOS!AN141:$AN$768,B133) -> 0 | B133: 300 | C133: Incumplimiento AP (Comparendo Local)
A134: =COUNTIF(ACTIVOS!AN142:$AN$768,B134) -> 0 | B134: AP | C134: Infraccion con Acuerdo de pago

Sheet ACTIVOS 2
AO1: Código: F-DM-45
AO2: Versión: 02 | AP2: Pág.: 1 de 1
AO3: Fecha emisión: 1/03/2017
AO4: Última revisión: 25/05/2024
B6: FECHA DE ACTUALIZACION | C6: 45678
B8: CEDULA | C8: NOMBRE | D8: ESTADO ACTUAL | E8: FECHA DE INGRESO | F8: FECHA DE RETIRO | G8: FECHA DE NACIMIENTO | H8: EDAD | I8: GÉNERO | J8: CORREO CORPORATIVO | K8: CARGO | L8: AREA | M8: DEPARTAMENTO | N8: ES CONDUCTOR LABORAL | O8: RODAMIENTO | P8: TIPO | Q8: PLACA | R8: ¿ES PROPIETARIO? | S8: PROPIETARIO ACTUAL | U8: NUMERO VIN | V8: NUMERO MOTOR | W8: MODELO | X8: MARCA | Y8: CILINDRAJE | Z8: KILOMETRAJE | AA8: FECHA DE MATRICULA | AB8: REVISIÓN TECNICO MECANICA | AE8: SOAT | AH8: LICENCIA DE CONDUCCIÓN | AL8: RESTRICCIONES | AM8: CUMPLIMIENTO | AN8: REPORTE DE SINIESTROS VIALES | AO8: TIPO Y ESTADO DE PAGO DE SUS INFRACCIONES DE TRÁNSITO | AP8: OBSERVACIONES | AQ8: VALIDACIÓN RETIRO
S9: NOMBRE | T9: IDENTIFICACIÓN | AB9: ESTADO ACTUAL | AC9: ESTADO ACTUAL_CON ERROR | AD9: FECHA VENCIMIENTO | AE9: ESTADO ACTUAL | AF9: ESTADO ACTUAL_CON ERROR | AG9: FECHA VENCIMIENTO | AH9: CATEGORIA DE LICENCIA PARA LA LABOR | AI9: CATEGORIA ACTUAL | AJ9: FECHA VENCIMIENTO DE LICENCIA PARA LA LABOR | AK9: ESTADO ACTUAL
A10: 1 | B10: 1143849922 | C10: GOMEZ RAMOS LINA MARCELA | D10: =IFERROR(VLOOKUP(B10,#REF!,6,0),"ACTIVO") -> ACTIVO | E10: 45078 | F10: =IFERROR(VLOOKUP(B10,#REF!,5,0),"") | G10: 34230 | H10: =+YEARFRAC(G10,TODAY(),1) -> 32.535191 | I10: Femenino | J10: lmgomez@gane.com.co | K10: ANALISTA CONTABLE DE NOMINA | L10: CONTABILIDAD | M10: FINANCIERO | N10: NO | O10: NO | P10: No tiene | AB10: =IF(AD10<=TODAY(),"Vencida","Vigente") -> Vencida | AC10: =IF(P10="No tiene","No aplica",IF(AD10>$C$6,"Vigente","No Vigente")) -> No aplica | AE10: =IF(AG10<=TODAY(),"Vencida","Vigente") -> Vencida | AF10: =+IF(P10="No tiene","No aplica",IF(AG10>$C$6,"Vigente","No Vigente")) -> No aplica | AK10: =+IF(P10="No tiene","No aplica",IF(AJ10>$C$6,"Vigente","No Vigente")) -> No aplica | AM10: =+COUNTIFS(AC10:AK10,"Vigente") -> 0 | AQ10: =+_xlfn.XLOOKUP(B10,'BD 2025-06-14'!$A$1:$A$700,'BD 2025-06-14'!$B$1:$B$700) -> GOMEZ RAMOS LINA MARCELA
A11: 2 | B11: 66814871 | C11: LASSO ENRIQUEZ ESPERANZA DEL CARMEN | D11: =IFERROR(VLOOKUP(B11,#REF!,6,0),"ACTIVO") -> ACTIVO | E11: 39101 | F11: =IFERROR(VLOOKUP(B11,#REF!,5,0),"") | G11: 25723 | H11: =+YEARFRAC(G11,TODAY(),1) -> 55.825448 | I11: Femenino | J11: elasso@gane.com.co | K11: ANALISTA DE ATRACCION | L11: CULTURA Y DESARROLLO | M11: DIRECCION GENERAL | N11: NO | O11: NO | P11: No tiene | AB11: =IF(AD11<=TODAY(),"Vencida","Vigente") -> Vencida | AC11: =IF(P11="No tiene","No aplica",IF(AD11>$C$6,"Vigente","No Vigente")) -> No aplica | AE11: =IF(AG11<=TODAY(),"Vencida","Vigente") -> Vencida | AF11: =+IF(P11="No tiene","No aplica",IF(AG11>$C$6,"Vigente","No Vigente")) -> No aplica | AK11: =+IF(P11="No tiene","No aplica",IF(AJ11>$C$6,"Vigente","No Vigente")) -> No aplica | AM11: =+COUNTIFS(AC11:AK11,"Vigente") -> 0 | AQ11: =+_xlfn.XLOOKUP(B11,'BD 2025-06-14'!$A$1:$A$700,'BD 2025-06-14'!$B$1:$B$700) -> LASSO ENRIQUEZ ESPERANZA DEL CARMEN
A12: 3 | B12: 66834944 | C12: QUINONES VIERA MIRIAM ELISA | D12: =IFERROR(VLOOKUP(B12,#REF!,6,0),"ACTIVO") -> ACTIVO | E12: 39203 | F12: =IFERROR(VLOOKUP(B12,#REF!,5,0),"") | G12: 26342 | H12: =+YEARFRAC(G12,TODAY(),1) -> 54.129374 | I12: Femenino | J12: mequinones@gane.com.co | K12: ANALISTA DE COMPRAS | L12: LOGISTICA | M12: ADMINISTRATIVO | N12: NO | O12: NO | P12: No tiene | AB12: =IF(AD12<=TODAY(),"Vencida","Vigente") -> Vencida | AC12: =IF(P12="No tiene","No aplica",IF(AD12>$C$6,"Vigente","No Vigente")) -> No aplica | AE12: =IF(AG12<=TODAY(),"Vencida","Vigente") -> Vencida | AF12: =+IF(P12="No tiene","No aplica",IF(AG12>$C$6,"Vigente","No Vigente")) -> No aplica | AK12: =+IF(P12="No tiene","No aplica",IF(AJ12>$C$6,"Vigente","No Vigente")) -> No aplica | AM12: =+COUNTIFS(AC12:AK12,"Vigente") -> 0 | AQ12: =+_xlfn.XLOOKUP(B12,'BD 2025-06-14'!$A$1:$A$700,'BD 2025-06-14'!$B$1:$B$700) -> QUINONES VIERA MIRIAM ELISA
A13: 4 | B13: 31308740 | C13: LABRADA CORTES YUDY ANDREA | D13: =IFERROR(VLOOKUP(B13,#REF!,6,0),"ACTIVO") -> ACTIVO | E13: 42500 | F13: =IFERROR(VLOOKUP(B13,#REF!,5,0),"") | G13: 30982 | H13: =+YEARFRAC(G13,TODAY(),1) -> 41.425761 | I13: Femenino | J13: yalabrada@gane.com.co | K13: ANALISTA DE COMPRAS | L13: LOGISTICA | M13: ADMINISTRATIVO | N13: NO | O13: NO | P13: No tiene | AB13: =IF(AD13<=TODAY(),"Vencida","Vigente") -> Vencida | AC13: =IF(P13="No tiene","No aplica",IF(AD13>$C$6,"Vigente","No Vigente")) -> No aplica | AE13: =IF(AG13<=TODAY(),"Vencida","Vigente") -> Vencida | AF13: =+IF(P13="No tiene","No aplica",IF(AG13>$C$6,"Vigente","No Vigente")) -> No aplica | AK13: =+IF(P13="No tiene","No aplica",IF(AJ13>$C$6,"Vigente","No Vigente")) -> No aplica | AM13: =+COUNTIFS(AC13:AK13,"Vigente") -> 0 | AQ13: =+_xlfn.XLOOKUP(B13,'BD 2025-06-14'!$A$1:$A$700,'BD 2025-06-14'!$B$1:$B$700) -> LABRADA CORTES YUDY ANDREA
A14: 5 | B14: 29106748 | C14: ARRECHEA MOSQUERA CARMEN SEIDAD | D14: =IFERROR(VLOOKUP(B14,#REF!,6,0),"ACTIVO") -> ACTIVO | E14: 42537 | F14: =IFERROR(VLOOKUP(B14,#REF!,5,0),"") | G14: 28687 | H14: =+YEARFRAC(G14,TODAY(),1) -> 47.710454 | I14: Femenino | J14: csarrechea@gane.com.co | K14: ANALISTA DE COMPRAS | L14: LOGISTICA | M14: ADMINISTRATIVO | N14: NO | O14: NO | P14: No tiene | AB14: =IF(AD14<=TODAY(),"Vencida","Vigente") -> Vencida | AC14: =IF(P14="No tiene","No aplica",IF(AD14>$C$6,"Vigente","No Vigente")) -> No aplica | AE14: =IF(AG14<=TODAY(),"Vencida","Vigente") -> Vencida | AF14: =+IF(P14="No tiene","No aplica",IF(AG14>$C$6,"Vigente","No Vigente")) -> No aplica | AK14: =+IF(P14="No tiene","No aplica",IF(AJ14>$C$6,"Vigente","No Vigente")) -> No aplica | AM14: =+COUNTIFS(AC14:AK14,"Vigente") -> 0 | AQ14: =+_xlfn.XLOOKUP(B14,'BD 2025-06-14'!$A$1:$A$700,'BD 2025-06-14'!$B$1:$B$700) -> ARRECHEA MOSQUERA CARMEN SEIDAD
A15: 6 | B15: 31307286 | C15: CASTANO VALLEJO VERONICA | D15: =IFERROR(VLOOKUP(B15,#REF!,6,0),"ACTIVO") -> ACTIVO | E15: 39762 | F15: =IFERROR(VLOOKUP(B15,#REF!,5,0),"") | G15: 30925 | H15: =+YEARFRAC(G15,TODAY(),1) -> 41.581816 | I15: Femenino | J15: vcastano@gane.com.co | K15: ANALISTA DE CONTABILIDAD | L15: CONTABILIDAD | M15: FINANCIERO | N15: NO | O15: NO | P15: No tiene | AB15: =IF(AD15<=TODAY(),"Vencida","Vigente") -> Vencida | AC15: =IF(P15="No tiene","No aplica",IF(AD15>$C$6,"Vigente","No Vigente")) -> No aplica | AE15: =IF(AG15<=TODAY(),"Vencida","Vigente") -> Vencida | AF15: =+IF(P15="No tiene","No aplica",IF(AG15>$C$6,"Vigente","No Vigente")) -> No aplica | AK15: =+IF(P15="No tiene","No aplica",IF(AJ15>$C$6,"Vigente","No Vigente")) -> No aplica | AM15: =+COUNTIFS(AC15:AK15,"Vigente") -> 0 | AQ15: =+_xlfn.XLOOKUP(B15,'BD 2025-06-14'!$A$1:$A$700,'BD 2025-06-14'!$B$1:$B$700) -> CASTANO VALLEJO VERONICA
A16: 7 | B16: 1003804381 | C16: BUITRAGO ALVAREZ EDWARD ANDRES | D16: =IFERROR(VLOOKUP(B16,#REF!,6,0),"ACTIVO") -> ACTIVO | E16: 45363 | F16: =IFERROR(VLOOKUP(B16,#REF!,5,0),"") | G16: 37030 | H16: =+YEARFRAC(G16,TODAY(),1) -> 24.869208 | I16: Masculino | J16: eabuitrago@gane.com.co | K16: ANALISTA DE CONTABILIDAD | L16: CONTABILIDAD | M16: FINANCIERO | N16: NO | O16: NO | P16: No tiene | AB16: =IF(AD16<=TODAY(),"Vencida","Vigente") -> Vencida | AC16: =IF(P16="No tiene","No aplica",IF(AD16>$C$6,"Vigente","No Vigente")) -> No aplica | AE16: =IF(AG16<=TODAY(),"Vencida","Vigente") -> Vencida | AF16: =+IF(P16="No tiene","No aplica",IF(AG16>$C$6,"Vigente","No Vigente")) -> No aplica | AK16: =+IF(P16="No tiene","No aplica",IF(AJ16>$C$6,"Vigente","No Vigente")) -> No aplica | AM16: =+COUNTIFS(AC16:AK16,"Vigente") -> 0 | AQ16: =+_xlfn.XLOOKUP(B16,'BD 2025-06-14'!$A$1:$A$700,'BD 2025-06-14'!$B$1:$B$700) -> BUITRAGO ALVAREZ EDWARD ANDRES
A17: 8 | B17: 1082690474 | C17: CABEZAS CABEZAS RODDY GUISSEPPI | D17: =IFERROR(VLOOKUP(B17,#REF!,6,0),"ACTIVO") -> ACTIVO | E17: 45404 | F17: =IFERROR(VLOOKUP(B17,#REF!,5,0),"") | G17: 33566 | H17: =+YEARFRAC(G17,TODAY(),1) -> 34.351814 | I17: Masculino | J17: rgcabezas@gane.com.co | K17: ANALISTA DE CONTABILIDAD | L17: CONTABILIDAD | M17: FINANCIERO | N17: NO | O17: NO | P17: No tiene | AB17: =IF(AD17<=TODAY(),"Vencida","Vigente") -> Vencida | AC17: =IF(P17="No tiene","No aplica",IF(AD17>$C$6,"Vigente","No Vigente")) -> No aplica | AE17: =IF(AG17<=TODAY(),"Vencida","Vigente") -> Vencida | AF17: =+IF(P17="No tiene","No aplica",IF(AG17>$C$6,"Vigente","No Vigente")) -> No aplica | AK17: =+IF(P17="No tiene","No aplica",IF(AJ17>$C$6,"Vigente","No Vigente")) -> No aplica | AM17: =+COUNTIFS(AC17:AK17,"Vigente") -> 0 | AQ17: =+_xlfn.XLOOKUP(B17,'BD 2025-06-14'!$A$1:$A$700,'BD 2025-06-14'!$B$1:$B$700) -> CABEZAS CABEZAS RODDY GUISSEPPI
A18: 9 | B18: 1020103002 | C18: MOSQUERA POTES KATHERINE DAYANA | D18: =IFERROR(VLOOKUP(B18,#REF!,6,0),"ACTIVO") -> ACTIVO | E18: 45629 | F18: =IFERROR(VLOOKUP(B18,#REF!,5,0),"") | G18: 38056 | H18: =+YEARFRAC(G18,TODAY(),1) -> 22.058207 | I18: Femenino | J18: kdmosquera@gane.com.co | K18: ANALISTA DE CONTABILIDAD | L18: CONTABILIDAD | M18: FINANCIERO | N18: NO | O18: NO | P18: No tiene | AB18: =IF(AD18<=TODAY(),"Vencida","Vigente") -> Vencida | AC18: =IF(P18="No tiene","No aplica",IF(AD18>$C$6,"Vigente","No Vigente")) -> No aplica | AE18: =IF(AG18<=TODAY(),"Vencida","Vigente") -> Vencida | AF18: =+IF(P18="No tiene","No aplica",IF(AG18>$C$6,"Vigente","No Vigente")) -> No aplica | AK18: =+IF(P18="No tiene","No aplica",IF(AJ18>$C$6,"Vigente","No Vigente")) -> No aplica | AM18: =+COUNTIFS(AC18:AK18,"Vigente") -> 0 | AQ18: =+_xlfn.XLOOKUP(B18,'BD 2025-06-14'!$A$1:$A$700,'BD 2025-06-14'!$B$1:$B$700) -> MOSQUERA POTES KATHERINE DAYANA
A19: 10 | B19: 1006166424 | C19: PERDOMO COLINA LINA MARCELA | D19: =IFERROR(VLOOKUP(B19,#REF!,6,0),"ACTIVO") -> ACTIVO | E19: 45664 | F19: =IFERROR(VLOOKUP(B19,#REF!,5,0),"") | G19: 36567 | H19: =+YEARFRAC(G19,TODAY(),1) -> 26.134861 | I19: Femenino | J19: lmperdomo@gane.com.co | K19: ANALISTA DE CONTABILIDAD | L19: CONTABILIDAD | M19: FINANCIERO | N19: NO | O19: NO | P19: No tiene | AB19: =IF(AD19<=TODAY(),"Vencida","Vigente") -> Vencida | AC19: =IF(P19="No tiene","No aplica",IF(AD19>$C$6,"Vigente","No Vigente")) -> No aplica | AE19: =IF(AG19<=TODAY(),"Vencida","Vigente") -> Vencida | AF19: =+IF(P19="No tiene","No aplica",IF(AG19>$C$6,"Vigente","No Vigente")) -> No aplica | AK19: =+IF(P19="No tiene","No aplica",IF(AJ19>$C$6,"Vigente","No Vigente")) -> No aplica | AM19: =+COUNTIFS(AC19:AK19,"Vigente") -> 0 | AQ19: =+_xlfn.XLOOKUP(B19,'BD 2025-06-14'!$A$1:$A$700,'BD 2025-06-14'!$B$1:$B$700) -> PERDOMO COLINA LINA MARCELA
A20: 11 | B20: 1118284356 | C20: CARDONA HERNANDEZ IVAN FELIPE | D20: =IFERROR(VLOOKUP(B20,#REF!,6,0),"ACTIVO") -> ACTIVO | E20: 39479 | F20: =IFERROR(VLOOKUP(B20,#REF!,5,0),"") | G20: 31122 | H20: =+YEARFRAC(G20,TODAY(),1) -> 41.044459 | I20: Masculino | J20: fcardona@gane.com.co | K20: ANALISTA DE ESCRUTINIO | L20: ESCRUTINIO | M20: ADMINISTRATIVO | N20: NO | O20: NO | P20: No tiene | AB20: =IF(AD20<=TODAY(),"Vencida","Vigente") -> Vencida | AC20: =IF(P20="No tiene","No aplica",IF(AD20>$C$6,"Vigente","No Vigente")) -> No aplica | AE20: =IF(AG20<=TODAY(),"Vencida","Vigente") -> Vencida | AF20: =+IF(P20="No tiene","No aplica",IF(AG20>$C$6,"Vigente","No Vigente")) -> No aplica | AK20: =+IF(P20="No tiene","No aplica",IF(AJ20>$C$6,"Vigente","No Vigente")) -> No aplica | AM20: =+COUNTIFS(AC20:AK20,"Vigente") -> 0 | AQ20: =+_xlfn.XLOOKUP(B20,'BD 2025-06-14'!$A$1:$A$700,'BD 2025-06-14'!$B$1:$B$700) -> CARDONA HERNANDEZ IVAN FELIPE
A21: 12 | B21: 1107102399 | C21: ZAMBRANO MONTOYA OSCAR ANDRES | D21: =IFERROR(VLOOKUP(B21,#REF!,6,0),"ACTIVO") -> ACTIVO | E21: 43759 | F21: =IFERROR(VLOOKUP(B21,#REF!,5,0),"") | G21: 35338 | H21: =+YEARFRAC(G21,TODAY(),1) -> 29.499691 | I21: Masculino | J21: ozambrano@gane.com.co | K21: ANALISTA DE MONITOREO | L21: OPERACIONES TIC | M21: TIC | N21: NO | O21: NO | P21: No tiene | AB21: =IF(AD21<=TODAY(),"Vencida","Vigente") -> Vencida | AC21: =IF(P21="No tiene","No aplica",IF(AD21>$C$6,"Vigente","No Vigente")) -> No aplica | AE21: =IF(AG21<=TODAY(),"Vencida","Vigente") -> Vencida | AF21: =+IF(P21="No tiene","No aplica",IF(AG21>$C$6,"Vigente","No Vigente")) -> No aplica | AK21: =+IF(P21="No tiene","No aplica",IF(AJ21>$C$6,"Vigente","No Vigente")) -> No aplica | AM21: =+COUNTIFS(AC21:AK21,"Vigente") -> 0 | AQ21: =+_xlfn.XLOOKUP(B21,'BD 2025-06-14'!$A$1:$A$700,'BD 2025-06-14'!$B$1:$B$700) -> ZAMBRANO MONTOYA OSCAR ANDRES
... A23: 14 | B23: 1143926109 | C23: MENA MOSQUERA CRISTIAN MARLON | D23: =IFERROR(VLOOKUP(B23,#REF!,6,0),"ACTIVO") -> ACTIVO | E23: 44789 | F23: =IFERROR(VLOOKUP(B23,#REF!,5,0),"") | G23: 32599 | H23: =+YEARFRAC(G23,TODAY(),1) -> 37.000648 | I23: Masculino | J23: cmmena@gane.com.co | K23: ANALISTA DE MONITOREO | L23: OPERACIONES TIC | M23: TIC | N23: NO | O23: NO | P23: No tiene | AB23: =IF(AD23<=TODAY(),"Vencida","Vigente") -> Vencida | AC23: =IF(P23="No tiene","No aplica",IF(AD23>$C$6,"Vigente","No Vigente")) -> No aplica | AE23: =IF(AG23<=TODAY(),"Vencida","Vigente") -> Vencida | AF23: =+IF(P23="No tiene","No aplica",IF(AG23>$C$6,"Vigente","No Vigente")) -> No aplica | AK23: =+IF(P23="No tiene","No aplica",IF(AJ23>$C$6,"Vigente","No Vigente")) -> No aplica | AM23: =+COUNTIFS(AC23:AK23,"Vigente") -> 0 | AQ23: =+_xlfn.XLOOKUP(B23,'BD 2025-06-14'!$A$1:$A$700,'BD 2025-06-14'!$B$1:$B$700) -> MENA MOSQUERA CRISTIAN MARLON
A24: 15 | B24: 4883086 | C24: TORRES MEJIA CARLOS | D24: =IFERROR(VLOOKUP(B24,#REF!,6,0),"ACTIVO") -> ACTIVO | E24: 42128 | F24: =IFERROR(VLOOKUP(B24,#REF!,5,0),"") | G24: 24327 | H24: =+YEARFRAC(G24,TODAY(),1) -> 59.647487 | I24: Masculino | J24: ctorres@gane.com.co | K24: ANALISTA DE SEGURIDAD | L24: SEGURIDAD | M24: ADMINISTRATIVO | N24: SI | O24: SI | P24: Moto | Q24: TFK64G | R24: Si | U24: 9FMKC3591RF000988 | V24: KC35E-A-3044394 | W24: 2024 | X24: HONDA | Y24: 162 | AA24: 45138 | AB24: =IF(AD24<=TODAY(),"Vencida","Vigente") -> Vigente | AC24: =IF(P24="No tiene","No aplica",IF(AD24>$C$6,"Vigente","No Vigente")) -> Vigente | AD24: 46229 | AE24: =IF(AG24<=TODAY(),"Vencida","Vigente") -> Vigente | AF24: =+IF(P24="No tiene","No aplica",IF(AG24>$C$6,"Vigente","No Vigente")) -> Vigente | AG24: 46230 | AH24: A2 | AI24: A2 (09/05/2032) B1 (24/01/2024) C1 (29/04/2017) | AJ24: 48343 | AK24: =+IF(P24="No tiene","No aplica",IF(AJ24>$C$6,"Vigente","No Vigente")) -> Vigente | AM24: =+COUNTIFS(AC24:AK24,"Vigente") -> 4 | AP24: Debe expedir RTM a los 2 años a partir de la fecha de matricula 31/07/2023 | AQ24: =+_xlfn.XLOOKUP(B24,'BD 2025-06-14'!$A$1:$A$700,'BD 2025-06-14'!$B$1:$B$700) -> TORRES MEJIA CARLOS
A25: 16 | B25: 16843161 | C25: RODRIGUEZ OSPINA IVAN ANDRES | D25: =IFERROR(VLOOKUP(B25,#REF!,6,0),"ACTIVO") -> ACTIVO | E25: 43306 | F25: =IFERROR(VLOOKUP(B25,#REF!,5,0),"") | G25: 29863 | H25: =+YEARFRAC(G25,TODAY(),1) -> 44.491399 | I25: Masculino | J25: iarodriguez@gane.com.co | K25: ANALISTA DE SEGURIDAD | L25: SEGURIDAD | M25: ADMINISTRATIVO | N25: SI | O25: SI | P25: Moto | Q25: CNM60H | R25: No | S25: OSSA LASSO MARIA ALEJANDRA | T25: 1113522508 | U25: 9GJB37PF7SP030555 | V25: PFXWRL53980 | W25: 2025 | X25: BAJAJ | Y25: 102 | AA25: 45450 | AB25: =IF(AD25<=TODAY(),"Vencida","Vigente") -> Vigente | AC25: =IF(P25="No tiene","No aplica",IF(AD25>$C$6,"Vigente","No Vigente")) -> Vigente | AD25: 46180 | AE25: =IF(AG25<=TODAY(),"Vencida","Vigente") -> Vigente | AF25: =+IF(P25="No tiene","No aplica",IF(AG25>$C$6,"Vigente","No Vigente")) -> Vigente | AG25: 46179 | AH25: A2 | AI25: B1 27/12/2027 | AJ25: 49007 | AK25: =+IF(P25="No tiene","No aplica",IF(AJ25>$C$6,"Vigente","No Vigente")) -> Vigente | AM25: =+COUNTIFS(AC25:AK25,"Vigente") -> 4 | AP25: Debe expedir RTM a los 2 años a partir de la fecha de matricula 07/06/2024 | AQ25: =+_xlfn.XLOOKUP(B25,'BD 2025-06-14'!$A$1:$A$700,'BD 2025-06-14'!$B$1:$B$700) -> RODRIGUEZ OSPINA IVAN ANDRES
A26: 17 | B26: 1108645085 | C26: ROJAS LAMPREA GABRIELA | D26: =IFERROR(VLOOKUP(B26,#REF!,6,0),"ACTIVO") -> ACTIVO | E26: 45476 | F26: =IFERROR(VLOOKUP(B26,#REF!,5,0),"") | G26: 39894 | H26: =+YEARFRAC(G26,TODAY(),1) -> 17.027989 | I26: Femenino | J26: grojas@gane.com.co | K26: APRENDIZ SENA | L26: LOGISTICA | M26: ADMINISTRATIVO | N26: NO | O26: NO | P26: No tiene | AB26: =IF(AD26<=TODAY(),"Vencida","Vigente") -> Vencida | AC26: =IF(P26="No tiene","No aplica",IF(AD26>$C$6,"Vigente","No Vigente")) -> No aplica | AE26: =IF(AG26<=TODAY(),"Vencida","Vigente") -> Vencida | AF26: =+IF(P26="No tiene","No aplica",IF(AG26>$C$6,"Vigente","No Vigente")) -> No aplica | AK26: =+IF(P26="No tiene","No aplica",IF(AJ26>$C$6,"Vigente","No Vigente")) -> No aplica | AM26: =+COUNTIFS(AC26:AK26,"Vigente") -> 0 | AQ26: =+_xlfn.XLOOKUP(B26,'BD 2025-06-14'!$A$1:$A$700,'BD 2025-06-14'!$B$1:$B$700) -> ROJAS LAMPREA GABRIELA
A27: 18 | B27: 1144105721 | C27: MONTENEGRO TRUQUE CAROLINA | D27: =IFERROR(VLOOKUP(B27,#REF!,6,0),"ACTIVO") -> ACTIVO | E27: 45516 | F27: =IFERROR(VLOOKUP(B27,#REF!,5,0),"") | G27: 36149 | H27: =+YEARFRAC(G27,TODAY(),1) -> 27.280589 | I27: Femenino | J27: cmontenegro@gane.com.co | K27: APRENDIZ SENA | L27: OPERACIONES COMERCIALES | M27: COMERCIAL | N27: NO | O27: NO | P27: No tiene | AB27: =IF(AD27<=TODAY(),"Vencida","Vigente") -> Vencida | AC27: =IF(P27="No tiene","No aplica",IF(AD27>$C$6,"Vigente","No Vigente")) -> No aplica | AE27: =IF(AG27<=TODAY(),"Vencida","Vigente") -> Vencida | AF27: =+IF(P27="No tiene","No aplica",IF(AG27>$C$6,"Vigente","No Vigente")) -> No aplica | AK27: =+IF(P27="No tiene","No aplica",IF(AJ27>$C$6,"Vigente","No Vigente")) -> No aplica | AM27: =+COUNTIFS(AC27:AK27,"Vigente") -> 0 | AQ27: =+_xlfn.XLOOKUP(B27,'BD 2025-06-14'!$A$1:$A$700,'BD 2025-06-14'!$B$1:$B$700) -> MONTENEGRO TRUQUE CAROLINA
A28: 19 | B28: 1111547929 | C28: ARANGO VELASQUEZ KEVIN GABRIEL | D28: =IFERROR(VLOOKUP(B28,#REF!,6,0),"ACTIVO") -> ACTIVO | E28: 45537 | F28: =IFERROR(VLOOKUP(B28,#REF!,5,0),"") | G28: 39724 | H28: =+YEARFRAC(G28,TODAY(),1) -> 17.491499 | I28: Masculino | J28: kgarango@gane.com.co | K28: APRENDIZ SENA | L28: OPERACIONES COMERCIALES | M28: COMERCIAL | N28: NO | O28: NO | P28: No tiene | AB28: =IF(AD28<=TODAY(),"Vencida","Vigente") -> Vencida | AC28: =IF(P28="No tiene","No aplica",IF(AD28>$C$6,"Vigente","No Vigente")) -> No aplica | AE28: =IF(AG28<=TODAY(),"Vencida","Vigente") -> Vencida | AF28: =+IF(P28="No tiene","No aplica",IF(AG28>$C$6,"Vigente","No Vigente")) -> No aplica | AK28: =+IF(P28="No tiene","No aplica",IF(AJ28>$C$6,"Vigente","No Vigente")) -> No aplica | AM28: =+COUNTIFS(AC28:AK28,"Vigente") -> 0 | AQ28: =+_xlfn.XLOOKUP(B28,'BD 2025-06-14'!$A$1:$A$700,'BD 2025-06-14'!$B$1:$B$700) -> ARANGO VELASQUEZ KEVIN GABRIEL
A29: 20 | B29: 1109671237 | C29: ZORNOSA GALLO SAMANTHA | D29: =IFERROR(VLOOKUP(B29,#REF!,6,0),"ACTIVO") -> ACTIVO | E29: 45544 | F29: =IFERROR(VLOOKUP(B29,#REF!,5,0),"") | G29: 39815 | H29: =+YEARFRAC(G29,TODAY(),1) -> 17.244296 | I29: Femenino | J29: szgallo@gane.com.co | K29: APRENDIZ SENA | L29: OPERACIONES COMERCIALES | M29: COMERCIAL | N29: NO | O29: NO | P29: No tiene | AB29: =IF(AD29<=TODAY(),"Vencida","Vigente") -> Vencida | AC29: =IF(P29="No tiene","No aplica",IF(AD29>$C$6,"Vigente","No Vigente")) -> No aplica | AE29: =IF(AG29<=TODAY(),"Vencida","Vigente") -> Vencida | AF29: =+IF(P29="No tiene","No aplica",IF(AG29>$C$6,"Vigente","No Vigente")) -> No aplica | AK29: =+IF(P29="No tiene","No aplica",IF(AJ29>$C$6,"Vigente","No Vigente")) -> No aplica | AM29: =+COUNTIFS(AC29:AK29,"Vigente") -> 0 | AQ29: =+_xlfn.XLOOKUP(B29,'BD 2025-06-14'!$A$1:$A$700,'BD 2025-06-14'!$B$1:$B$700) -> ZORNOSA GALLO SAMANTHA
A30: 21 | B30: 1108644972 | C30: ROJAS SAAVEDRA NATALIA | D30: =IFERROR(VLOOKUP(B30,#REF!,6,0),"ACTIVO") -> ACTIVO | E30: 45551 | F30: =IFERROR(VLOOKUP(B30,#REF!,5,0),"") | G30: 39934 | H30: =+YEARFRAC(G30,TODAY(),1) -> 16.918467 | I30: Femenino | J30: nrojas@gane.com.co | K30: APRENDIZ SENA | L30: OPERACIONES COMERCIALES | M30: COMERCIAL | N30: NO | O30: NO | P30: No tiene | AB30: =IF(AD30<=TODAY(),"Vencida","Vigente") -> Vencida | AC30: =IF(P30="No tiene","No aplica",IF(AD30>$C$6,"Vigente","No Vigente")) -> No aplica | AE30: =IF(AG30<=TODAY(),"Vencida","Vigente") -> Vencida | AF30: =+IF(P30="No tiene","No aplica",IF(AG30>$C$6,"Vigente","No Vigente")) -> No aplica | AK30: =+IF(P30="No tiene","No aplica",IF(AJ30>$C$6,"Vigente","No Vigente")) -> No aplica | AM30: =+COUNTIFS(AC30:AK30,"Vigente") -> 0 | AQ30: =+_xlfn.XLOOKUP(B30,'BD 2025-06-14'!$A$1:$A$700,'BD 2025-06-14'!$B$1:$B$700) -> ROJAS SAAVEDRA NATALIA
A31: 22 | B31: 1109187542 | C31: MINA CORDOBA MARIA CAMILA | D31: =IFERROR(VLOOKUP(B31,#REF!,6,0),"ACTIVO") -> ACTIVO | E31: 45551 | F31: =IFERROR(VLOOKUP(B31,#REF!,5,0),"") | G31: 38980 | H31: =+YEARFRAC(G31,TODAY(),1) -> 19.529726 | I31: Femenino | J31: mcmina@gane.com.co | K31: APRENDIZ SENA | L31: OPERACIONES COMERCIALES | M31: COMERCIAL | N31: NO | O31: NO | P31: No tiene | AB31: =IF(AD31<=TODAY(),"Vencida","Vigente") -> Vencida | AC31: =IF(P31="No tiene","No aplica",IF(AD31>$C$6,"Vigente","No Vigente")) -> No aplica | AE31: =IF(AG31<=TODAY(),"Vencida","Vigente") -> Vencida | AF31: =+IF(P31="No tiene","No aplica",IF(AG31>$C$6,"Vigente","No Vigente")) -> No aplica | AK31: =+IF(P31="No tiene","No aplica",IF(AJ31>$C$6,"Vigente","No Vigente")) -> No aplica | AM31: =+COUNTIFS(AC31:AK31,"Vigente") -> 0 | AQ31: =+_xlfn.XLOOKUP(B31,'BD 2025-06-14'!$A$1:$A$700,'BD 2025-06-14'!$B$1:$B$700) -> MINA CORDOBA MARIA CAMILA
A32: 23 | B32: 1110294638 | C32: ARCE SANCHEZ GELEN DAYAN | D32: =IFERROR(VLOOKUP(B32,#REF!,6,0),"ACTIVO") -> ACTIVO | E32: 45551 | F32: =IFERROR(VLOOKUP(B32,#REF!,5,0),"") | G32: 39320 | H32: =+YEARFRAC(G32,TODAY(),1) -> 18.59822 | I32: Femenino | J32: gdarce@gane.com.co | K32: APRENDIZ SENA | L32: LOGISTICA | M32: ADMINISTRATIVO | N32: NO | O32: NO | P32: No tiene | AB32: =IF(AD32<=TODAY(),"Vencida","Vigente") -> Vencida | AC32: =IF(P32="No tiene","No aplica",IF(AD32>$C$6,"Vigente","No Vigente")) -> No aplica | AE32: =IF(AG32<=TODAY(),"Vencida","Vigente") -> Vencida | AF32: =+IF(P32="No tiene","No aplica",IF(AG32>$C$6,"Vigente","No Vigente")) -> No aplica | AK32: =+IF(P32="No tiene","No aplica",IF(AJ32>$C$6,"Vigente","No Vigente")) -> No aplica | AM32: =+COUNTIFS(AC32:AK32,"Vigente") -> 0 | AQ32: =+_xlfn.XLOOKUP(B32,'BD 2025-06-14'!$A$1:$A$700,'BD 2025-06-14'!$B$1:$B$700) -> ARCE SANCHEZ GELEN DAYAN
A33: 24 | B33: 1059840437 | C33: FRANKLY RIVERA KENER DANIEL | D33: =IFERROR(VLOOKUP(B33,#REF!,6,0),"ACTIVO") -> ACTIVO | E33: 45588 | F33: =IFERROR(VLOOKUP(B33,#REF!,5,0),"") | G33: 38144 | H33: =+YEARFRAC(G33,TODAY(),1) -> 21.817284 | I33: Masculino | J33: kdfranfly@gane.com.co | K33: APRENDIZ SENA | L33: MERCADEO | M33: COMERCIAL | N33: NO | O33: NO | P33: No tiene | AB33: =IF(AD33<=TODAY(),"Vencida","Vigente") -> Vencida | AC33: =IF(P33="No tiene","No aplica",IF(AD33>$C$6,"Vigente","No Vigente")) -> No aplica | AE33: =IF(AG33<=TODAY(),"Vencida","Vigente") -> Vencida | AF33: =+IF(P33="No tiene","No aplica",IF(AG33>$C$6,"Vigente","No Vigente")) -> No aplica | AK33: =+IF(P33="No tiene","No aplica",IF(AJ33>$C$6,"Vigente","No Vigente")) -> No aplica | AM33: =+COUNTIFS(AC33:AK33,"Vigente") -> 0 | AQ33: =+_xlfn.XLOOKUP(B33,'BD 2025-06-14'!$A$1:$A$700,'BD 2025-06-14'!$B$1:$B$700) -> FRANKLY RIVERA KENER DANIEL
A34: 25 | B34: 1110045753 | C34: VARGAS RUBIO SOFIA | D34: =IFERROR(VLOOKUP(B34,#REF!,6,0),"ACTIVO") -> ACTIVO | E34: 45601 | F34: =IFERROR(VLOOKUP(B34,#REF!,5,0),"") | G34: 39650 | H34: =+YEARFRAC(G34,TODAY(),1) -> 17.694092 | I34: Femenino | J34: svargas@gane.com.co | K34: APRENDIZ SENA | L34: OPERACIONES COMERCIALES | M34: COMERCIAL | N34: NO | O34: NO | P34: No tiene | AB34: =IF(AD34<=TODAY(),"Vencida","Vigente") -> Vencida | AC34: =IF(P34="No tiene","No aplica",IF(AD34>$C$6,"Vigente","No Vigente")) -> No aplica | AE34: =IF(AG34<=TODAY(),"Vencida","Vigente") -> Vencida | AF34: =+IF(P34="No tiene","No aplica",IF(AG34>$C$6,"Vigente","No Vigente")) -> No aplica | AK34: =+IF(P34="No tiene","No aplica",IF(AJ34>$C$6,"Vigente","No Vigente")) -> No aplica | AM34: =+COUNTIFS(AC34:AK34,"Vigente") -> 0 | AQ34: =+_xlfn.XLOOKUP(B34,'BD 2025-06-14'!$A$1:$A$700,'BD 2025-06-14'!$B$1:$B$700) -> VARGAS RUBIO SOFIA
A35: 26 | B35: 7159169 | C35: LOPEZ BRICENO EMILIO ANTONIO | D35: =IFERROR(VLOOKUP(B35,#REF!,6,0),"ACTIVO") -> ACTIVO | E35: 45601 | F35: =IFERROR(VLOOKUP(B35,#REF!,5,0),"") | G35: 39470 | H35: =+YEARFRAC(G35,TODAY(),1) -> 18.186888 | I35: Masculino | J35: elopez@gane.com.co | K35: APRENDIZ SENA | L35: OPERACIONES COMERCIALES | M35: COMERCIAL | N35: NO | O35: NO | P35: No tiene | AB35: =IF(AD35<=TODAY(),"Vencida","Vigente") -> Vencida | AC35: =IF(P35="No tiene","No aplica",IF(AD35>$C$6,"Vigente","No Vigente")) -> No aplica | AE35: =IF(AG35<=TODAY(),"Vencida","Vigente") -> Vencida | AF35: =+IF(P35="No tiene","No aplica",IF(AG35>$C$6,"Vigente","No Vigente")) -> No aplica | AK35: =+IF(P35="No tiene","No aplica",IF(AJ35>$C$6,"Vigente","No Vigente")) -> No aplica | AM35: =+COUNTIFS(AC35:AK35,"Vigente") -> 0 | AQ35: =+_xlfn.XLOOKUP(B35,'BD 2025-06-14'!$A$1:$A$700,'BD 2025-06-14'!$B$1:$B$700) -> LOPEZ BRICENO EMILIO ANTONIO
A36: 27 | B36: 1111548805 | C36: MUNOZ MEDINA JUAN DAVID | D36: =IFERROR(VLOOKUP(B36,#REF!,6,0),"ACTIVO") -> ACTIVO | E36: 45604 | F36: =IFERROR(VLOOKUP(B36,#REF!,5,0),"") | G36: 39954 | H36: =+YEARFRAC(G36,TODAY(),1) -> 16.863706 | I36: Masculino | J36: jdmuðoz@gane.com.co | K36: APRENDIZ SENA | L36: TESORERIA | M36: FINANCIERO | N36: NO | O36: NO | P36: No tiene | AB36: =IF(AD36<=TODAY(),"Vencida","Vigente") -> Vencida | AC36: =IF(P36="No tiene","No aplica",IF(AD36>$C$6,"Vigente","No Vigente")) -> No aplica | AE36: =IF(AG36<=TODAY(),"Vencida","Vigente") -> Vencida | AF36: =+IF(P36="No tiene","No aplica",IF(AG36>$C$6,"Vigente","No Vigente")) -> No aplica | AK36: =+IF(P36="No tiene","No aplica",IF(AJ36>$C$6,"Vigente","No Vigente")) -> No aplica | AM36: =+COUNTIFS(AC36:AK36,"Vigente") -> 0 | AQ36: =+_xlfn.XLOOKUP(B36,'BD 2025-06-14'!$A$1:$A$700,'BD 2025-06-14'!$B$1:$B$700) -> MUNOZ MEDINA JUAN DAVID
A37: 28 | B37: 1111659067 | C37: SINISTERRA RIASCOS MELISSA | D37: =IFERROR(VLOOKUP(B37,#REF!,6,0),"ACTIVO") -> ACTIVO | E37: 45621 | F37: =IFERROR(VLOOKUP(B37,#REF!,5,0),"") | G37: 36923 | H37: =+YEARFRAC(G37,TODAY(),1) -> 25.162174 | I37: Femenino | J37: msinisterra@gane.com.co | K37: APRENDIZ SENA | L37: TESORERIA | M37: FINANCIERO | N37: NO | O37: NO | P37: No tiene | AB37: =IF(AD37<=TODAY(),"Vencida","Vigente") -> Vencida | AC37: =IF(P37="No tiene","No aplica",IF(AD37>$C$6,"Vigente","No Vigente")) -> No aplica | AE37: =IF(AG37<=TODAY(),"Vencida","Vigente") -> Vencida | AF37: =+IF(P37="No tiene","No aplica",IF(AG37>$C$6,"Vigente","No Vigente")) -> No aplica | AK37: =+IF(P37="No tiene","No aplica",IF(AJ37>$C$6,"Vigente","No Vigente")) -> No aplica | AM37: =+COUNTIFS(AC37:AK37,"Vigente") -> 0 | AQ37: =+_xlfn.XLOOKUP(B37,'BD 2025-06-14'!$A$1:$A$700,'BD 2025-06-14'!$B$1:$B$700) -> SINISTERRA RIASCOS MELISSA
... A67: 58 | B67: 1023026154 | C67: RAMIREZ CHACON INGRID GINETH | D67: =IFERROR(VLOOKUP(B67,#REF!,6,0),"ACTIVO") -> ACTIVO | E67: 45187 | F67: =IFERROR(VLOOKUP(B67,#REF!,5,0),"") | G67: 35728 | H67: =+YEARFRAC(G67,TODAY(),1) -> 28.433878 | I67: Femenino | J67: igramirez@gane.com.co | K67: ASESOR DE CARTERA | L67: TESORERIA | M67: FINANCIERO | N67: NO | O67: NO | P67: No tiene | AB67: =IF(AD67<=TODAY(),"Vencida","Vigente") -> Vencida | AC67: =IF(P67="No tiene","No aplica",IF(AD67>$C$6,"Vigente","No Vigente")) -> No aplica | AE67: =IF(AG67<=TODAY(),"Vencida","Vigente") -> Vencida | AF67: =+IF(P67="No tiene","No aplica",IF(AG67>$C$6,"Vigente","No Vigente")) -> No aplica | AK67: =+IF(P67="No tiene","No aplica",IF(AJ67>$C$6,"Vigente","No Vigente")) -> No aplica | AM67: =+COUNTIFS(AC67:AK67,"Vigente") -> 0 | AQ67: =+_xlfn.XLOOKUP(B67,'BD 2025-06-14'!$A$1:$A$700,'BD 2025-06-14'!$B$1:$B$700) -> RAMIREZ CHACON INGRID GINETH
A68: 59 | B68: 1130590251 | C68: PRADA VILLA EDGAR HERNAN | D68: =IFERROR(VLOOKUP(B68,#REF!,6,0),"ACTIVO") -> ACTIVO | E68: 45614 | F68: =IFERROR(VLOOKUP(B68,#REF!,5,0),"") | G68: 31704 | H68: =+YEARFRAC(G68,TODAY(),1) -> 39.450351 | I68: Masculino | J68: ehprada@gane.com.co | K68: ASESOR DE VENTAS - BETPLAY | L68: LINEA DE NEGOCIOS | M68: COMERCIAL | N68: SI | O68: SI | P68: Moto | Q68: IWH85C | R68: No | S68: Lopez Javier | T68: 14835665 | U68: 9FMPCG62XBF006325 | V68: SDH150FMG-2A*A5807995* | W68: 2011 | X68: HONDA | Y68: 97 | AA68: 40637 | AB68: =IF(AD68<=TODAY(),"Vencida","Vigente") -> Vencida | AC68: =IF(P68="No tiene","No aplica",IF(AD68>$C$6,"Vigente","No Vigente")) -> Vigente | AD68: 46049 | AE68: =IF(AG68<=TODAY(),"Vencida","Vigente") -> Vencida | AF68: =+IF(P68="No tiene","No aplica",IF(AG68>$C$6,"Vigente","No Vigente")) -> Vigente | AG68: 46040 | AH68: A2 | AI68: A2 | AJ68: 48982 | AK68: =+IF(P68="No tiene","No aplica",IF(AJ68>$C$6,"Vigente","No Vigente")) -> Vigente | AM68: =+COUNTIFS(AC68:AK68,"Vigente") -> 3 | AQ68: =+_xlfn.XLOOKUP(B68,'BD 2025-06-14'!$A$1:$A$700,'BD 2025-06-14'!$B$1:$B$700) -> PRADA VILLA EDGAR HERNAN
A69: 60 | B69: 1130658285 | C69: FIGUEROA DELGADO RODOLFO | D69: =IFERROR(VLOOKUP(B69,#REF!,6,0),"ACTIVO") -> ACTIVO | E69: 45748 | F69: =IFERROR(VLOOKUP(B69,#REF!,5,0),"") | G69: 32115 | H69: =+YEARFRAC(G69,TODAY(),1) -> 38.324435 | I69: Masculino | J69: rfigueroa@gane.com.co | K69: ASESOR DE VENTAS - BETPLAY | L69: LINEA DE NEGOCIOS | M69: COMERCIAL | N69: SI | O69: SI | P69: Moto | Q69: KLN45F | R69: Si | U69: 9F2C11257M5003756 | V69: ZS154FMI-38M103618 | W69: 2021 | X69: AKT | Y69: 124 | AA69: 44074 | AB69: =IF(AD69<=TODAY(),"Vencida","Vigente") -> Vencida | AC69: =IF(P69="No tiene","No aplica",IF(AD69>$C$6,"Vigente","No Vigente")) -> Vigente | AD69: 46018 | AE69: =IF(AG69<=TODAY(),"Vencida","Vigente") -> Vencida | AF69: =+IF(P69="No tiene","No aplica",IF(AG69>$C$6,"Vigente","No Vigente")) -> Vigente | AG69: 46018 | AH69: A2 | AI69: A2 (02/11/2032) B2 (24/04/2030) C2 (24/07/2023) | AJ69: 48520 | AK69: =+IF(P69="No tiene","No aplica",IF(AJ69>$C$6,"Vigente","No Vigente")) -> Vigente | AM69: =+COUNTIFS(AC69:AK69,"Vigente") -> 3 | AQ69: =+_xlfn.XLOOKUP(B69,'BD 2025-06-14'!$A$1:$A$700,'BD 2025-06-14'!$B$1:$B$700) -> FIGUEROA DELGADO RODOLFO
A70: 61 | B70: 79849153 | C70: RODRIGUEZ VELASQUEZ JOHN MANUEL | D70: =IFERROR(VLOOKUP(B70,#REF!,6,0),"ACTIVO") -> ACTIVO | E70: 40371 | F70: =IFERROR(VLOOKUP(B70,#REF!,5,0),"") | G70: 27724 | H70: =+YEARFRAC(G70,TODAY(),1) -> 50.346338 | I70: Masculino | J70: jmrodriguez@gane.com.co | K70: ASESOR DE VENTAS - GIROS, PAGOS, RECARGAS | L70: LINEA DE NEGOCIOS | M70: COMERCIAL | N70: SI | O70: SI | P70: Moto | Q70: PRM41G | R70: Si | U70: LC6JCK4P3P0026077 | V70: 157FMJ-3*G2U57080* | W70: 2023 | X70: Suzuki | Y70: 149 | AA70: 45020 | AB70: =IF(AD70<=TODAY(),"Vencida","Vigente") -> Vencida | AC70: =IF(P70="No tiene","No aplica",IF(AD70>$C$6,"Vigente","No Vigente")) -> Vigente | AD70: 46113 | AE70: =IF(AG70<=TODAY(),"Vencida","Vigente") -> Vencida | AF70: =+IF(P70="No tiene","No aplica",IF(AG70>$C$6,"Vigente","No Vigente")) -> Vigente | AG70: 46113 | AH70: A2 | AI70: A2 | AJ70: 49144 | AK70: =+IF(P70="No tiene","No aplica",IF(AJ70>$C$6,"Vigente","No Vigente")) -> Vigente | AM70: =+COUNTIFS(AC70:AK70,"Vigente") -> 3 | AP70: Moto nueva, debe expedir RTM a los 2 años a partir de la fecha de matricula 4/4/2023 | AQ70: =+_xlfn.XLOOKUP(B70,'BD 2025-06-14'!$A$1:$A$700,'BD 2025-06-14'!$B$1:$B$700) -> RODRIGUEZ VELASQUEZ JOHN MANUEL
A71: 62 | B71: 67038967 | C71: SANCHEZ GUTIERREZ ANGEL | D71: =IFERROR(VLOOKUP(B71,#REF!,6,0),"ACTIVO") -> ACTIVO | E71: 41535 | F71: =IFERROR(VLOOKUP(B71,#REF!,5,0),"") | G71: 31309 | H71: =+YEARFRAC(G71,TODAY(),1) -> 40.532464 | I71: Masculino | J71: asanchez@gane.com.co | K71: ASESOR DE VENTAS - GIROS, PAGOS, RECARGAS | L71: LINEA DE NEGOCIOS | M71: COMERCIAL | N71: SI | O71: SI | P71: Moto | Q71: QXP04H | R71: Si | U71: ME4MC5690SA014988 | V71: MC56E2028289 | W71: 2025 | X71: HONDA | Y71: 184 | AA71: 45882 | AB71: =IF(AD71<=TODAY(),"Vencida","Vigente") -> Vigente | AC71: =IF(P71="No tiene","No aplica",IF(AD71>$C$6,"Vigente","No Vigente")) -> Vigente | AD71: 46612 | AE71: =IF(AG71<=TODAY(),"Vencida","Vigente") -> Vigente | AF71: =+IF(P71="No tiene","No aplica",IF(AG71>$C$6,"Vigente","No Vigente")) -> Vigente | AG71: 46246 | AH71: A2 | AI71: A2 | AJ71: 48898 | AK71: =+IF(P71="No tiene","No aplica",IF(AJ71>$C$6,"Vigente","No Vigente")) -> Vigente | AM71: =+COUNTIFS(AC71:AK71,"Vigente") -> 4 | AP71: Reporta cambio de moto el dia 11/12/2025 | AQ71: =+_xlfn.XLOOKUP(B71,'BD 2025-06-14'!$A$1:$A$700,'BD 2025-06-14'!$B$1:$B$700) -> SANCHEZ GUTIERREZ ANGEL
A72: 63 | B72: 1144070871 | C72: ROMAN OCAMPO MILDREY | D72: =IFERROR(VLOOKUP(B72,#REF!,6,0),"ACTIVO") -> ACTIVO | E72: 42888 | F72: =IFERROR(VLOOKUP(B72,#REF!,5,0),"") | G72: 34486 | H72: =+YEARFRAC(G72,TODAY(),1) -> 31.833651 | I72: Femenino | J72: mroman@gane.com.co | K72: ASESOR DE VENTAS - GIROS, PAGOS, RECARGAS | L72: LINEA DE NEGOCIOS | M72: COMERCIAL | N72: SI | O72: SI | P72: Moto | Q72: KLO34E | R72: Si | U72: 9FLU62013HCJ51394 | V72: KN25SR2241927 | W72: 2017 | X72: Kymco | Y72: 125 | AA72: 42788 | AB72: =IF(AD72<=TODAY(),"Vencida","Vigente") -> Vigente | AC72: =IF(P72="No tiene","No aplica",IF(AD72>$C$6,"Vigente","No Vigente")) -> Vigente | AD72: 46236 | AE72: =IF(AG72<=TODAY(),"Vencida","Vigente") -> Vigente | AF72: =+IF(P72="No tiene","No aplica",IF(AG72>$C$6,"Vigente","No Vigente")) -> Vigente | AG72: 46236 | AH72: A2 | AI72: A2 | AJ72: 46448 | AK72: =+IF(P72="No tiene","No aplica",IF(AJ72>$C$6,"Vigente","No Vigente")) -> Vigente | AM72: =+COUNTIFS(AC72:AK72,"Vigente") -> 4 | AQ72: =+_xlfn.XLOOKUP(B72,'BD 2025-06-14'!$A$1:$A$700,'BD 2025-06-14'!$B$1:$B$700) -> ROMAN OCAMPO MILDREY
A73: 64 | B73: 1085687299 | C73: HINESTROZA TORRES BENYI CRISTINA | D73: =IFERROR(VLOOKUP(B73,#REF!,6,0),"ACTIVO") -> ACTIVO | E73: 43172 | F73: =IFERROR(VLOOKUP(B73,#REF!,5,0),"") | G73: 32314 | H73: =+YEARFRAC(G73,TODAY(),1) -> 37.77894 | I73: Femenino | J73: bchinestroza@gane.com.co | K73: ASESOR DE VENTAS - GIROS, PAGOS, RECARGAS | L73: LINEA DE NEGOCIOS | M73: COMERCIAL | N73: SI | O73: SI | P73: Moto | Q73: UEH77F | R73: Si | U73: 9GFXCJTC1NCE03628 | V73: 1P53FMIHM1179586 | W73: 2022 | X73: Victory | Y73: 125 | AA73: 44383 | AB73: =IF(AD73<=TODAY(),"Vencida","Vigente") -> Vigente | AC73: =IF(P73="No tiene","No aplica",IF(AD73>$C$6,"Vigente","No Vigente")) -> Vigente | AD73: 46208 | AE73: =IF(AG73<=TODAY(),"Vencida","Vigente") -> Vigente | AF73: =+IF(P73="No tiene","No aplica",IF(AG73>$C$6,"Vigente","No Vigente")) -> Vigente | AG73: 46231 | AH73: A2 | AI73: A2 | AJ73: 48773 | AK73: =+IF(P73="No tiene","No aplica",IF(AJ73>$C$6,"Vigente","No Vigente")) -> Vigente | AM73: =+COUNTIFS(AC73:AK73,"Vigente") -> 4 | AQ73: =+_xlfn.XLOOKUP(B73,'BD 2025-06-14'!$A$1:$A$700,'BD 2025-06-14'!$B$1:$B$700) -> HINESTROZA TORRES BENYI CRISTINA
A74: 65 | B74: 1113641054 | C74: MAZO SALAS LINA MARCELA | D74: =IFERROR(VLOOKUP(B74,#REF!,6,0),"ACTIVO") -> ACTIVO | E74: 43370 | F74: =IFERROR(VLOOKUP(B74,#REF!,5,0),"") | G74: 32710 | H74: =+YEARFRAC(G74,TODAY(),1) -> 36.696736 | I74: Femenino | J74: lmmazo@gane.com.co | K74: ASESOR DE VENTAS - GIROS, PAGOS, RECARGAS | L74: LINEA DE NEGOCIOS | M74: COMERCIAL | N74: SI | O74: SI | P74: Moto | Q74: YTI12G | R74: Si | U74: 9FLB3A1H8REA16023 | V74: 0H2FP1301595 | W74: 2024 | X74: TVS | Y74: 109 | AA74: 45330 | AB74: =IF(AD74<=TODAY(),"Vencida","Vigente") -> Vencida | AC74: =IF(P74="No tiene","No aplica",IF(AD74>$C$6,"Vigente","No Vigente")) -> Vigente | AD74: 46061 | AE74: =IF(AG74<=TODAY(),"Vencida","Vigente") -> Vencida | AF74: =+IF(P74="No tiene","No aplica",IF(AG74>$C$6,"Vigente","No Vigente")) -> Vigente | AG74: 46060 | AH74: A2 | AI74: A2 | AJ74: 48097 | AK74: =+IF(P74="No tiene","No aplica",IF(AJ74>$C$6,"Vigente","No Vigente")) -> Vigente | AM74: =+COUNTIFS(AC74:AK74,"Vigente") -> 3 | AP74: Cambió de moto | AQ74: =+_xlfn.XLOOKUP(B74,'BD 2025-06-14'!$A$1:$A$700,'BD 2025-06-14'!$B$1:$B$700) -> MAZO SALAS LINA MARCELA
A75: 66 | B75: 1130638562 | C75: QUINTERO SOLARTE DIANA CAROLINA | D75: =IFERROR(VLOOKUP(B75,#REF!,6,0),"ACTIVO") -> ACTIVO | E75: 43504 | F75: =IFERROR(VLOOKUP(B75,#REF!,5,0),"") | G75: 32284 | H75: =+YEARFRAC(G75,TODAY(),1) -> 37.861074 | I75: Femenino | J75: dcquintero@gane.com.co | K75: ASESOR DE VENTAS - GIROS, PAGOS, RECARGAS | L75: LINEA DE NEGOCIOS | M75: COMERCIAL | N75: SI | O75: SI | P75: Moto | Q75: WDO14F | R75: Si | U75: 9FSBE4EW6NC104421 | V75: E482-335054 | W75: 2022 | X75: SUZUKI | Y75: 113 | AA75: 44429 | AB75: =IF(AD75<=TODAY(),"Vencida","Vigente") -> Vigente | AC75: =IF(P75="No tiene","No aplica",IF(AD75>$C$6,"Vigente","No Vigente")) -> Vigente | AD75: 46260 | AE75: =IF(AG75<=TODAY(),"Vencida","Vigente") -> Vigente | AF75: =+IF(P75="No tiene","No aplica",IF(AG75>$C$6,"Vigente","No Vigente")) -> Vigente | AG75: 46281 | AH75: A2 | AI75: A2 | AJ75: 49164 | AK75: =+IF(P75="No tiene","No aplica",IF(AJ75>$C$6,"Vigente","No Vigente")) -> Vigente | AM75: =+COUNTIFS(AC75:AK75,"Vigente") -> 4 | AQ75: =+_xlfn.XLOOKUP(B75,'BD 2025-06-14'!$A$1:$A$700,'BD 2025-06-14'!$B$1:$B$700) -> QUINTERO SOLARTE DIANA CAROLINA
A76: 67 | B76: 1130634495 | C76: GOMEZ HERNANDEZ SULAY GEOVANA | D76: =IFERROR(VLOOKUP(B76,#REF!,6,0),"ACTIVO") -> ACTIVO | E76: 43504 | F76: =IFERROR(VLOOKUP(B76,#REF!,5,0),"") | G76: 31999 | H76: =+YEARFRAC(G76,TODAY(),1) -> 38.642026 | I76: Femenino | J76: sggomez@gane.com.co | K76: ASESOR DE VENTAS - GIROS, PAGOS, RECARGAS | L76: LINEA DE NEGOCIOS | M76: COMERCIAL | N76: SI | O76: SI | P76: Moto | Q76: GEF96G | R76: Si | U76: 9F2C91252P5004200 | V76: ZS154FMI-38N200576 | W76: 2023 | X76: AKT | Y76: 125 | AA76: 44771 | AB76: =IF(AD76<=TODAY(),"Vencida","Vigente") -> Vigente | AC76: =IF(P76="No tiene","No aplica",IF(AD76>$C$6,"Vigente","No Vigente")) -> Vigente | AD76: 46230 | AE76: =IF(AG76<=TODAY(),"Vencida","Vigente") -> Vigente | AF76: =+IF(P76="No tiene","No aplica",IF(AG76>$C$6,"Vigente","No Vigente")) -> Vigente | AG76: 46230 | AH76: A2 | AI76: A2 | AJ76: 48421 | AK76: =+IF(P76="No tiene","No aplica",IF(AJ76>$C$6,"Vigente","No Vigente")) -> Vigente | AM76: =+COUNTIFS(AC76:AK76,"Vigente") -> 4 | AQ76: =+_xlfn.XLOOKUP(B76,'BD 2025-06-14'!$A$1:$A$700,'BD 2025-06-14'!$B$1:$B$700) -> GOMEZ HERNANDEZ SULAY GEOVANA
A77: 68 | B77: 1144095481 | C77: FILIGRANA CHAUSTRE TANIA | D77: =IFERROR(VLOOKUP(B77,#REF!,6,0),"ACTIVO") -> ACTIVO | E77: 43755 | F77: =IFERROR(VLOOKUP(B77,#REF!,5,0),"") | G77: 35531 | H77: =+YEARFRAC(G77,TODAY(),1) -> 28.973259 | I77: Femenino | J77: tfiligrana@gane.com.co | K77: ASESOR DE VENTAS - GIROS, PAGOS, RECARGAS | L77: LINEA DE NEGOCIOS | M77: COMERCIAL | N77: SI | O77: SI | P77: Moto | Q77: QMX10E | R77: Si | U77: 9FSBE4EN9JC151492 | V77: E482-315339 | W77: 2018 | X77: Suzuki | Y77: 115 | AA77: 43035 | AB77: =IF(AD77<=TODAY(),"Vencida","Vigente") -> Vencida | AC77: =IF(P77="No tiene","No aplica",IF(AD77>$C$6,"Vigente","No Vigente")) -> Vigente | AD77: 45958 | AE77: =IF(AG77<=TODAY(),"Vencida","Vigente") -> Vencida | AF77: =+IF(P77="No tiene","No aplica",IF(AG77>$C$6,"Vigente","No Vigente")) -> Vigente | AG77: 45957 | AH77: A2 | AI77: A2 | AJ77: 46481 | AK77: =+IF(P77="No tiene","No aplica",IF(AJ77>$C$6,"Vigente","No Vigente")) -> Vigente | AM77: =+COUNTIFS(AC77:AK77,"Vigente") -> 3 | AQ77: =+_xlfn.XLOOKUP(B77,'BD 2025-06-14'!$A$1:$A$700,'BD 2025-06-14'!$B$1:$B$700) -> FILIGRANA CHAUSTRE TANIA
A78: 69 | B78: 1130627977 | C78: GUTIERREZ GOMEZ JOSE FERNANDO | D78: =IFERROR(VLOOKUP(B78,#REF!,6,0),"ACTIVO") -> ACTIVO | E78: 43906 | F78: =IFERROR(VLOOKUP(B78,#REF!,5,0),"") | G78: 31636 | H78: =+YEARFRAC(G78,TODAY(),1) -> 39.636528 | I78: Masculino | J78: jfgutierrez@gane.com.co | K78: ASESOR DE VENTAS - GIROS, PAGOS, RECARGAS | L78: LINEA DE NEGOCIOS | M78: COMERCIAL | N78: SI | O78: SI | P78: Moto | Q78: AZX86G | R78: Si | U78: 9FLT22008NDH06069 | V78: 0R1AN2XA3587 | W78: 2022 | X78: TVS | Y78: 197 | AA78: 44588 | AB78: =IF(AD78<=TODAY(),"Vencida","Vigente") -> Vencida | AC78: =IF(P78="No tiene","No aplica",IF(AD78>$C$6,"Vigente","No Vigente")) -> Vigente | AD78: 46078 | AE78: =IF(AG78<=TODAY(),"Vencida","Vigente") -> Vencida | AF78: =+IF(P78="No tiene","No aplica",IF(AG78>$C$6,"Vigente","No Vigente")) -> Vigente | AG78: 46049 | AH78: A2 | AI78: A2 | AJ78: 46420 | AK78: =+IF(P78="No tiene","No aplica",IF(AJ78>$C$6,"Vigente","No Vigente")) -> Vigente | AM78: =+COUNTIFS(AC78:AK78,"Vigente") -> 3 | AQ78: =+_xlfn.XLOOKUP(B78,'BD 2025-06-14'!$A$1:$A$700,'BD 2025-06-14'!$B$1:$B$700) -> GUTIERREZ GOMEZ JOSE FERNANDO
A79: 70 | B79: 1005968424 | C79: SOLIS AYALA JUAN SEBASTIAN | D79: =IFERROR(VLOOKUP(B79,#REF!,6,0),"ACTIVO") -> ACTIVO | E79: 44713 | F79: =IFERROR(VLOOKUP(B79,#REF!,5,0),"") | G79: 37890 | H79: =+YEARFRAC(G79,TODAY(),1) -> 22.513347 | I79: Masculino | J79: jssolis@gane.com.co | K79: ASESOR DE VENTAS - NUEVOS JUEGOS | L79: VENTAS | M79: COMERCIAL | N79: SI | O79: SI | P79: Moto | Q79: ZSJ44G | R79: Si | U79: 9FL25AF31SDB36233 | V79: AF3AR1XF0429 | W79: 2025 | X79: Honda | Y79: 124 | AA79: 45400 | AB79: =IF(AD79<=TODAY(),"Vencida","Vigente") -> Vigente | AC79: =IF(P79="No tiene","No aplica",IF(AD79>$C$6,"Vigente","No Vigente")) -> Vigente | AD79: 46130 | AE79: =IF(AG79<=TODAY(),"Vencida","Vigente") -> Vigente | AF79: =+IF(P79="No tiene","No aplica",IF(AG79>$C$6,"Vigente","No Vigente")) -> Vigente | AG79: 46130 | AH79: A2 | AI79: A2 | AJ79: 48313 | AK79: =+IF(P79="No tiene","No aplica",IF(AJ79>$C$6,"Vigente","No Vigente")) -> Vigente | AM79: =+COUNTIFS(AC79:AK79,"Vigente") -> 4 | AP79: Se actualizo informacion de la nueva moto el dia 22/04/2025. La motocicleta es nueva, debe de expedir RTM en el año 2026. | AQ79: =+_xlfn.XLOOKUP(B79,'BD 2025-06-14'!$A$1:$A$700,'BD 2025-06-14'!$B$1:$B$700) -> SOLIS AYALA JUAN SEBASTIAN
A80: 71 | B80: 16799736 | C80: RAMIREZ BEJARANO MAURICIO | D80: =IFERROR(VLOOKUP(B80,#REF!,6,0),"ACTIVO") -> ACTIVO | E80: 38869 | F80: =IFERROR(VLOOKUP(B80,#REF!,5,0),"") | G80: 26405 | H80: =+YEARFRAC(G80,TODAY(),1) -> 53.956892 | I80: Masculino | J80: mramirez@gane.com.co | K80: ASESOR DE VENTAS TANGIBLES | L80: LINEA DE NEGOCIOS | M80: COMERCIAL | N80: SI | O80: SI | P80: Moto | Q80: LAP53D | R80: Si | U80: 9FMHA1125FF003689 | V80: HA11EDD9D00032 | W80: 2015 | X80: Honda | Y80: 100 | AA80: 41806 | AB80: =IF(AD80<=TODAY(),"Vencida","Vigente") -> Vigente | AC80: =IF(P80="No tiene","No aplica",IF(AD80>$C$6,"Vigente","No Vigente")) -> Vigente | AD80: 46209 | AE80: =IF(AG80<=TODAY(),"Vencida","Vigente") -> Vigente | AF80: =+IF(P80="No tiene","No aplica",IF(AG80>$C$6,"Vigente","No Vigente")) -> Vigente | AG80: 46201 | AH80: A2 | AI80: A2 | AJ80: 48728 | AK80: =+IF(P80="No tiene","No aplica",IF(AJ80>$C$6,"Vigente","No Vigente")) -> Vigente | AM80: =+COUNTIFS(AC80:AK80,"Vigente") -> 4 | AQ80: =+_xlfn.XLOOKUP(B80,'BD 2025-06-14'!$A$1:$A$700,'BD 2025-06-14'!$B$1:$B$700) -> RAMIREZ BEJARANO MAURICIO
A81: 72 | B81: 16744628 | C81: HERNANDEZ CUELLAR ALVARO | D81: =IFERROR(VLOOKUP(B81,#REF!,6,0),"ACTIVO") -> ACTIVO | E81: 38875 | F81: =IFERROR(VLOOKUP(B81,#REF!,5,0),"") | G81: 24788 | H81: =+YEARFRAC(G81,TODAY(),1) -> 58.384668 | I81: Masculino | J81: ahernandez@gane.com.co | K81: ASESOR DE VENTAS TANGIBLES | L81: LINEA DE NEGOCIOS | M81: COMERCIAL | N81: SI | O81: SI | P81: Moto | Q81: JJN09B | R81: No | S81: John Jaime Gil Vasquez | T81: 94498203 | U81: KC09E5005407 | V81: KC09E5005407 | W81: 2008 | X81: Honda | Y81: 150 | AA81: 39449 | AB81: =IF(AD81<=TODAY(),"Vencida","Vigente") -> Vencida | AC81: =IF(P81="No tiene","No aplica",IF(AD81>$C$6,"Vigente","No Vigente")) -> Vigente | AD81: 46039 | AE81: =IF(AG81<=TODAY(),"Vencida","Vigente") -> Vencida | AF81: =+IF(P81="No tiene","No aplica",IF(AG81>$C$6,"Vigente","No Vigente")) -> Vigente | AG81: 46014 | AH81: A2 | AI81: A2 | AJ81: 48714 | AK81: =+IF(P81="No tiene","No aplica",IF(AJ81>$C$6,"Vigente","No Vigente")) -> Vigente | AM81: =+COUNTIFS(AC81:AK81,"Vigente") -> 3 | AQ81: =+_xlfn.XLOOKUP(B81,'BD 2025-06-14'!$A$1:$A$700,'BD 2025-06-14'!$B$1:$B$700) -> HERNANDEZ CUELLAR ALVARO
A82: 73 | B82: 16917763 | C82: LOPEZ ARANGO MARIO ALBERTO | D82: =IFERROR(VLOOKUP(B82,#REF!,6,0),"ACTIVO") -> ACTIVO | E82: 38899 | F82: =IFERROR(VLOOKUP(B82,#REF!,5,0),"") | G82: 29512 | H82: =+YEARFRAC(G82,TODAY(),1) -> 45.450399 | I82: Masculino | J82: malopez@gane.com.co | K82: ASESOR DE VENTAS TANGIBLES | L82: LINEA DE NEGOCIOS | M82: COMERCIAL | N82: SI | O82: SI | P82: Moto | Q82: BPN60E | R82: No | S82: Martha Elena Arango Arbelaez | T82: 29806928 | U82: 9FLA64CZ2GAB16603 | V82: JEZWFM30618 | W82: 2016 | X82: BAJAJ | Y82: 144 | AA82: 42502 | AB82: =IF(AD82<=TODAY(),"Vencida","Vigente") -> Vencida | AC82: =IF(P82="No tiene","No aplica",IF(AD82>$C$6,"Vigente","No Vigente")) -> Vigente | AD82: 46088 | AE82: =IF(AG82<=TODAY(),"Vencida","Vigente") -> Vigente | AF82: =+IF(P82="No tiene","No aplica",IF(AG82>$C$6,"Vigente","No Vigente")) -> Vigente | AG82: 46244 | AH82: A2 | AI82: A2 | AJ82: 48771 | AK82: =+IF(P82="No tiene","No aplica",IF(AJ82>$C$6,"Vigente","No Vigente")) -> Vigente | AM82: =+COUNTIFS(AC82:AK82,"Vigente") -> 4 | AQ82: =+_xlfn.XLOOKUP(B82,'BD 2025-06-14'!$A$1:$A$700,'BD 2025-06-14'!$B$1:$B$700) -> LOPEZ ARANGO MARIO ALBERTO
A83: 74 | B83: 16766666 | C83: MURIEL LOPEZ CARLOS ALBERTO | D83: =IFERROR(VLOOKUP(B83,#REF!,6,0),"ACTIVO") -> ACTIVO | E83: 39218 | F83: =IFERROR(VLOOKUP(B83,#REF!,5,0),"") | G83: 25275 | H83: =+YEARFRAC(G83,TODAY(),1) -> 57.052681 | I83: Masculino | J83: camuriel@gane.com.co | K83: ASESOR DE VENTAS TANGIBLES | L83: LINEA DE NEGOCIOS | M83: COMERCIAL | N83: SI | O83: SI | P83: Moto | Q83: ZXX33E | R83: Si | U83: 9FLA37CYXKAA09907 | V83: JEZWJG06553 | W83: 2019 | X83: Bajaj | Y83: 125 | AA83: 43509 | AB83: =IF(AD83<=TODAY(),"Vencida","Vigente") -> Vencida | AC83: =IF(P83="No tiene","No aplica",IF(AD83>$C$6,"Vigente","No Vigente")) -> Vigente | AD83: 46069 | AE83: =IF(AG83<=TODAY(),"Vencida","Vigente") -> Vigente | AF83: =+IF(P83="No tiene","No aplica",IF(AG83>$C$6,"Vigente","No Vigente")) -> Vigente | AG83: 46306 | AH83: A2 | AI83: A2 | AJ83: 48709 | AK83: =+IF(P83="No tiene","No aplica",IF(AJ83>$C$6,"Vigente","No Vigente")) -> Vigente | AM83: =+COUNTIFS(AC83:AK83,"Vigente") -> 4 | AQ83: =+_xlfn.XLOOKUP(B83,'BD 2025-06-14'!$A$1:$A$700,'BD 2025-06-14'!$B$1:$B$700) -> MURIEL LOPEZ CARLOS ALBERTO
A84: 75 | B84: 94514840 | C84: MARTINEZ LOPEZ JAIRO ALONSO | D84: =IFERROR(VLOOKUP(B84,#REF!,6,0),"ACTIVO") -> ACTIVO | E84: 39412 | F84: =IFERROR(VLOOKUP(B84,#REF!,5,0),"") | G84: 28526 | H84: =+YEARFRAC(G84,TODAY(),1) -> 48.151254 | I84: Masculino | J84: jamartinez@gane.com.co | K84: ASESOR DE VENTAS TANGIBLES | L84: LINEA DE NEGOCIOS | M84: COMERCIAL | N84: SI | O84: SI | P84: Moto | Q84: DEG97D | R84: Si | U84: 9FLA37CZXECF22060 | V84: JEZWDK31599 | W84: 2014 | X84: Bajaj | Y84: 125 | AA84: 41451 | AB84: =IF(AD84<=TODAY(),"Vencida","Vigente") -> Vigente | AC84: =IF(P84="No tiene","No aplica",IF(AD84>$C$6,"Vigente","No Vigente")) -> Vigente | AD84: 46255 | AE84: =IF(AG84<=TODAY(),"Vencida","Vigente") -> Vigente | AF84: =+IF(P84="No tiene","No aplica",IF(AG84>$C$6,"Vigente","No Vigente")) -> Vigente | AG84: 46235 | AH84: A2 | AI84: A2 | AJ84: 48702 | AK84: =+IF(P84="No tiene","No aplica",IF(AJ84>$C$6,"Vigente","No Vigente")) -> Vigente | AM84: =+COUNTIFS(AC84:AK84,"Vigente") -> 4 | AQ84: =+_xlfn.XLOOKUP(B84,'BD 2025-06-14'!$A$1:$A$700,'BD 2025-06-14'!$B$1:$B$700) -> MARTINEZ LOPEZ JAIRO ALONSO
A85: 76 | B85: 94525706 | C85: CAMACHO CASTILLO JHON JAIRO | D85: =IFERROR(VLOOKUP(B85,#REF!,6,0),"ACTIVO") -> ACTIVO | E85: 39476 | F85: =IFERROR(VLOOKUP(B85,#REF!,5,0),"") | G85: 28844 | H85: =+YEARFRAC(G85,TODAY(),1) -> 47.280606 | I85: Masculino | J85: jjcamacho@gane.com.co | K85: ASESOR DE VENTAS TANGIBLES | L85: LINEA DE NEGOCIOS | M85: COMERCIAL | N85: SI | O85: SI | P85: Moto | Q85: TDJ88E | R85: No | S85: JOAN FERNANDO HERNANDEZ SANTACRUZ | T85: 1151954435 | U85: 9G5HAH022KVJD0808 | V85: HA11ENJ9A08286 | W85: 2019 | X85: HERO | Y85: 98 | AA85: 43245 | AB85: =IF(AD85<=TODAY(),"Vencida","Vigente") -> Vencida | AC85: =IF(P85="No tiene","No aplica",IF(AD85>$C$6,"Vigente","No Vigente")) -> Vigente | AD85: 46086 | AE85: =IF(AG85<=TODAY(),"Vencida","Vigente") -> Vencida | AF85: =+IF(P85="No tiene","No aplica",IF(AG85>$C$6,"Vigente","No Vigente")) -> Vigente | AG85: 46084 | AH85: A2 | AI85: A2 | AJ85: 48750 | AK85: =+IF(P85="No tiene","No aplica",IF(AJ85>$C$6,"Vigente","No Vigente")) -> Vigente | AM85: =+COUNTIFS(AC85:AK85,"Vigente") -> 3 | AP85: No ha expedido el SOAT, se le aviso por Whatsapp el 07062025. Documentos vencidos. | AQ85: =+_xlfn.XLOOKUP(B85,'BD 2025-06-14'!$A$1:$A$700,'BD 2025-06-14'!$B$1:$B$700) -> CAMACHO CASTILLO JHON JAIRO
A86: 77 | B86: 66823253 | C86: PRADO RIOS JACQUELINE | D86: =IFERROR(VLOOKUP(B86,#REF!,6,0),"ACTIVO") -> ACTIVO | E86: 39554 | F86: =IFERROR(VLOOKUP(B86,#REF!,5,0),"") | G86: 25792 | H86: =+YEARFRAC(G86,TODAY(),1) -> 55.636534 | I86: Femenino | J86: jprado@gane.com.co | K86: ASESOR DE VENTAS TANGIBLES | L86: LINEA DE NEGOCIOS | M86: COMERCIAL | N86: SI | O86: SI | P86: Moto | Q86: WTB21G | R86: No | S86: DAVID RENDON CASTAÑO | T86: 9891454 | U86: 9FSBE4E11RC101100 | V86: E489-211084 | W86: 2024 | X86: SUZUKI | Y86: 113 | AA86: 45276 | AB86: =IF(AD86<=TODAY(),"Vencida","Vigente") -> Vencida | AC86: =IF(P86="No tiene","No aplica",IF(AD86>$C$6,"Vigente","No Vigente")) -> Vigente | AD86: 46007 | AE86: =IF(AG86<=TODAY(),"Vencida","Vigente") -> Vencida | AF86: =+IF(P86="No tiene","No aplica",IF(AG86>$C$6,"Vigente","No Vigente")) -> Vigente | AG86: 46009 | AH86: A2 | AI86: A2 | AJ86: 48551 | AK86: =+IF(P86="No tiene","No aplica",IF(AJ86>$C$6,"Vigente","No Vigente")) -> Vigente | AM86: =+COUNTIFS(AC86:AK86,"Vigente") -> 3 | AQ86: =+_xlfn.XLOOKUP(B86,'BD 2025-06-14'!$A$1:$A$700,'BD 2025-06-14'!$B$1:$B$700) -> PRADO RIOS JACQUELINE
A87: 78 | B87: 16771408 | C87: NARANJO RAMIREZ OSCAR MARIO | D87: =IFERROR(VLOOKUP(B87,#REF!,6,0),"ACTIVO") -> ACTIVO | E87: 39965 | F87: =IFERROR(VLOOKUP(B87,#REF!,5,0),"") | G87: 25396 | H87: =+YEARFRAC(G87,TODAY(),1) -> 56.721394 | I87: Masculino | J87: omnaranjo@gane.com.co | K87: ASESOR DE VENTAS TANGIBLES | L87: LINEA DE NEGOCIOS | M87: COMERCIAL | N87: SI | O87: SI | P87: Moto | Q87: QFQ80E | R87: Si | U87: MD634KE68J2A22341 | V87: 0E6AJ2179061 | W87: 2018 | X87: TVS | Y87: 177 | AA87: 43059 | AB87: =IF(AD87<=TODAY(),"Vencida","Vigente") -> Vigente | AC87: =IF(P87="No tiene","No aplica",IF(AD87>$C$6,"Vigente","No Vigente")) -> Vigente | AD87: 46123 | AE87: =IF(AG87<=TODAY(),"Vencida","Vigente") -> Vencida | AF87: =+IF(P87="No tiene","No aplica",IF(AG87>$C$6,"Vigente","No Vigente")) -> Vigente | AG87: 46025 | AH87: A2 | AI87: A2 | AJ87: 48724 | AK87: =+IF(P87="No tiene","No aplica",IF(AJ87>$C$6,"Vigente","No Vigente")) -> Vigente | AM87: =+COUNTIFS(AC87:AK87,"Vigente") -> 3 | AQ87: =+_xlfn.XLOOKUP(B87,'BD 2025-06-14'!$A$1:$A$700,'BD 2025-06-14'!$B$1:$B$700) -> NARANJO RAMIREZ OSCAR MARIO
A88: 79 | B88: 6098150 | C88: ZEA GALVEZ DIEGO FERNANDO | D88: =IFERROR(VLOOKUP(B88,#REF!,6,0),"ACTIVO") -> ACTIVO | E88: 39995 | F88: =IFERROR(VLOOKUP(B88,#REF!,5,0),"") | G88: 28789 | H88: =+YEARFRAC(G88,TODAY(),1) -> 47.43119 | I88: Masculino | J88: dfzea@gane.com.co | K88: ASESOR DE VENTAS TANGIBLES | L88: LINEA DE NEGOCIOS | M88: COMERCIAL | N88: SI | O88: SI | P88: Moto | Q88: PRJ70G | R88: Si | U88: LC6JCK4P2P0020268 | V88: 157FMJ-3*G2U55661* | W88: 2023 | X88: Suzuki | Y88: 149 | AA88: 45012 | AB88: =IF(AD88<=TODAY(),"Vencida","Vigente") -> Vigente | AC88: =IF(P88="No tiene","No aplica",IF(AD88>$C$6,"Vigente","No Vigente")) -> Vigente | AD88: 46167 | AE88: =IF(AG88<=TODAY(),"Vencida","Vigente") -> Vigente | AF88: =+IF(P88="No tiene","No aplica",IF(AG88>$C$6,"Vigente","No Vigente")) -> Vigente | AG88: 46119 | AH88: A2 | AI88: A2 | AJ88: 48696 | AK88: =+IF(P88="No tiene","No aplica",IF(AJ88>$C$6,"Vigente","No Vigente")) -> Vigente | AM88: =+COUNTIFS(AC88:AK88,"Vigente") -> 4 | AP88: Moto nueva, debe expedir RTM a los 2 años a partir de la fecha de matricula 27/3/2023 | AQ88: =+_xlfn.XLOOKUP(B88,'BD 2025-06-14'!$A$1:$A$700,'BD 2025-06-14'!$B$1:$B$700) -> ZEA GALVEZ DIEGO FERNANDO
A89: 80 | B89: 16733826 | C89: BARCO CARDENAS RODRIGO | D89: =IFERROR(VLOOKUP(B89,#REF!,6,0),"ACTIVO") -> ACTIVO | E89: 39995 | F89: =IFERROR(VLOOKUP(B89,#REF!,5,0),"") | G89: 24453 | H89: =+YEARFRAC(G89,TODAY(),1) -> 59.302513 | I89: Masculino | J89: rbarco@gane.com.co | K89: ASESOR DE VENTAS TANGIBLES | L89: LINEA DE NEGOCIOS | M89: COMERCIAL | N89: SI | O89: SI | P89: Moto | Q89: KLY71E | R89: Si | U89: 9FLA64CZ5HAC31407 | V89: JEZWGH23872 | W89: 2017 | X89: Bajaj | Y89: 144 | AA89: 42836 | AB89: =IF(AD89<=TODAY(),"Vencida","Vigente") -> Vigente | AC89: =IF(P89="No tiene","No aplica",IF(AD89>$C$6,"Vigente","No Vigente")) -> Vigente | AD89: 46190 | AE89: =IF(AG89<=TODAY(),"Vencida","Vigente") -> Vigente | AF89: =+IF(P89="No tiene","No aplica",IF(AG89>$C$6,"Vigente","No Vigente")) -> Vigente | AG89: 46240 | AH89: A2, B1, C1 | AI89: A2 (21/12/2031) B1 (14/12/2027) C1 (14/12/2020) | AJ89: 48203 | AK89: =+IF(P89="No tiene","No aplica",IF(AJ89>$C$6,"Vigente","No Vigente")) -> Vigente | AM89: =+COUNTIFS(AC89:AK89,"Vigente") -> 4 | AQ89: =+_xlfn.XLOOKUP(B89,'BD 2025-06-14'!$A$1:$A$700,'BD 2025-06-14'!$B$1:$B$700) -> BARCO CARDENAS RODRIGO
A90: 81 | B90: 1130628573 | C90: MORALES BAUTISTA JHOAN NICOLAS | D90: =IFERROR(VLOOKUP(B90,#REF!,6,0),"ACTIVO") -> ACTIVO | E90: 41591 | F90: =IFERROR(VLOOKUP(B90,#REF!,5,0),"") | G90: 31664 | H90: =+YEARFRAC(G90,TODAY(),1) -> 39.559866 | I90: Masculino | J90: jnmorales@gane.com.co | K90: ASESOR DE VENTAS TANGIBLES | L90: LINEA DE NEGOCIOS | M90: COMERCIAL | N90: SI | O90: SI | P90: Moto | Q90: LJH55H | R90: Si | U90: 9G5KCU123TVSA0972 | V90: KC01AERHK01404 | W90: 2026 | X90: HERO | Y90: 163 | AA90: 45709 | AB90: =IF(AD90<=TODAY(),"Vencida","Vigente") -> Vigente | AC90: =IF(P90="No tiene","No aplica",IF(AD90>$C$6,"Vigente","No Vigente")) -> Vigente | AD90: 46439 | AE90: =IF(AG90<=TODAY(),"Vencida","Vigente") -> Vencida | AF90: =+IF(P90="No tiene","No aplica",IF(AG90>$C$6,"Vigente","No Vigente")) -> Vigente | AG90: 46073 | AH90: A2 | AI90: A2 | AJ90: 49087 | AK90: =+IF(P90="No tiene","No aplica",IF(AJ90>$C$6,"Vigente","No Vigente")) -> Vigente | AM90: =+COUNTIFS(AC90:AK90,"Vigente") -> 3 | AP90: Reporta cambio de vehiculo el dia 12/12/2025 | AQ90: =+_xlfn.XLOOKUP(B90,'BD 2025-06-14'!$A$1:$A$700,'BD 2025-06-14'!$B$1:$B$700) -> MORALES BAUTISTA JHOAN NICOLAS
A91: 82 | B91: 16750197 | C91: BUILES CAICEDO MARTIN EMILIO | D91: =IFERROR(VLOOKUP(B91,#REF!,6,0),"ACTIVO") -> ACTIVO | E91: 41778 | F91: =IFERROR(VLOOKUP(B91,#REF!,5,0),"") | G91: 24869 | H91: =+YEARFRAC(G91,TODAY(),1) -> 58.162227 | I91: Masculino | J91: mebuiles@gane.com.co | K91: ASESOR DE VENTAS TANGIBLES | L91: LINEA DE NEGOCIOS | M91: COMERCIAL | N91: SI | O91: SI | P91: Moto | Q91: JBW42G | R91: No | S91: Angie Vanessa Builes Gonzalez | T91: 1107531579 | U91: 9GFJCKLH9PHF23965 | V91: ZS157FMJ25N112674 | W91: 2023 | X91: Victory | Y91: 149 | AA91: 44792 | AB91: =IF(AD91<=TODAY(),"Vencida","Vigente") -> Vigente | AC91: =IF(P91="No tiene","No aplica",IF(AD91>$C$6,"Vigente","No Vigente")) -> Vigente | AD91: 46256 | AE91: =IF(AG91<=TODAY(),"Vencida","Vigente") -> Vigente | AF91: =+IF(P91="No tiene","No aplica",IF(AG91>$C$6,"Vigente","No Vigente")) -> Vigente | AG91: 46252 | AH91: A2 | AI91: A2 | AJ91: 48640 | AK91: =+IF(P91="No tiene","No aplica",IF(AJ91>$C$6,"Vigente","No Vigente")) -> Vigente | AM91: =+COUNTIFS(AC91:AK91,"Vigente") -> 4 | AQ91: =+_xlfn.XLOOKUP(B91,'BD 2025-06-14'!$A$1:$A$700,'BD 2025-06-14'!$B$1:$B$700) -> BUILES CAICEDO MARTIN EMILIO
A92: 83 | B92: 94493287 | C92: CASTRO CONCHA LUIS FERNANDO | D92: =IFERROR(VLOOKUP(B92,#REF!,6,0),"ACTIVO") -> ACTIVO | E92: 41821 | F92: =IFERROR(VLOOKUP(B92,#REF!,5,0),"") | G92: 27997 | H92: =+YEARFRAC(G92,TODAY(),1) -> 49.598239 | I92: Masculino | J92: lfcastro@gane.com.co | K92: ASESOR DE VENTAS TANGIBLES | L92: LINEA DE NEGOCIOS | M92: COMERCIAL | N92: SI | O92: SI | P92: Moto | Q92: EGL66D | R92: Si | U92: 9FLA37CZ6ECJ34143 | V92: JEZWDD43632 | W92: 2014 | X92: Bajaj | Y92: 125 | AA92: 41572 | AB92: =IF(AD92<=TODAY(),"Vencida","Vigente") -> Vigente | AC92: =IF(P92="No tiene","No aplica",IF(AD92>$C$6,"Vigente","No Vigente")) -> Vigente | AD92: 46323 | AE92: =IF(AG92<=TODAY(),"Vencida","Vigente") -> Vigente | AF92: =+IF(P92="No tiene","No aplica",IF(AG92>$C$6,"Vigente","No Vigente")) -> Vigente | AG92: 46322 | AH92: A2 | AI92: A2 | AJ92: 48739 | AK92: =+IF(P92="No tiene","No aplica",IF(AJ92>$C$6,"Vigente","No Vigente")) -> Vigente | AM92: =+COUNTIFS(AC92:AK92,"Vigente") -> 4 | AQ92: =+_xlfn.XLOOKUP(B92,'BD 2025-06-14'!$A$1:$A$700,'BD 2025-06-14'!$B$1:$B$700) -> CASTRO CONCHA LUIS FERNANDO
A93: 84 | B93: 1112476508 | C93: SANCHEZ JIMENEZ HERNAN DARIO | D93: =IFERROR(VLOOKUP(B93,#REF!,6,0),"ACTIVO") -> ACTIVO | E93: 42851 | F93: =IFERROR(VLOOKUP(B93,#REF!,5,0),"") | G93: 33836 | H93: =+YEARFRAC(G93,TODAY(),1) -> 33.611937 | I93: Masculino | J93: hdsanchez@gane.com.co | K93: ASESOR DE VENTAS TANGIBLES | L93: LINEA DE NEGOCIOS | M93: COMERCIAL | N93: SI | O93: SI | P93: Moto | Q93: TES90D | R93: Si | U93: 9FMKD0725KF003944 | V93: KD07E2352042 | W93: 2019 | X93: Honda | Y93: 150 | AA93: 43277 | AB93: =IF(AD93<=TODAY(),"Vencida","Vigente") -> Vigente | AC93: =IF(P93="No tiene","No aplica",IF(AD93>$C$6,"Vigente","No Vigente")) -> Vigente | AD93: 46264 | AE93: =IF(AG93<=TODAY(),"Vencida","Vigente") -> Vigente | AF93: =+IF(P93="No tiene","No aplica",IF(AG93>$C$6,"Vigente","No Vigente")) -> Vigente | AG93: 46259 | AH93: A2 | AI93: A2 | AJ93: 46351 | AK93: =+IF(P93="No tiene","No aplica",IF(AJ93>$C$6,"Vigente","No Vigente")) -> Vigente | AM93: =+COUNTIFS(AC93:AK93,"Vigente") -> 4 | AQ93: =+_xlfn.XLOOKUP(B93,'BD 2025-06-14'!$A$1:$A$700,'BD 2025-06-14'!$B$1:$B$700) -> SANCHEZ JIMENEZ HERNAN DARIO
A94: 85 | B94: 14839664 | C94: ZUNIGA RAMIREZ RAFAEL | D94: =IFERROR(VLOOKUP(B94,#REF!,6,0),"ACTIVO") -> ACTIVO | E94: 43224 | F94: =IFERROR(VLOOKUP(B94,#REF!,5,0),"") | G94: 29522 | H94: =+YEARFRAC(G94,TODAY(),1) -> 45.423021 | I94: Masculino | J94: rzuniga@gane.com.co | K94: ASESOR DE VENTAS TANGIBLES | L94: LINEA DE NEGOCIOS | M94: COMERCIAL | N94: SI | O94: SI | P94: Moto | Q94: ADQ84E | R94: Si | U94: 9G5HA11A2GV004599 | V94: HA11EJF9K51533 | W94: 2016 | X94: Hero | Y94: 100 | AA94: 42504 | AB94: =IF(AD94<=TODAY(),"Vencida","Vigente") -> Vigente | AC94: =IF(P94="No tiene","No aplica",IF(AD94>$C$6,"Vigente","No Vigente")) -> Vigente | AD94: 46189 | AE94: =IF(AG94<=TODAY(),"Vencida","Vigente") -> Vigente | AF94: =+IF(P94="No tiene","No aplica",IF(AG94>$C$6,"Vigente","No Vigente")) -> Vigente | AG94: 46298 | AH94: A2 | AI94: A2 | AJ94: 46198 | AK94: =+IF(P94="No tiene","No aplica",IF(AJ94>$C$6,"Vigente","No Vigente")) -> Vigente | AM94: =+COUNTIFS(AC94:AK94,"Vigente") -> 4 | AQ94: =+_xlfn.XLOOKUP(B94,'BD 2025-06-14'!$A$1:$A$700,'BD 2025-06-14'!$B$1:$B$700) -> ZUNIGA RAMIREZ RAFAEL
A95: 86 | B95: 87432752 | C95: ORTIZ PRADO VICTOR JAMES | D95: =IFERROR(VLOOKUP(B95,#REF!,6,0),"ACTIVO") -> ACTIVO | E95: 43257 | F95: =IFERROR(VLOOKUP(B95,#REF!,5,0),"") | G95: 26810 | H95: =+YEARFRAC(G95,TODAY(),1) -> 52.850074 | I95: Masculino | J95: vjortiz@gane.com.co | K95: ASESOR DE VENTAS TANGIBLES | L95: LINEA DE NEGOCIOS | M95: COMERCIAL | N95: SI | O95: SI | P95: Moto | Q95: GJO46F | R95: Si | U95: 9FMKD0722LF013543 | V95: KD07E2447277 | W95: 2020 | X95: Honda | Y95: 149 | AA95: 43760 | AB95: =IF(AD95<=TODAY(),"Vencida","Vigente") -> Vigente | AC95: =IF(P95="No tiene","No aplica",IF(AD95>$C$6,"Vigente","No Vigente")) -> Vigente | AD95: 46327 | AE95: =IF(AG95<=TODAY(),"Vencida","Vigente") -> Vigente | AF95: =+IF(P95="No tiene","No aplica",IF(AG95>$C$6,"Vigente","No Vigente")) -> Vigente | AG95: 46332 | AH95: A2 | AI95: A2 | AJ95: 48715 | AK95: =+IF(P95="No tiene","No aplica",IF(AJ95>$C$6,"Vigente","No Vigente")) -> Vigente | AM95: =+COUNTIFS(AC95:AK95,"Vigente") -> 4 | AQ95: =+_xlfn.XLOOKUP(B95,'BD 2025-06-14'!$A$1:$A$700,'BD 2025-06-14'!$B$1:$B$700) -> ORTIZ PRADO VICTOR JAMES
A96: 87 | B96: 1144203703 | C96: TORRES VERA BRAJHAN | D96: =IFERROR(VLOOKUP(B96,#REF!,6,0),"ACTIVO") -> ACTIVO | E96: 43657 | F96: =IFERROR(VLOOKUP(B96,#REF!,5,0),"") | G96: 35728 | H96: =+YEARFRAC(G96,TODAY(),1) -> 28.433878 | I96: Masculino | J96: btorres@gane.com.co | K96: ASESOR DE VENTAS TANGIBLES | L96: LINEA DE NEGOCIOS | M96: COMERCIAL | N96: SI | O96: SI | P96: Moto | Q96: OGH24E | R96: No | S96: Henri Antonio Chilito | T96: 16717150 | U96: 9FKDE0918J2067744 | V96: E3L5E067744 | W96: 2018 | X96: Yamaha | Y96: 124 | AA96: 42927 | AB96: =IF(AD96<=TODAY(),"Vencida","Vigente") -> Vencida | AC96: =IF(P96="No tiene","No aplica",IF(AD96>$C$6,"Vigente","No Vigente")) -> Vigente | AD96: 46107 | AE96: =IF(AG96<=TODAY(),"Vencida","Vigente") -> Vencida | AF96: =+IF(P96="No tiene","No aplica",IF(AG96>$C$6,"Vigente","No Vigente")) -> Vigente | AG96: 46097 | AH96: A2 | AI96: A2 | AJ96: 49368 | AK96: =+IF(P96="No tiene","No aplica",IF(AJ96>$C$6,"Vigente","No Vigente")) -> Vigente | AM96: =+COUNTIFS(AC96:AK96,"Vigente") -> 3 | AQ96: =+_xlfn.XLOOKUP(B96,'BD 2025-06-14'!$A$1:$A$700,'BD 2025-06-14'!$B$1:$B$700) -> TORRES VERA BRAJHAN
A97: 88 | B97: 1118284581 | C97: MENDOZA ZAMUDIO WILLIAM ALEXIS | D97: =IFERROR(VLOOKUP(B97,#REF!,6,0),"ACTIVO") -> ACTIVO | E97: 44062 | F97: =IFERROR(VLOOKUP(B97,#REF!,5,0),"") | G97: 31659 | H97: =+YEARFRAC(G97,TODAY(),1) -> 39.573556 | I97: Masculino | J97: wamendoza@gane.com.co | K97: ASESOR DE VENTAS TANGIBLES | L97: LINEA DE NEGOCIOS | M97: COMERCIAL | N97: SI | O97: SI | P97: Moto | Q97: NAR33F | R97: Si | U97: 9FLA18AY4MAH08905 | V97: DUZWLM19003 | W97: 2021 | X97: Bajaj | Y97: 100 | AA97: 44078 | AB97: =IF(AD97<=TODAY(),"Vencida","Vigente") -> Vigente | AC97: =IF(P97="No tiene","No aplica",IF(AD97>$C$6,"Vigente","No Vigente")) -> Vigente | AD97: 46290 | AE97: =IF(AG97<=TODAY(),"Vencida","Vigente") -> Vigente | AF97: =+IF(P97="No tiene","No aplica",IF(AG97>$C$6,"Vigente","No Vigente")) -> Vigente | AG97: 46291 | AH97: A2 | AI97: A2 | AJ97: 48786 | AK97: =+IF(P97="No tiene","No aplica",IF(AJ97>$C$6,"Vigente","No Vigente")) -> Vigente | AM97: =+COUNTIFS(AC97:AK97,"Vigente") -> 4 | AQ97: =+_xlfn.XLOOKUP(B97,'BD 2025-06-14'!$A$1:$A$700,'BD 2025-06-14'!$B$1:$B$700) -> MENDOZA ZAMUDIO WILLIAM ALEXIS
A98: 89 | B98: 65705929 | C98: GALINDO LUZ CARIME | D98: =IFERROR(VLOOKUP(B98,#REF!,6,0),"ACTIVO") -> ACTIVO | E98: 44068 | F98: =IFERROR(VLOOKUP(B98,#REF!,5,0),"") | G98: 29145 | H98: =+YEARFRAC(G98,TODAY(),1) -> 46.455852 | I98: Femenino | J98: lcgalindo@gane.com.co | K98: ASESOR DE VENTAS TANGIBLES | L98: LINEA DE NEGOCIOS | M98: COMERCIAL | N98: SI | O98: SI | P98: Moto | Q98: TYG81F | R98: No | S98: Rosalia Galindo Perdomo | T98: 65690542 | U98: 9F2C91259P5002301 | V98: ZS154FMI-38N110510 | W98: 2023 | X98: AKT | Y98: 125 | AA98: 44690 | AB98: =IF(AD98<=TODAY(),"Vencida","Vigente") -> Vigente | AC98: =IF(P98="No tiene","No aplica",IF(AD98>$C$6,"Vigente","No Vigente")) -> Vigente | AD98: 46151 | AE98: =IF(AG98<=TODAY(),"Vencida","Vigente") -> Vigente | AF98: =+IF(P98="No tiene","No aplica",IF(AG98>$C$6,"Vigente","No Vigente")) -> Vigente | AG98: 46151 | AH98: A2 | AI98: A2 | AJ98: 48751 | AK98: =+IF(P98="No tiene","No aplica",IF(AJ98>$C$6,"Vigente","No Vigente")) -> Vigente | AM98: =+COUNTIFS(AC98:AK98,"Vigente") -> 4 | AQ98: =+_xlfn.XLOOKUP(B98,'BD 2025-06-14'!$A$1:$A$700,'BD 2025-06-14'!$B$1:$B$700) -> GALINDO LUZ CARIME
A99: 90 | B99: 1143857521 | C99: VARGAS CORTES LUIS ANTONIO | D99: =IFERROR(VLOOKUP(B99,#REF!,6,0),"ACTIVO") -> ACTIVO | E99: 44186 | F99: =IFERROR(VLOOKUP(B99,#REF!,5,0),"") | G99: 34654 | H99: =+YEARFRAC(G99,TODAY(),1) -> 31.373683 | I99: Masculino | J99: lavargas@gane.com.co | K99: ASESOR DE VENTAS TANGIBLES | L99: LINEA DE NEGOCIOS | M99: COMERCIAL | N99: SI | O99: SI | P99: Moto | Q99: BMI43H | R99: Si | U99: 9G5HAH020SVRD0071 | V99: HA11EPP9L00985 | W99: 2025 | X99: HERO | Y99: 98 | AA99: 45432 | AB99: =IF(AD99<=TODAY(),"Vencida","Vigente") -> Vigente | AC99: =IF(P99="No tiene","No aplica",IF(AD99>$C$6,"Vigente","No Vigente")) -> Vigente | AD99: 46162 | AE99: =IF(AG99<=TODAY(),"Vencida","Vigente") -> Vigente | AF99: =+IF(P99="No tiene","No aplica",IF(AG99>$C$6,"Vigente","No Vigente")) -> Vigente | AG99: 46159 | AH99: A2 | AI99: A2 | AJ99: 46653 | AK99: =+IF(P99="No tiene","No aplica",IF(AJ99>$C$6,"Vigente","No Vigente")) -> Vigente | AM99: =+COUNTIFS(AC99:AK99,"Vigente") -> 4 | AP99: Moto nueva, debe expedir RTM a los 2 años a partir de la fecha de matricula 20/5/2024 | AQ99: =+_xlfn.XLOOKUP(B99,'BD 2025-06-14'!$A$1:$A$700,'BD 2025-06-14'!$B$1:$B$700) -> VARGAS CORTES LUIS ANTONIO
A100: 91 | B100: 1113531156 | C100: CUATIN LARRAHONDO CRISTHIAN FERNANDO | D100: =IFERROR(VLOOKUP(B100,#REF!,6,0),"ACTIVO") -> ACTIVO | E100: 44266 | F100: =IFERROR(VLOOKUP(B100,#REF!,5,0),"") | G100: 34595 | H100: =+YEARFRAC(G100,TODAY(),1) -> 31.535219 | I100: Masculino | J100: cfcuatin@gane.com.co | K100: ASESOR DE VENTAS TANGIBLES | L100: LINEA DE NEGOCIOS | M100: COMERCIAL | N100: SI | O100: SI | P100: Moto | Q100: TGP82F | R100: Si | U100: 9F2C91253N5003229 | V100: ZS154FMI-38N102182 | W100: 2022 | X100: AKT | Y100: 124 | AA100: 44370 | AB100: =IF(AD100<=TODAY(),"Vencida","Vigente") -> Vigente | AC100: =IF(P100="No tiene","No aplica",IF(AD100>$C$6,"Vigente","No Vigente")) -> Vigente | AD100: 46263 | AE100: =IF(AG100<=TODAY(),"Vencida","Vigente") -> Vigente | AF100: =+IF(P100="No tiene","No aplica",IF(AG100>$C$6,"Vigente","No Vigente")) -> Vigente | AG100: 46288 | AH100: A2 | AI100: A2 | AJ100: 49324 | AK100: =+IF(P100="No tiene","No aplica",IF(AJ100>$C$6,"Vigente","No Vigente")) -> Vigente | AM100: =+COUNTIFS(AC100:AK100,"Vigente") -> 4 | AP100: Reporta cambio de moto el dia 13/6/2025 | AQ100: =+_xlfn.XLOOKUP(B100,'BD 2025-06-14'!$A$1:$A$700,'BD 2025-06-14'!$B$1:$B$700) -> CUATIN LARRAHONDO CRISTHIAN FERNANDO
A101: 92 | B101: 1118289653 | C101: GIRALDO VARELA FREDDY ALEJANDRO | D101: =IFERROR(VLOOKUP(B101,#REF!,6,0),"ACTIVO") -> ACTIVO | E101: 44369 | F101: =IFERROR(VLOOKUP(B101,#REF!,5,0),"") | G101: 32393 | H101: =+YEARFRAC(G101,TODAY(),1) -> 37.562654 | I101: Masculino | J101: fagiraldo@gane.com.co | K101: ASESOR DE VENTAS TANGIBLES | L101: LINEA DE NEGOCIOS | M101: COMERCIAL | N101: SI | O101: SI | P101: Moto | Q101: CMF03H | R101: Si | U101: LC6JCK4PXS0002884 | V101: 157FMJ-3*G2U87150* | W101: 2025 | X101: SUZUKI | Y101: 149 | AA101: 45436 | AB101: =IF(AD101<=TODAY(),"Vencida","Vigente") -> Vigente | AC101: =IF(P101="No tiene","No aplica",IF(AD101>$C$6,"Vigente","No Vigente")) -> Vigente | AD101: 46166 | AE101: =IF(AG101<=TODAY(),"Vencida","Vigente") -> Vigente | AF101: =+IF(P101="No tiene","No aplica",IF(AG101>$C$6,"Vigente","No Vigente")) -> Vigente | AG101: 46165 | AH101: A2 | AI101: A2 -21/06/2033 B1 - 13/07/2033 | AJ101: 48751 | AK101: =+IF(P101="No tiene","No aplica",IF(AJ101>$C$6,"Vigente","No Vigente")) -> Vigente | AM101: =+COUNTIFS(AC101:AK101,"Vigente") -> 4 | AP101: Moto nueva, debe expedir RTM a los 2 años a partir de la fecha de matricula 24/5/2024 | AQ101: =+_xlfn.XLOOKUP(B101,'BD 2025-06-14'!$A$1:$A$700,'BD 2025-06-14'!$B$1:$B$700) -> GIRALDO VARELA FREDDY ALEJANDRO
A102: 93 | B102: 1113527871 | C102: NARVAEZ YESQUEN JULIO ADOLFO | D102: =IFERROR(VLOOKUP(B102,#REF!,6,0),"ACTIVO") -> ACTIVO | E102: 44475 | F102: =IFERROR(VLOOKUP(B102,#REF!,5,0),"") | G102: 34086 | H102: =+YEARFRAC(G102,TODAY(),1) -> 32.929457 | I102: Masculino | J102: janarvaez@gane.com.co | K102: ASESOR DE VENTAS TANGIBLES | L102: LINEA DE NEGOCIOS | M102: COMERCIAL | N102: SI | O102: SI | P102: Moto | Q102: KDL41G | R102: Si | U102: 9F2B42006PB007044 | V102: 163FMLVQ360090 | W102: 2023 | X102: AKT | Y102: 197 | AA102: 44890 | AB102: =IF(AD102<=TODAY(),"Vencida","Vigente") -> Vencida | AC102: =IF(P102="No tiene","No aplica",IF(AD102>$C$6,"Vigente","No Vigente")) -> Vigente | AD102: 46009 | AE102: =IF(AG102<=TODAY(),"Vencida","Vigente") -> Vigente | AF102: =+IF(P102="No tiene","No aplica",IF(AG102>$C$6,"Vigente","No Vigente")) -> Vigente | AG102: 46136 | AH102: A2 | AI102: A2 | AJ102: 48499 | AK102: =+IF(P102="No tiene","No aplica",IF(AJ102>$C$6,"Vigente","No Vigente")) -> Vigente | AM102: =+COUNTIFS(AC102:AK102,"Vigente") -> 4 | AP102: Incapacitado por FX | AQ102: =+_xlfn.XLOOKUP(B102,'BD 2025-06-14'!$A$1:$A$700,'BD 2025-06-14'!$B$1:$B$700) -> NARVAEZ YESQUEN JULIO ADOLFO
A103: 94 | B103: 1143960260 | C103: OSPINA AYALA WILDER ESNEIDER | D103: =IFERROR(VLOOKUP(B103,#REF!,6,0),"ACTIVO") -> ACTIVO | E103: 44566 | F103: =IFERROR(VLOOKUP(B103,#REF!,5,0),"") | G103: 34288 | H103: =+YEARFRAC(G103,TODAY(),1) -> 32.376389 | I103: Masculino | J103: weospina@gane.com.co | K103: ASESOR DE VENTAS TANGIBLES | L103: LINEA DE NEGOCIOS | M103: COMERCIAL | N103: SI | O103: SI | P103: Moto | Q103: WDA45F | R103: Si | U103: 9G5HAH027NVMG0450 | V103: HA11ENM9D01849 | W103: 2022 | X103: Hero | Y103: 98 | AA103: 44419 | AB103: =IF(AD103<=TODAY(),"Vencida","Vigente") -> Vigente | AC103: =IF(P103="No tiene","No aplica",IF(AD103>$C$6,"Vigente","No Vigente")) -> Vigente | AD103: 46242 | AE103: =IF(AG103<=TODAY(),"Vencida","Vigente") -> Vigente | AF103: =+IF(P103="No tiene","No aplica",IF(AG103>$C$6,"Vigente","No Vigente")) -> Vigente | AG103: 46248 | AH103: A2 | AI103: A2 | AJ103: 49140 | AK103: =+IF(P103="No tiene","No aplica",IF(AJ103>$C$6,"Vigente","No Vigente")) -> Vigente | AM103: =+COUNTIFS(AC103:AK103,"Vigente") -> 4 | AQ103: =+_xlfn.XLOOKUP(B103,'BD 2025-06-14'!$A$1:$A$700,'BD 2025-06-14'!$B$1:$B$700) -> OSPINA AYALA WILDER ESNEIDER
A104: 95 | B104: 1144078734 | C104: VARGAS MAJIN ERIK JOHAN | D104: =IFERROR(VLOOKUP(B104,#REF!,6,0),"ACTIVO") -> ACTIVO | E104: 44697 | F104: =IFERROR(VLOOKUP(B104,#REF!,5,0),"") | G104: 34754 | H104: =+YEARFRAC(G104,TODAY(),1) -> 31.099247 | I104: Masculino | J104: ejvargas@gane.com.co | K104: ASESOR DE VENTAS TANGIBLES | L104: LINEA DE NEGOCIOS | M104: COMERCIAL | N104: SI | O104: SI | P104: Moto | Q104: DSB75H | R104: Si | U104: 9GJB97PD1RP000152 | V104: PDXCNH76007 | W104: 2024 | X104: BAJAJ | Y104: 249 | AA104: 45472 | AB104: =IF(AD104<=TODAY(),"Vencida","Vigente") -> Vigente | AC104: =IF(P104="No tiene","No aplica",IF(AD104>$C$6,"Vigente","No Vigente")) -> Vigente | AD104: 46202 | AE104: =IF(AG104<=TODAY(),"Vencida","Vigente") -> Vigente | AF104: =+IF(P104="No tiene","No aplica",IF(AG104>$C$6,"Vigente","No Vigente")) -> Vigente | AG104: 46194 | AH104: A2 | AI104: A2 | AJ104: 49645 | AK104: =+IF(P104="No tiene","No aplica",IF(AJ104>$C$6,"Vigente","No Vigente")) -> Vigente | AL104: CONDUCIR CON LENTES | AM104: =+COUNTIFS(AC104:AK104,"Vigente") -> 4 | AQ104: =+_xlfn.XLOOKUP(B104,'BD 2025-06-14'!$A$1:$A$700,'BD 2025-06-14'!$B$1:$B$700) -> VARGAS MAJIN ERIK JOHAN
A105: 96 | B105: 1114878861 | C105: TORRES ROA JUAN MANUEL | D105: =IFERROR(VLOOKUP(B105,#REF!,6,0),"ACTIVO") -> ACTIVO | E105: 44728 | F105: =IFERROR(VLOOKUP(B105,#REF!,5,0),"") | G105: 32269 | H105: =+YEARFRAC(G105,TODAY(),1) -> 37.902141 | I105: Masculino | J105: jmtorres@gane.com.co | K105: ASESOR DE VENTAS TANGIBLES | L105: LINEA DE NEGOCIOS | M105: COMERCIAL | N105: SI | O105: SI | P105: Moto | Q105: LIX76H | R105: Si | U105: 9G5LDL02XTVSB0007 | V105: MC20ABRGB00281 | W105: 2026 | X105: Hero | Y105: 200 | AA105: 45709 | AB105: =IF(AD105<=TODAY(),"Vencida","Vigente") -> Vigente | AC105: =IF(P105="No tiene","No aplica",IF(AD105>$C$6,"Vigente","No Vigente")) -> Vigente | AD105: 46439 | AE105: =IF(AG105<=TODAY(),"Vencida","Vigente") -> Vencida | AF105: =+IF(P105="No tiene","No aplica",IF(AG105>$C$6,"Vigente","No Vigente")) -> Vigente | AG105: 46073 | AH105: A2 | AI105: A2 | AJ105: 49409 | AK105: =+IF(P105="No tiene","No aplica",IF(AJ105>$C$6,"Vigente","No Vigente")) -> Vigente | AM105: =+COUNTIFS(AC105:AK105,"Vigente") -> 3 | AP105: Se realizo actualizacion de cambio de motocicleta el dia 31/03/2025 (moto nueva). Moto nueva, debe expedir RTM a los 2 años a partir de la fecha de matricula 21/2/2025 | AQ105: =+_xlfn.XLOOKUP(B105,'BD 2025-06-14'!$A$1:$A$700,'BD 2025-06-14'!$B$1:$B$700) -> TORRES ROA JUAN MANUEL
A106: 97 | B106: 1113629455 | C106: MORALES MORA DIEGO ALBERTO | D106: =IFERROR(VLOOKUP(B106,#REF!,6,0),"ACTIVO") -> ACTIVO | E106: 44729 | F106: =IFERROR(VLOOKUP(B106,#REF!,5,0),"") | G106: 32035 | H106: =+YEARFRAC(G106,TODAY(),1) -> 38.543463 | I106: Masculino | J106: damorales@gane.com.co | K106: ASESOR DE VENTAS TANGIBLES | L106: LINEA DE NEGOCIOS | M106: COMERCIAL | N106: SI | O106: SI | P106: Moto | Q106: HFA48G | R106: Si | U106: 9FL25AF35PEF05337 | V106: AF3AP19A1386 | W106: 2023 | X106: TVS | Y106: 124 | AA106: 44754 | AB106: =IF(AD106<=TODAY(),"Vencida","Vigente") -> Vencida | AC106: =IF(P106="No tiene","No aplica",IF(AD106>$C$6,"Vigente","No Vigente")) -> Vigente | AD106: 45847 | AE106: =IF(AG106<=TODAY(),"Vencida","Vigente") -> Vencida | AF106: =+IF(P106="No tiene","No aplica",IF(AG106>$C$6,"Vigente","No Vigente")) -> Vigente | AG106: 45849 | AH106: A2 | AI106: A2 | AJ106: 48731 | AK106: =+IF(P106="No tiene","No aplica",IF(AJ106>$C$6,"Vigente","No Vigente")) -> Vigente | AM106: =+COUNTIFS(AC106:AK106,"Vigente") -> 3 | AQ106: =+_xlfn.XLOOKUP(B106,'BD 2025-06-14'!$A$1:$A$700,'BD 2025-06-14'!$B$1:$B$700) -> MORALES MORA DIEGO ALBERTO
A107: 98 | B107: 1107519027 | C107: CAMILO TORRES GIRALDO | D107: =IFERROR(VLOOKUP(B107,#REF!,6,0),"ACTIVO") -> ACTIVO | E107: 44767 | F107: =IFERROR(VLOOKUP(B107,#REF!,5,0),"") | G107: 35912 | H107: =+YEARFRAC(G107,TODAY(),1) -> 27.929475 | I107: Masculino | J107: ectorres@gane.com.co | K107: ASESOR DE VENTAS TANGIBLES | L107: LINEA DE NEGOCIOS | M107: COMERCIAL | N107: SI | O107: SI | P107: Moto | Q107: DSK84G | R107: No | S107: Angela Maria Osorio Bermudez | T107: 67024492 | U107: 9GFJCKLH3PKB20289 | V107: ZS157FMJ25N110166 | W107: 2023 | X107: Victory | Y107: 149 | AA107: 44699 | AB107: =IF(AD107<=TODAY(),"Vencida","Vigente") -> Vigente | AC107: =IF(P107="No tiene","No aplica",IF(AD107>$C$6,"Vigente","No Vigente")) -> Vigente | AD107: 46161 | AE107: =IF(AG107<=TODAY(),"Vencida","Vigente") -> Vigente | AF107: =+IF(P107="No tiene","No aplica",IF(AG107>$C$6,"Vigente","No Vigente")) -> Vigente | AG107: 46163 | AH107: A2 | AI107: A2 | AJ107: 48345 | AK107: =+IF(P107="No tiene","No aplica",IF(AJ107>$C$6,"Vigente","No Vigente")) -> Vigente | AM107: =+COUNTIFS(AC107:AK107,"Vigente") -> 4 | AQ107: =+_xlfn.XLOOKUP(B107,'BD 2025-06-14'!$A$1:$A$700,'BD 2025-06-14'!$B$1:$B$700) -> TORRES GIRALDO EUDES CAMILO
A108: 99 | B108: 1085281488 | C108: MAIGUAL ERASO DANNY YAIR | D108: =IFERROR(VLOOKUP(B108,#REF!,6,0),"ACTIVO") -> ACTIVO | E108: 45124 | F108: =IFERROR(VLOOKUP(B108,#REF!,5,0),"") | G108: 32967 | H108: =+YEARFRAC(G108,TODAY(),1) -> 35.992452 | I108: Masculino | J108: dymaigual@gane.com.co | K108: ASESOR DE VENTAS TANGIBLES | L108: LINEA DE NEGOCIOS | M108: COMERCIAL | N108: SI | O108: SI | P108: Moto | Q108: SFV90E | R108: No | S108: Cardenas Franco Anubi | T108: 1144058463 | U108: 9FSBE4EN0LC165994 | V108: E482-322025 | W108: 2020 | X108: Suzuki | Y108: 113 | AA108: 43585 | AB108: =IF(AD108<=TODAY(),"Vencida","Vigente") -> Vigente | AC108: =IF(P108="No tiene","No aplica",IF(AD108>$C$6,"Vigente","No Vigente")) -> Vigente | AD108: 46172 | AE108: =IF(AG108<=TODAY(),"Vencida","Vigente") -> Vigente | AF108: =+IF(P108="No tiene","No aplica",IF(AG108>$C$6,"Vigente","No Vigente")) -> Vigente | AG108: 46173 | AH108: A2 | AI108: A2 | AJ108: 49114 | AK108: =+IF(P108="No tiene","No aplica",IF(AJ108>$C$6,"Vigente","No Vigente")) -> Vigente | AM108: =+COUNTIFS(AC108:AK108,"Vigente") -> 4 | AQ108: =+_xlfn.XLOOKUP(B108,'BD 2025-06-14'!$A$1:$A$700,'BD 2025-06-14'!$B$1:$B$700) -> MAIGUAL ERASO DANNY YAIR
A109: 100 | B109: 1114899300 | C109: CASTILLO YENNY DANIELA | D109: =IFERROR(VLOOKUP(B109,#REF!,6,0),"ACTIVO") -> ACTIVO | E109: 45124 | F109: =IFERROR(VLOOKUP(B109,#REF!,5,0),"") | G109: 34946 | H109: =+YEARFRAC(G109,TODAY(),1) -> 30.57358 | I109: Femenino | J109: ydcastillo@gane.com.co | K109: ASESOR DE VENTAS TANGIBLES | L109: LINEA DE NEGOCIOS | M109: COMERCIAL | N109: SI | O109: SI | P109: Moto | Q109: YTI32G | R109: Si | U109: 9FMJA3792SE000413 | V109: JA37E-3416146 | W109: 2025 | X109: HONDA | Y109: 109 | AA109: 45343 | AB109: =IF(AD109<=TODAY(),"Vencida","Vigente") -> Vencida | AC109: =IF(P109="No tiene","No aplica",IF(AD109>$C$6,"Vigente","No Vigente")) -> Vigente | AD109: 46074 | AE109: =IF(AG109<=TODAY(),"Vencida","Vigente") -> Vencida | AF109: =+IF(P109="No tiene","No aplica",IF(AG109>$C$6,"Vigente","No Vigente")) -> Vigente | AG109: 46073 | AH109: A2 | AI109: A2 | AJ109: 49035 | AK109: =+IF(P109="No tiene","No aplica",IF(AJ109>$C$6,"Vigente","No Vigente")) -> Vigente | AM109: =+COUNTIFS(AC109:AK109,"Vigente") -> 3 | AP109: Moto nueva, debe expedir RTM a los 2 años a partir de la fecha de matricula 21/2/2026 | AQ109: =+_xlfn.XLOOKUP(B109,'BD 2025-06-14'!$A$1:$A$700,'BD 2025-06-14'!$B$1:$B$700) -> CASTILLO YENNY DANIELA
A110: 101 | B110: 1193170379 | C110: CORTES CHARRIA JOSE LUIS | D110: =IFERROR(VLOOKUP(B110,#REF!,6,0),"ACTIVO") -> ACTIVO | E110: 45162 | F110: =IFERROR(VLOOKUP(B110,#REF!,5,0),"") | G110: 36997 | H110: =+YEARFRAC(G110,TODAY(),1) -> 24.959562 | I110: Masculino | J110: jcortes@gane.com.co | K110: ASESOR DE VENTAS TANGIBLES | L110: LINEA DE NEGOCIOS | M110: COMERCIAL | N110: SI | O110: SI | P110: Moto | Q110: CLB90G | R110: Si | U110: 9G5JAS026PVNA0373 | V110: JA06EXM9G00327 | W110: 2023 | X110: Hero | Y110: 124 | AA110: 44620 | AB110: =IF(AD110<=TODAY(),"Vencida","Vigente") -> Vigente | AC110: =IF(P110="No tiene","No aplica",IF(AD110>$C$6,"Vigente","No Vigente")) -> Vigente | AD110: 46259 | AE110: =IF(AG110<=TODAY(),"Vencida","Vigente") -> Vencida | AF110: =+IF(P110="No tiene","No aplica",IF(AG110>$C$6,"Vigente","No Vigente")) -> Vigente | AG110: 46080 | AH110: A2 | AI110: A2 | AJ110: 48272 | AK110: =+IF(P110="No tiene","No aplica",IF(AJ110>$C$6,"Vigente","No Vigente")) -> Vigente | AM110: =+COUNTIFS(AC110:AK110,"Vigente") -> 3 | AQ110: =+_xlfn.XLOOKUP(B110,'BD 2025-06-14'!$A$1:$A$700,'BD 2025-06-14'!$B$1:$B$700) -> CORTES CHARRIA JOSE LUIS
A111: 102 | B111: 1144190231 | C111: VICTORIA VALDES HECTOR EDUARDO | D111: =IFERROR(VLOOKUP(B111,#REF!,6,0),"ACTIVO") -> ACTIVO | E111: 45173 | F111: =IFERROR(VLOOKUP(B111,#REF!,5,0),"") | G111: 35003 | H111: =+YEARFRAC(G111,TODAY(),1) -> 30.417522 | I111: Masculino | J111: hevictoria@gane.com.co | K111: ASESOR DE VENTAS TANGIBLES | L111: LINEA DE NEGOCIOS | M111: COMERCIAL | N111: SI | O111: SI | P111: Moto | Q111: SHX47F | R111: Si | U111: 9F2D51250N5008484 | V111: 157FMITE362672 | W111: 2022 | X111: AKT | Y111: 124 | AA111: 44300 | AB111: =IF(AD111<=TODAY(),"Vencida","Vigente") -> Vigente | AC111: =IF(P111="No tiene","No aplica",IF(AD111>$C$6,"Vigente","No Vigente")) -> Vigente | AD111: 46188 | AE111: =IF(AG111<=TODAY(),"Vencida","Vigente") -> Vigente | AF111: =+IF(P111="No tiene","No aplica",IF(AG111>$C$6,"Vigente","No Vigente")) -> Vigente | AG111: 46188 | AH111: A2 | AI111: A2 | AJ111: 46118 | AK111: =+IF(P111="No tiene","No aplica",IF(AJ111>$C$6,"Vigente","No Vigente")) -> Vigente | AM111: =+COUNTIFS(AC111:AK111,"Vigente") -> 4 | AQ111: =+_xlfn.XLOOKUP(B111,'BD 2025-06-14'!$A$1:$A$700,'BD 2025-06-14'!$B$1:$B$700) -> VICTORIA VALDES HECTOR EDUARDO
A112: 103 | B112: 1144173071 | C112: MUNOZ RODRIGUEZ MILLER ANDRES | D112: =IFERROR(VLOOKUP(B112,#REF!,6,0),"ACTIVO") -> ACTIVO | E112: 45173 | F112: =IFERROR(VLOOKUP(B112,#REF!,5,0),"") | G112: 34272 | H112: =+YEARFRAC(G112,TODAY(),1) -> 32.420196 | I112: Masculino | J112: mandresm@gane.com.co | K112: ASESOR DE VENTAS TANGIBLES | L112: LINEA DE NEGOCIOS | M112: COMERCIAL | N112: SI | O112: SI | P112: Moto | Q112: FMW14E | R112: No | S112: Ituyan Jaramillo Segundo | T112: 94467748 | U112: 9FMJC472XHF000326 | V112: JC47E-7-6070355 | W112: 2017 | X112: Honda | Y112: 109 | AA112: 42719 | AB112: =IF(AD112<=TODAY(),"Vencida","Vigente") -> Vigente | AC112: =IF(P112="No tiene","No aplica",IF(AD112>$C$6,"Vigente","No Vigente")) -> Vigente | AD112: 46253 | AE112: =IF(AG112<=TODAY(),"Vencida","Vigente") -> Vigente | AF112: =+IF(P112="No tiene","No aplica",IF(AG112>$C$6,"Vigente","No Vigente")) -> Vigente | AG112: 46251 | AH112: A2 | AI112: A2 | AJ112: 48808 | AK112: =+IF(P112="No tiene","No aplica",IF(AJ112>$C$6,"Vigente","No Vigente")) -> Vigente | AM112: =+COUNTIFS(AC112:AK112,"Vigente") -> 4 | AQ112: =+_xlfn.XLOOKUP(B112,'BD 2025-06-14'!$A$1:$A$700,'BD 2025-06-14'!$B$1:$B$700) -> MUNOZ RODRIGUEZ MILLER ANDRES
A113: 104 | B113: 1151954025 | C113: MENESES PINEDA JADER ANDREI | D113: =IFERROR(VLOOKUP(B113,#REF!,6,0),"ACTIVO") -> ACTIVO | E113: 45231 | F113: =IFERROR(VLOOKUP(B113,#REF!,5,0),"") | G113: 34505 | H113: =+YEARFRAC(G113,TODAY(),1) -> 31.781631 | I113: Masculino | J113: jmeneses@gane.com.co | K113: AUXILIAR ADMINISTRATIVO (TANGIBLES) | L113: LINEA DE NEGOCIOS | M113: COMERCIAL | N113: SI | O113: SI | P113: Moto | Q113: JDQ31G | R113: Si | U113: 9F2D91252PX001208 | V113: XS1P52QMI-322000383 | W113: 2023 | X113: AKT | Y113: 124 | AA113: 44834 | AB113: =IF(AD113<=TODAY(),"Vencida","Vigente") -> Vigente | AC113: =IF(P113="No tiene","No aplica",IF(AD113>$C$6,"Vigente","No Vigente")) -> Vigente | AD113: 46297 | AE113: =IF(AG113<=TODAY(),"Vencida","Vigente") -> Vigente | AF113: =+IF(P113="No tiene","No aplica",IF(AG113>$C$6,"Vigente","No Vigente")) -> Vigente | AG113: 46302 | AH113: A2 | AI113: A2 | AJ113: 48534 | AK113: =+IF(P113="No tiene","No aplica",IF(AJ113>$C$6,"Vigente","No Vigente")) -> Vigente | AM113: =+COUNTIFS(AC113:AK113,"Vigente") -> 4 | AQ113: =+_xlfn.XLOOKUP(B113,'BD 2025-06-14'!$A$1:$A$700,'BD 2025-06-14'!$B$1:$B$700) -> MENESES PINEDA JADER ANDREI
A114: 105 | B114: 1144080796 | C114: TALAGA CIFUENTES YEIMY CAROLINA | D114: =IFERROR(VLOOKUP(B114,#REF!,6,0),"ACTIVO") -> ACTIVO | E114: 45524 | F114: =IFERROR(VLOOKUP(B114,#REF!,5,0),"") | G114: 34875 | H114: =+YEARFRAC(G114,TODAY(),1) -> 30.767967 | I114: Femenino | J114: yctalaga@gane.com.co | K114: ASESOR DE VENTAS TANGIBLES | L114: LINEA DE NEGOCIOS | M114: COMERCIAL | N114: SI | O114: SI | P114: Moto | Q114: EFS64D | R114: No | S114: DIEGO JULIAN LATORRE MARTINEZ | T114: 16916223 | U114: 9F2A61107EAC01702 | V114: 152FMHKQ368270 | W114: 2014 | X114: AKT | Y114: 107 | AA114: 41523 | AB114: =IF(AD114<=TODAY(),"Vencida","Vigente") -> Vigente | AC114: =IF(P114="No tiene","No aplica",IF(AD114>$C$6,"Vigente","No Vigente")) -> Vigente | AD114: 46285 | AE114: =IF(AG114<=TODAY(),"Vencida","Vigente") -> Vencida | AF114: =+IF(P114="No tiene","No aplica",IF(AG114>$C$6,"Vigente","No Vigente")) -> Vigente | AG114: 46059 | AH114: A2 | AI114: A2 | AJ114: 47957 | AK114: =+IF(P114="No tiene","No aplica",IF(AJ114>$C$6,"Vigente","No Vigente")) -> Vigente | AM114: =+COUNTIFS(AC114:AK114,"Vigente") -> 3 | AQ114: =+_xlfn.XLOOKUP(B114,'BD 2025-06-14'!$A$1:$A$700,'BD 2025-06-14'!$B$1:$B$700) -> TALAGA CIFUENTES YEIMY CAROLINA
A115: 106 | B115: 1112477767 | C115: CARDONA TREJOS LIEZEL MARYURI | D115: =IFERROR(VLOOKUP(B115,#REF!,6,0),"ACTIVO") -> ACTIVO | E115: 45566 | F115: =IFERROR(VLOOKUP(B115,#REF!,5,0),"") | G115: 33895 | H115: =+YEARFRAC(G115,TODAY(),1) -> 33.450407 | I115: Femenino | J115: lmcardona@gane.com.co | K115: ASESOR DE VENTAS TANGIBLES | L115: LINEA DE NEGOCIOS | M115: COMERCIAL | N115: SI | O115: SI | P115: Moto | Q115: TDE05E | R115: Si | U115: 9FLXCHTC6KCD13275 | V115: 1P50FMHHJ1137951 | W115: 2019 | X115: VICTORY | Y115: 109 | AA115: 43224 | AB115: =IF(AD115<=TODAY(),"Vencida","Vigente") -> Vigente | AC115: =IF(P115="No tiene","No aplica",IF(AD115>$C$6,"Vigente","No Vigente")) -> Vigente | AD115: 46201 | AE115: =IF(AG115<=TODAY(),"Vencida","Vigente") -> Vigente | AF115: =+IF(P115="No tiene","No aplica",IF(AG115>$C$6,"Vigente","No Vigente")) -> Vigente | AG115: 46210 | AH115: A2 | AI115: A2 | AJ115: 47036 | AK115: =+IF(P115="No tiene","No aplica",IF(AJ115>$C$6,"Vigente","No Vigente")) -> Vigente | AM115: =+COUNTIFS(AC115:AK115,"Vigente") -> 4 | AQ115: =+_xlfn.XLOOKUP(B115,'BD 2025-06-14'!$A$1:$A$700,'BD 2025-06-14'!$B$1:$B$700) -> CARDONA TREJOS LIEZEL MARYURI
A116: 107 | B116: 1130645222 | C116: ARANGO CERON GIOVANNY JAVIER | D116: =IFERROR(VLOOKUP(B116,#REF!,6,0),"ACTIVO") -> ACTIVO | E116: 45572 | F116: =IFERROR(VLOOKUP(B116,#REF!,5,0),"") | G116: 31539 | H116: =+YEARFRAC(G116,TODAY(),1) -> 39.902104 | I116: Masculino | J116: gjarango@gane.com.co | K116: ASESOR DE VENTAS TANGIBLES | L116: LINEA DE NEGOCIOS | M116: COMERCIAL | N116: SI | O116: SI | P116: Moto | Q116: TEY37F | R116: Si | U116: 9FLT31604NDD02667 | V116: DE7AN23A0958 | W116: 2022 | X116: TVS | Y116: 159 | AA116: 44411 | AB116: =IF(AD116<=TODAY(),"Vencida","Vigente") -> Vigente | AC116: =IF(P116="No tiene","No aplica",IF(AD116>$C$6,"Vigente","No Vigente")) -> Vigente | AD116: 46239 | AE116: =IF(AG116<=TODAY(),"Vencida","Vigente") -> Vencida | AF116: =+IF(P116="No tiene","No aplica",IF(AG116>$C$6,"Vigente","No Vigente")) -> Vigente | AG116: 46052 | AH116: A2 | AI116: A2 | AJ116: 48981 | AK116: =+IF(P116="No tiene","No aplica",IF(AJ116>$C$6,"Vigente","No Vigente")) -> Vigente | AM116: =+COUNTIFS(AC116:AK116,"Vigente") -> 3 | AQ116: =+_xlfn.XLOOKUP(B116,'BD 2025-06-14'!$A$1:$A$700,'BD 2025-06-14'!$B$1:$B$700) -> ARANGO CERON GIOVANNY JAVIER
A117: 108 | B117: 1114873900 | C117: VASQUEZ TENORIO EDISON ALEJANDRO | D117: =IFERROR(VLOOKUP(B117,#REF!,6,0),"ACTIVO") -> ACTIVO | E117: 45629 | F117: =IFERROR(VLOOKUP(B117,#REF!,5,0),"") | G117: 37373 | H117: =+YEARFRAC(G117,TODAY(),1) -> 23.929471 | I117: Masculino | J117: evasquez@gane.com.co | K117: ASESOR DE VENTAS TANGIBLES | L117: OPERACIONES COMERCIALES | M117: COMERCIAL | N117: SI | O117: SI | P117: Moto | Q117: PBT79C | R117: No | S117: Irne Valencia Martinez | T117: 16880438 | U117: 9FMHA1125CF019001 | V117: HA11EDB9K04490 | W117: 2012 | X117: HONDA | Y117: 97 | AA117: 41015 | AB117: =IF(AD117<=TODAY(),"Vencida","Vigente") -> Vencida | AC117: =IF(P117="No tiene","No aplica",IF(AD117>$C$6,"Vigente","No Vigente")) -> Vigente | AD117: 46011 | AE117: =IF(AG117<=TODAY(),"Vencida","Vigente") -> Vigente | AF117: =+IF(P117="No tiene","No aplica",IF(AG117>$C$6,"Vigente","No Vigente")) -> Vigente | AG117: 46144 | AH117: A2 | AI117: A2 - 13/5/2032 C1 - 13/5/2025 B1 - 13/5/2032 | AJ117: 48347 | AK117: =+IF(P117="No tiene","No aplica",IF(AJ117>$C$6,"Vigente","No Vigente")) -> Vigente | AM117: =+COUNTIFS(AC117:AK117,"Vigente") -> 4 | AQ117: =+_xlfn.XLOOKUP(B117,'BD 2025-06-14'!$A$1:$A$700,'BD 2025-06-14'!$B$1:$B$700) -> VASQUEZ TENORIO EDISON ALEJANDRO
A118: 109 | B118: 1060587765 | C118: ASTAIZA ESPINOSA RONALD | D118: =IFERROR(VLOOKUP(B118,#REF!,6,0),"ACTIVO") -> ACTIVO | E118: 45677 | F118: =IFERROR(VLOOKUP(B118,#REF!,5,0),"") | G118: 32007 | H118: =+YEARFRAC(G118,TODAY(),1) -> 38.620123 | I118: Masculino | J118: rastaiza@gane.com.co | K118: ASESOR DE VENTAS TANGIBLES | L118: LINEA DE NEGOCIOS | M118: COMERCIAL | N118: SI | O118: SI | P118: Moto | Q118: SGS35F | R118: No | S118: ALDA LIBEY ERAZO CORTEZ | T118: 67017350 | U118: 9FMJA2594NF002899 | V118: JA25E4746759 | W118: 2022 | X118: HONDA | Y118: 125 | AA118: 44308 | AB118: =IF(AD118<=TODAY(),"Vencida","Vigente") -> Vigente | AC118: =IF(P118="No tiene","No aplica",IF(AD118>$C$6,"Vigente","No Vigente")) -> Vigente | AD118: 46170 | AE118: =IF(AG118<=TODAY(),"Vencida","Vigente") -> Vigente | AF118: =+IF(P118="No tiene","No aplica",IF(AG118>$C$6,"Vigente","No Vigente")) -> Vigente | AG118: 46195 | AH118: A2 | AI118: A2 | AJ118: 47908 | AK118: =+IF(P118="No tiene","No aplica",IF(AJ118>$C$6,"Vigente","No Vigente")) -> Vigente | AM118: =+COUNTIFS(AC118:AK118,"Vigente") -> 4 | AQ118: =+_xlfn.XLOOKUP(B118,'BD 2025-06-14'!$A$1:$A$700,'BD 2025-06-14'!$B$1:$B$700) -> ASTAIZA ESPINOSA RONALD
A119: 110 | B119: 1111659179 | C119: SILVA VARON JEFFRY STIWAR | D119: =IFERROR(VLOOKUP(B119,#REF!,6,0),"ACTIVO") -> ACTIVO | E119: 45698 | F119: =IFERROR(VLOOKUP(B119,#REF!,5,0),"") | G119: 38059 | H119: =+YEARFRAC(G119,TODAY(),1) -> 22.049994 | I119: Masculino | J119: jssilva@gane.com.co | K119: ASESOR DE VENTAS TANGIBLES | L119: LINEA DE NEGOCIOS | M119: COMERCIAL | N119: SI | O119: SI | P119: Moto | Q119: WDE72D | R119: Si | U119: MBLHA11ADF9X00115 | V119: HA11EFE9K00520 | W119: 2015 | X119: Hero | Y119: 100 | AA119: 42181 | AB119: =IF(AD119<=TODAY(),"Vencida","Vigente") -> Vencida | AC119: =IF(P119="No tiene","No aplica",IF(AD119>$C$6,"Vigente","No Vigente")) -> Vigente | AD119: 45769 | AE119: =IF(AG119<=TODAY(),"Vencida","Vigente") -> Vencida | AF119: =+IF(P119="No tiene","No aplica",IF(AG119>$C$6,"Vigente","No Vigente")) -> Vigente | AG119: 46069 | AH119: A2 | AI119: A2 | AJ119: 48905 | AK119: =+IF(P119="No tiene","No aplica",IF(AJ119>$C$6,"Vigente","No Vigente")) -> Vigente | AM119: =+COUNTIFS(AC119:AK119,"Vigente") -> 3 | AP119: Incapacitado | AQ119: =+_xlfn.XLOOKUP(B119,'BD 2025-06-14'!$A$1:$A$700,'BD 2025-06-14'!$B$1:$B$700) -> SILVA VARON JEFFRY STIWAR
A120: 111 | B120: 1143850032 | C120: GUEVARA ARISTIZABAL YERALDIN | D120: =IFERROR(VLOOKUP(B120,#REF!,6,0),"ACTIVO") -> ACTIVO | E120: 45216 | F120: =IFERROR(VLOOKUP(B120,#REF!,5,0),"") | G120: 34230 | H120: =+YEARFRAC(G120,TODAY(),1) -> 32.535191 | I120: Femenino | J120: yguevara@gane.com.co | K120: ASISTENTE - RIESGOS (MONITOREO) | L120: RIESGOS | M120: GESTION DE RIESGOS | N120: NO | O120: NO | P120: No tiene | AB120: =IF(AD120<=TODAY(),"Vencida","Vigente") -> Vencida | AC120: =IF(P120="No tiene","No aplica",IF(AD120>$C$6,"Vigente","No Vigente")) -> No aplica | AE120: =IF(AG120<=TODAY(),"Vencida","Vigente") -> Vencida | AF120: =+IF(P120="No tiene","No aplica",IF(AG120>$C$6,"Vigente","No Vigente")) -> No aplica | AK120: =+IF(P120="No tiene","No aplica",IF(AJ120>$C$6,"Vigente","No Vigente")) -> No aplica | AM120: =+COUNTIFS(AC120:AK120,"Vigente") -> 0 | AQ120: =+_xlfn.XLOOKUP(B120,'BD 2025-06-14'!$A$1:$A$700,'BD 2025-06-14'!$B$1:$B$700) -> GUEVARA ARISTIZABAL YERALDIN
A121: 112 | B121: 1151943197 | C121: HERNANDEZ HERRERA JOSE EDWIN | D121: =IFERROR(VLOOKUP(B121,#REF!,6,0),"ACTIVO") -> ACTIVO | E121: 43248 | F121: =IFERROR(VLOOKUP(B121,#REF!,5,0),"") | G121: 33538 | H121: =+YEARFRAC(G121,TODAY(),1) -> 34.428474 | I121: Masculino | J121: jehernandez@gane.com.co | K121: ASISTENTE ADMINISTRATIVO TANGIBLES | L121: LINEA DE NEGOCIOS | M121: COMERCIAL | N121: NO | O121: NO | P121: No tiene | AB121: =IF(AD121<=TODAY(),"Vencida","Vigente") -> Vencida | AC121: =IF(P121="No tiene","No aplica",IF(AD121>$C$6,"Vigente","No Vigente")) -> No aplica | AE121: =IF(AG121<=TODAY(),"Vencida","Vigente") -> Vencida | AF121: =+IF(P121="No tiene","No aplica",IF(AG121>$C$6,"Vigente","No Vigente")) -> No aplica | AK121: =+IF(P121="No tiene","No aplica",IF(AJ121>$C$6,"Vigente","No Vigente")) -> No aplica | AM121: =+COUNTIFS(AC121:AK121,"Vigente") -> 0 | AQ121: =+_xlfn.XLOOKUP(B121,'BD 2025-06-14'!$A$1:$A$700,'BD 2025-06-14'!$B$1:$B$700) -> HERNANDEZ HERRERA JOSE EDWIN
A122: 113 | B122: 1005872140 | C122: IPIA CAPOTE JULIAN | D122: =IFERROR(VLOOKUP(B122,#REF!,6,0),"ACTIVO") -> ACTIVO | E122: 44659 | F122: =IFERROR(VLOOKUP(B122,#REF!,5,0),"") | G122: 36807 | H122: =+YEARFRAC(G122,TODAY(),1) -> 25.477794 | I122: Masculino | J122: jipia@gane.com.co | K122: ASISTENTE DE API | L122: SOLUCIONES INFORMATICAS | M122: TIC | N122: NO | O122: NO | P122: No tiene | AB122: =IF(AD122<=TODAY(),"Vencida","Vigente") -> Vencida | AC122: =IF(P122="No tiene","No aplica",IF(AD122>$C$6,"Vigente","No Vigente")) -> No aplica | AE122: =IF(AG122<=TODAY(),"Vencida","Vigente") -> Vencida | AF122: =+IF(P122="No tiene","No aplica",IF(AG122>$C$6,"Vigente","No Vigente")) -> No aplica | AK122: =+IF(P122="No tiene","No aplica",IF(AJ122>$C$6,"Vigente","No Vigente")) -> No aplica | AM122: =+COUNTIFS(AC122:AK122,"Vigente") -> 0 | AQ122: =+_xlfn.XLOOKUP(B122,'BD 2025-06-14'!$A$1:$A$700,'BD 2025-06-14'!$B$1:$B$700) -> IPIA CAPOTE JULIAN
A123: 114 | B123: 1006033735 | C123: BLANDON MONDRAGON ANDRES FELIPE | D123: =IFERROR(VLOOKUP(B123,#REF!,6,0),"ACTIVO") -> ACTIVO | E123: 44840 | F123: =IFERROR(VLOOKUP(B123,#REF!,5,0),"") | G123: 36827 | H123: =+YEARFRAC(G123,TODAY(),1) -> 25.423038 | I123: Masculino | J123: afblandon@gane.com.co | K123: ASISTENTE DE API | L123: SOLUCIONES INFORMATICAS | M123: TIC | N123: NO | O123: NO | P123: No tiene | AB123: =IF(AD123<=TODAY(),"Vencida","Vigente") -> Vencida | AC123: =IF(P123="No tiene","No aplica",IF(AD123>$C$6,"Vigente","No Vigente")) -> No aplica | AE123: =IF(AG123<=TODAY(),"Vencida","Vigente") -> Vencida | AF123: =+IF(P123="No tiene","No aplica",IF(AG123>$C$6,"Vigente","No Vigente")) -> No aplica | AK123: =+IF(P123="No tiene","No aplica",IF(AJ123>$C$6,"Vigente","No Vigente")) -> No aplica | AM123: =+COUNTIFS(AC123:AK123,"Vigente") -> 0 | AQ123: =+_xlfn.XLOOKUP(B123,'BD 2025-06-14'!$A$1:$A$700,'BD 2025-06-14'!$B$1:$B$700) -> BLANDON MONDRAGON ANDRES FELIPE
A124: 115 | B124: 1010127678 | C124: QUINTANA VARGAS KELLY VIVIANA | D124: =IFERROR(VLOOKUP(B124,#REF!,6,0),"ACTIVO") -> ACTIVO | E124: 45078 | F124: =IFERROR(VLOOKUP(B124,#REF!,5,0),"") | G124: 37184 | H124: =+YEARFRAC(G124,TODAY(),1) -> 24.447557 | I124: Femenino | J124: kvquintana@gane.com.co | K124: ASISTENTE DE API | L124: SOLUCIONES INFORMATICAS | M124: TIC | N124: NO | O124: NO | P124: No tiene | AB124: =IF(AD124<=TODAY(),"Vencida","Vigente") -> Vencida | AC124: =IF(P124="No tiene","No aplica",IF(AD124>$C$6,"Vigente","No Vigente")) -> No aplica | AE124: =IF(AG124<=TODAY(),"Vencida","Vigente") -> Vencida | AF124: =+IF(P124="No tiene","No aplica",IF(AG124>$C$6,"Vigente","No Vigente")) -> No aplica | AK124: =+IF(P124="No tiene","No aplica",IF(AJ124>$C$6,"Vigente","No Vigente")) -> No aplica | AM124: =+COUNTIFS(AC124:AK124,"Vigente") -> 0 | AQ124: =+_xlfn.XLOOKUP(B124,'BD 2025-06-14'!$A$1:$A$700,'BD 2025-06-14'!$B$1:$B$700) -> QUINTANA VARGAS KELLY VIVIANA
A125: 116 | B125: 1192794580 | C125: LONDONO FIERRO JOAN STEVEN | D125: =IFERROR(VLOOKUP(B125,#REF!,6,0),"ACTIVO") -> ACTIVO | E125: 45216 | F125: =IFERROR(VLOOKUP(B125,#REF!,5,0),"") | G125: 36922 | H125: =+YEARFRAC(G125,TODAY(),1) -> 25.164912 | I125: Masculino | J125: jlondono@gane.com.co | K125: ASISTENTE DE API | L125: SOLUCIONES INFORMATICAS | M125: TIC | N125: NO | O125: NO | P125: No tiene | AB125: =IF(AD125<=TODAY(),"Vencida","Vigente") -> Vencida | AC125: =IF(P125="No tiene","No aplica",IF(AD125>$C$6,"Vigente","No Vigente")) -> No aplica | AE125: =IF(AG125<=TODAY(),"Vencida","Vigente") -> Vencida | AF125: =+IF(P125="No tiene","No aplica",IF(AG125>$C$6,"Vigente","No Vigente")) -> No aplica | AK125: =+IF(P125="No tiene","No aplica",IF(AJ125>$C$6,"Vigente","No Vigente")) -> No aplica | AM125: =+COUNTIFS(AC125:AK125,"Vigente") -> 0 | AQ125: =+_xlfn.XLOOKUP(B125,'BD 2025-06-14'!$A$1:$A$700,'BD 2025-06-14'!$B$1:$B$700) -> LONDONO FIERRO JOAN STEVEN
A126: 117 | B126: 1105362359 | C126: VARGAS GOMEZ JUAN DAVID | D126: =IFERROR(VLOOKUP(B126,#REF!,6,0),"ACTIVO") -> ACTIVO | E126: 45581 | F126: =IFERROR(VLOOKUP(B126,#REF!,5,0),"") | G126: 38295 | H126: =+YEARFRAC(G126,TODAY(),1) -> 21.40388 | I126: Masculino | J126: jdvargas@gane.com.co | K126: ASISTENTE DE API | L126: SOLUCIONES INFORMATICAS | M126: TIC | N126: NO | O126: NO | P126: No tiene | AB126: =IF(AD126<=TODAY(),"Vencida","Vigente") -> Vencida | AC126: =IF(P126="No tiene","No aplica",IF(AD126>$C$6,"Vigente","No Vigente")) -> No aplica | AE126: =IF(AG126<=TODAY(),"Vencida","Vigente") -> Vencida | AF126: =+IF(P126="No tiene","No aplica",IF(AG126>$C$6,"Vigente","No Vigente")) -> No aplica | AK126: =+IF(P126="No tiene","No aplica",IF(AJ126>$C$6,"Vigente","No Vigente")) -> No aplica | AM126: =+COUNTIFS(AC126:AK126,"Vigente") -> 0 | AQ126: =+_xlfn.XLOOKUP(B126,'BD 2025-06-14'!$A$1:$A$700,'BD 2025-06-14'!$B$1:$B$700) -> VARGAS GOMEZ JUAN DAVID
A127: 118 | B127: 86080045 | C127: JOJOA URBANO WILMER | D127: =IFERROR(VLOOKUP(B127,#REF!,6,0),"ACTIVO") -> ACTIVO | E127: 41352 | F127: =IFERROR(VLOOKUP(B127,#REF!,5,0),"") | G127: 30714 | H127: =+YEARFRAC(G127,TODAY(),1) -> 42.159493 | I127: Masculino | J127: wjojoa@gane.com.co | K127: ASISTENTE DE APLICACIONES | L127: SOLUCIONES INFORMATICAS | M127: TIC | N127: NO | O127: NO | P127: No tiene | AB127: =IF(AD127<=TODAY(),"Vencida","Vigente") -> Vencida | AC127: =IF(P127="No tiene","No aplica",IF(AD127>$C$6,"Vigente","No Vigente")) -> No aplica | AE127: =IF(AG127<=TODAY(),"Vencida","Vigente") -> Vencida | AF127: =+IF(P127="No tiene","No aplica",IF(AG127>$C$6,"Vigente","No Vigente")) -> No aplica | AK127: =+IF(P127="No tiene","No aplica",IF(AJ127>$C$6,"Vigente","No Vigente")) -> No aplica | AM127: =+COUNTIFS(AC127:AK127,"Vigente") -> 0 | AQ127: =+_xlfn.XLOOKUP(B127,'BD 2025-06-14'!$A$1:$A$700,'BD 2025-06-14'!$B$1:$B$700) -> JOJOA URBANO WILMER
A128: 119 | B128: 16846620 | C128: CUERO MOSQUERA JEFFERSON | D128: =IFERROR(VLOOKUP(B128,#REF!,6,0),"ACTIVO") -> ACTIVO | E128: 43571 | F128: =IFERROR(VLOOKUP(B128,#REF!,5,0),"") | G128: 30411 | H128: =+YEARFRAC(G128,TODAY(),1) -> 42.989733 | I128: Masculino | J128: jcuero@gane.com.co | K128: ASISTENTE DE APLICACIONES | L128: SOLUCIONES INFORMATICAS | M128: TIC | N128: NO | O128: NO | P128: No tiene | AB128: =IF(AD128<=TODAY(),"Vencida","Vigente") -> Vencida | AC128: =IF(P128="No tiene","No aplica",IF(AD128>$C$6,"Vigente","No Vigente")) -> No aplica | AE128: =IF(AG128<=TODAY(),"Vencida","Vigente") -> Vencida | AF128: =+IF(P128="No tiene","No aplica",IF(AG128>$C$6,"Vigente","No Vigente")) -> No aplica | AK128: =+IF(P128="No tiene","No aplica",IF(AJ128>$C$6,"Vigente","No Vigente")) -> No aplica | AM128: =+COUNTIFS(AC128:AK128,"Vigente") -> 0 | AQ128: =+_xlfn.XLOOKUP(B128,'BD 2025-06-14'!$A$1:$A$700,'BD 2025-06-14'!$B$1:$B$700) -> CUERO MOSQUERA JEFFERSON
A129: 120 | B129: 1143993427 | C129: DURAN ORTEGA DANNA ALEJANDRA | D129: =IFERROR(VLOOKUP(B129,#REF!,6,0),"ACTIVO") -> ACTIVO | E129: 44034 | F129: =IFERROR(VLOOKUP(B129,#REF!,5,0),"") | G129: 36037 | H129: =+YEARFRAC(G129,TODAY(),1) -> 27.587236 | I129: Femenino | J129: daduran@gane.com.co | K129: ASISTENTE DE APLICACIONES | L129: SOLUCIONES INFORMATICAS | M129: TIC | N129: NO | O129: NO | P129: No tiene | AB129: =IF(AD129<=TODAY(),"Vencida","Vigente") -> Vencida | AC129: =IF(P129="No tiene","No aplica",IF(AD129>$C$6,"Vigente","No Vigente")) -> No aplica | AE129: =IF(AG129<=TODAY(),"Vencida","Vigente") -> Vencida | AF129: =+IF(P129="No tiene","No aplica",IF(AG129>$C$6,"Vigente","No Vigente")) -> No aplica | AK129: =+IF(P129="No tiene","No aplica",IF(AJ129>$C$6,"Vigente","No Vigente")) -> No aplica | AM129: =+COUNTIFS(AC129:AK129,"Vigente") -> 0 | AQ129: =+_xlfn.XLOOKUP(B129,'BD 2025-06-14'!$A$1:$A$700,'BD 2025-06-14'!$B$1:$B$700) -> DURAN ORTEGA DANNA ALEJANDRA
A130: 121 | B130: 1107510619 | C130: GONZALEZ TORRES BRAYAN STEVEN | D130: =IFERROR(VLOOKUP(B130,#REF!,6,0),"ACTIVO") -> ACTIVO | E130: 44127 | F130: =IFERROR(VLOOKUP(B130,#REF!,5,0),"") | G130: 35601 | H130: =+YEARFRAC(G130,TODAY(),1) -> 28.781601 | I130: Masculino | J130: bsgonzalez@gane.com.co | K130: ASISTENTE DE APLICACIONES | L130: SOLUCIONES INFORMATICAS | M130: TIC | N130: NO | O130: NO | P130: No tiene | AB130: =IF(AD130<=TODAY(),"Vencida","Vigente") -> Vencida | AC130: =IF(P130="No tiene","No aplica",IF(AD130>$C$6,"Vigente","No Vigente")) -> No aplica | AE130: =IF(AG130<=TODAY(),"Vencida","Vigente") -> Vencida | AF130: =+IF(P130="No tiene","No aplica",IF(AG130>$C$6,"Vigente","No Vigente")) -> No aplica | AK130: =+IF(P130="No tiene","No aplica",IF(AJ130>$C$6,"Vigente","No Vigente")) -> No aplica | AM130: =+COUNTIFS(AC130:AK130,"Vigente") -> 0 | AQ130: =+_xlfn.XLOOKUP(B130,'BD 2025-06-14'!$A$1:$A$700,'BD 2025-06-14'!$B$1:$B$700) -> GONZALEZ TORRES BRAYAN STEVEN
A131: 122 | B131: 1144064036 | C131: ARCINIEGAS QUIROGA LUIS ALFONSO | D131: =IFERROR(VLOOKUP(B131,#REF!,6,0),"ACTIVO") -> ACTIVO | E131: 44673 | F131: =IFERROR(VLOOKUP(B131,#REF!,5,0),"") | G131: 34202 | H131: =+YEARFRAC(G131,TODAY(),1) -> 32.611854 | I131: Masculino | J131: laarciniegas@gane.com.co | K131: ASISTENTE DE APLICACIONES | L131: SOLUCIONES INFORMATICAS | M131: TIC | N131: NO | O131: NO | P131: No tiene | AB131: =IF(AD131<=TODAY(),"Vencida","Vigente") -> Vencida | AC131: =IF(P131="No tiene","No aplica",IF(AD131>$C$6,"Vigente","No Vigente")) -> No aplica | AE131: =IF(AG131<=TODAY(),"Vencida","Vigente") -> Vencida | AF131: =+IF(P131="No tiene","No aplica",IF(AG131>$C$6,"Vigente","No Vigente")) -> No aplica | AK131: =+IF(P131="No tiene","No aplica",IF(AJ131>$C$6,"Vigente","No Vigente")) -> No aplica | AM131: =+COUNTIFS(AC131:AK131,"Vigente") -> 0 | AQ131: =+_xlfn.XLOOKUP(B131,'BD 2025-06-14'!$A$1:$A$700,'BD 2025-06-14'!$B$1:$B$700) -> ARCINIEGAS QUIROGA LUIS ALFONSO
... A136: 127 | B136: 1144160016 | C136: DUQUE ECHEVERRY LINDA TATIANA | D136: =IFERROR(VLOOKUP(B136,#REF!,6,0),"ACTIVO") -> ACTIVO | E136: 44014 | F136: =IFERROR(VLOOKUP(B136,#REF!,5,0),"") | G136: 33804 | H136: =+YEARFRAC(G136,TODAY(),1) -> 33.699546 | I136: Femenino | J136: lduque@gane.com.co | K136: ASISTENTE DE AUDITORIA | L136: AUDITORIA | M136: AUDITORIA | N136: NO | O136: NO | P136: No tiene | AB136: =IF(AD136<=TODAY(),"Vencida","Vigente") -> Vencida | AC136: =IF(P136="No tiene","No aplica",IF(AD136>$C$6,"Vigente","No Vigente")) -> No aplica | AE136: =IF(AG136<=TODAY(),"Vencida","Vigente") -> Vencida | AF136: =+IF(P136="No tiene","No aplica",IF(AG136>$C$6,"Vigente","No Vigente")) -> No aplica | AK136: =+IF(P136="No tiene","No aplica",IF(AJ136>$C$6,"Vigente","No Vigente")) -> No aplica | AM136: =+COUNTIFS(AC136:AK136,"Vigente") -> 0 | AQ136: =+_xlfn.XLOOKUP(B136,'BD 2025-06-14'!$A$1:$A$700,'BD 2025-06-14'!$B$1:$B$700) -> DUQUE ECHEVERRY LINDA TATIANA
...

Sheet Conductores
A1: BASE DE DATOS REVISIÓN TECNICO MECANICA Y SOAT | CC1: =TODAY() -> 46113
A2: No. | D2: IDENTIFICACIÓN | E2: NOMBRE | F2: FECHA DE NACIMIENTO | G2: GENERO | H2: ESCOLARIDAD | I2: EDAD | J2: ESTADO CIVIL | K2: CARGO | L2: DEPARTAMENTO | M2: FECHA DE INGRESO A LA EMPRESA | N2: ANTIGÜEDAD (AÑOS) | P2: TIPO DE VEHÍCULO QUE CONDUCE EN MISIÓN O LABOR | Q2: CATEGORIA DE LICENCIA PARA LA LABOR | R2: VIGENCIA LICENCIA PARA LA LABOR | S2: ESTADO DE LICENCIA PARA LA LABOR | T2: FECHA DISCIPLINARIOS | V2: PLACA | W2: NUMERO VIN | X2: NUMERO MOTOR | Y2: MODELO | Z2: MARCA | AA2: CILINDRAJE | AB2: KILOMETRAJE | AC2: FECHA DE MATRICULA | AD2: TIPO | AE2: ¿ES PROPIETARIO? | AF2: PROPIETARIO ACTUAL | AH2: PORCENTAJE BENEFICIO | AJ2: REVISIÓN TECNICO MECANICA | AM2: SOAT | AP2: LICENCIA DE CONDUCCIÓN | AS2: SINIESTROS VIALES EN MISION ULTIMOS 5 AÑOS EN LA LABOR | AT2: CANTIDAD DE SINIESTROS | AU2: MULTAS | AV2: TIPO DE INFRACCIÓN | AW2: ESTADO DE PAGO DE INFRACCIONES | AX2: CAPACITACIONES Y EVALUACIÓN ANUAL SEGURIDAD VIAL | AY2: CAPACITACIÓN PLAN DE EMERGENCIA VIAL | AZ2: TIPO DE VEHÍCULO USO CASA-TRABAJO | BA2: SINIESTROS VIALES CASA A TRABAJO ULTIMOS 5 AÑOS | BB2: CANTIDAD | BC2: OBSERVACIONES OTRAS LICENCIAS | BD2: OBSERVACIONES
T3: SANCIONES | U3: LLAMADOS DE ATENCIÓN | AF3: NOMBRE | AG3: IDENTIFICACIÓN | AH3: SOAT | AI3: RTM | AJ3: ESTADO ACTUAL | AK3: FECHA VENCIMIENTO | AL3: FECHA EJECUCIÓN | AM3: ESTADO ACTUAL | AN3: FECHA VENCIMIENTO | AO3: FECHA EJECUCIÓN | AP3: CATEGORIA | AQ3: FECHA VENCIMIENTO | AR3: ESTADO ACTUAL
A4: 1 | D4: 84451541 | E4: Abella Ramos Jorge Jose | F4: 30248 | G4: MASCULINO | I4: =(CC$1-F4)/365 -> 43.465753 | K4: Auxiliar Operativo - Comercial (Tangibles) | L4: Comercial | M4: 45006 | N4: =(CC$1-M4)/365 -> 3.0328767 | O4: 3052967867 | V4: WVY19D | W4: 9F2B81252GA006082 | X4: 157FMINQ152029 | Y4: 2016 | Z4: AKT | AA4: 125 | AC4: 42298 | AD4: Moto | AE4: Si | AH4: 0.5 | AI4: 1 | AJ4: =IF(AK4>TODAY(),"Vigente","No Vigente") -> No Vigente | AK4: =(AL4+365) -> 45340 | AL4: 44975 | AM4: =IF(AN4>TODAY(),"Vigente","No Vigente") -> No Vigente | AN4: =(AO4+365) -> 45333 | AO4: 44968 | AP4: A2 | AQ4: 45972 | AR4: =IF(AQ4>TODAY(),"Vigente","No Vigente") -> No Vigente | BC4: Tiene licencia B1 (22/10/2023) y C1(22/10/2023) | BD4: Retirado
A5: 2 | D5: 1005943971 | E5: Acevedo Hernandez Aymer Arley | F5: 35204 | G5: MASCULINO | H5: Bachiller academico | I5: =(CC$1-F5)/365 -> 29.887671 | J5: Soltero | K5: Asesor de venta | L5: Comercial | M5: 44062 | N5: =(CC$1-M5)/365 -> 5.6191781 | O5: 312 888 5751 | P5: MOTOCICLETA | Q5: A2 | R5: 47094 | S5: Vigente | T5: 0 | U5: 0 | V5: WVN58E | W5: 9G5JAR056JVHK033 | X5: 9G5JAR056JVHK0033 | Y5: 2018 | Z5: Hero | AA5: 125 | AC5: 43375 | AD5: Moto | AE5: Si | AH5: 0.5 | AI5: 1 | AJ5: Vigente | AK5: 45453 | AL5: 45087 | AM5: Vigente | AN5: 10/16/2024 | AO5: 45215 | AP5: A2 | AQ5: 47094 | AR5: =IF(AQ5>TODAY(),"Vigente","No Vigente") -> Vigente | AU5: No tiene multas | AV5: No | AW5: No | BC5: Retirado | BD5: Retirado
A6: 3 | D6: 16722977 | E6: Agudelo Salazar Jhon Fernando | F6: 23966 | G6: MASCULINO | H6: Tecnico profesional en ingenieria en sistemas | I6: =(CC$1-F6)/365 -> 60.676712 | J6: Casado | K6: Técnico de Soporte | L6: TIC´s | M6: 38874 | N6: =(CC$1-M6)/365 -> 19.832877 | O6: 320 520 8968 | P6: MOTOCICLETA | Q6: A2 | R6: 45097 | S6: Vencida | T6: 2 | V6: LIX28E | W6: 9G5HA11A3HV009618 | X6: HA11EJG9H06606 | Y6: 2017 | Z6: Hero | AA6: 98 | AC6: 42812 | AD6: Moto | AE6: si | AH6: NO APLICA | AI6: NO APLICA | AJ6: =IF(AK6>TODAY(),"Vigente","No Vigente") -> No Vigente | AK6: 45955 | AL6: 45590 | AM6: =IF(AN6>TODAY(),"Vigente","No Vigente") -> No Vigente | AN6: 45951 | AO6: 45587 | AP6: A2 | AQ6: 45097 | AR6: =IF(AQ6>TODAY(),"Vigente","No Vigente") -> No Vigente | AU6: Si | AV6: D02 Conducir sin portar el seguro obligatorio de accidentes de transito. | AW6: Multa del: 21/12/2021 se ecuenta con cobro coactivo - Multa del 25/08/2023 pendiente para pago. | BC6: Restricciones medico laboral para ejercer funciones en motocicleta | BD6: No ha enviado información.
A7: 4 | D7: 71185148 | E7: Aguiar Medardo Alcides | F7: 24353 | G7: MASCULINO | H7: Tecnologo electrico | I7: =(CC$1-F7)/365 -> 59.616438 | J7: Unión Libre | K7: Lider de Ventas | L7: Comercial | M7: 39470 | N7: =(CC$1-M7)/365 -> 18.2 | O7: 315 525 2674 | P7: MOTOCICLETA | Q7: A2 | R7: 45097 | S7: Vencida | T7: 0 | U7: 0 | AD7: Moto | AH7: NO APLICA | AI7: NO APLICA | AJ7: =IF(AK7>TODAY(),"Vigente","No Vigente") -> No Vigente | AK7: =(AL7+365) -> 365 | AM7: =IF(AN7>TODAY(),"Vigente","No Vigente") -> No Vigente | AN7: =(AO7+365) -> 365 | AQ7: 45097 | AR7: =IF(AQ7>TODAY(),"Vigente","No Vigente") -> No Vigente | BC7: Restricciones medico laboral para ejercer funciones en motocicleta | BD7: No ha enviado información.
A8: 5 | D8: 1112476996 | E8: Aguilar Yina Paola | F8: 33886 | G8: FEMENINO | H8: Bachiller academico | I8: =(CC$1-F8)/365 -> 33.49863 | J8: Soltera | K8: Auxiliar Operativo de Recaudo | L8: Financiero | M8: 43587 | N8: =(CC$1-M8)/365 -> 6.9205479 | O8: 316 256 6801 - 3115242212 | P8: MOTOCICLETA | Q8: A2 | R8: 47902 | S8: Vigente | T8: 0 | V8: GKG13F | W8: 9F2C1125XL5008593 | X8: ZS154FMI-38L104874 | Y8: 2020 | Z8: AKT | AA8: 124 | AC8: 43811 | AD8: Moto | AE8: SI | AH8: NO APLICA | AI8: NO APLICA | AJ8: =IF(AK8>TODAY(),"Vigente","No Vigente") -> No Vigente | AK8: 45820 | AL8: 45455 | AM8: =IF(AN8>TODAY(),"Vigente","No Vigente") -> No Vigente | AN8: 45784 | AO8: 45420 | AP8: A2 | AQ8: 47902 | AR8: =IF(AQ8>TODAY(),"Vigente","No Vigente") -> Vigente | AU8: No tiene multas. | BC8: Debe conducir con lentes | BD8: Se actualiza manualmente información.
A9: 6 | D9: 94521502 | E9: Aguirre Bedoya Ivan Dario | F9: 28706 | G9: MASCULINO | I9: =(CC$1-F9)/365 -> 47.690411 | K9: Mensajero - Comercial | L9: Comercial | M9: 44572 | N9: =(CC$1-M9)/365 -> 4.2219178 | O9: 315 412 7343 | P9: MOTOCICLETA | Q9: A2 | R9: 46926 | S9: Vigente | T9: 0 | U9: 0 | V9: JEP16G | W9: 9G5HAR023PVNH0372 | X9: HA11EPM9M03300 | Y9: 2023 | Z9: Hero | AA9: 98 | AC9: 44842 | AD9: Moto | AE9: Si | AH9: 0.5 | AI9: 1 | AJ9: =IF(AK9>TODAY(),"Vigente","No Vigente") -> No Vigente | AK9: 45879 | AL9: 45207 | AM9: Vigente | AN9: =(AO9+365) -> 45572 | AO9: 45207 | AP9: A2 | AQ9: 46926 | AR9: =IF(AQ9>TODAY(),"Vigente","No Vigente") -> Vigente | AU9: Actualmente no tiene multas | BC9: Licencia B1 (29/09/2023) | BD9: Retirado
A10: 7 | D10: 1007544618 | E10: Alvarado Diaz Sebastian | F10: 37128 | G10: MASCULINO | I10: =(CC$1-F10)/365 -> 24.616438 | K10: Entrenador Comercial | L10: Comercial | M10: 44702 | N10: =(CC$1-M10)/365 -> 3.8657534 | O10: 313 616 2352 | P10: MOTOCICLETA | Q10: A2 | R10: 44313 | S10: Vigente | T10: 0 | U10: 0 | V10: CLK30G | W10: 9FMJA2590PF002207 | X10: JA25E-4903374 | Y10: 2023 | Z10: Honda | AA10: 124 | AC10: 44624 | AD10: Moto | AE10: Si | AH10: 0.5 | AI10: 1 | AJ10: =IF(AK10>TODAY(),"Vigente","No Vigente") -> No Vigente | AK10: 45720 | AL10: 45355 | AM10: Vigente | AN10: 45719 | AO10: 45353 | AP10: A2 | AQ10: 47965 | AR10: =IF(AQ10>TODAY(),"Vigente","No Vigente") -> Vigente | AU10: Actualmente no tiene multas
A11: 8 | D11: 14637323 | E11: Álvarez Urrutia Jhonathan | F11: 30854 | G11: MASCULINO | H11: Bachiller tecnico | I11: =(CC$1-F11)/365 -> 41.805479 | J11: Union libre | K11: Auxiliar Operativo de Recaudo | L11: Financiero | M11: 39517 | N11: =(CC$1-M11)/365 -> 18.071233 | O11: 318 734 7605 | P11: MOTOCICLETA | Q11: A2 - B1 | R11: A1 03/01/2024 - B1 31/01/2032 | S11: Vigente | T11: 0 | U11: 0 | V11: YMS87E | W11: 9FMKD0729KF015160 | X11: KD07E2380950 | Y11: 2019 | Z11: Honda | AA11: 149 | AC11: 43475 | AD11: Moto | AE11: No | AF11: Fernández Benítez María Elena | AG11: 31307215 | AH11: 0.5 | AI11: 1 | AJ11: =IF(AK11>TODAY(),"Vigente","No Vigente") -> No Vigente | AK11: 45682 | AL11: 45316 | AM11: =IF(AN11>TODAY(),"Vigente","No Vigente") -> No Vigente | AN11: =(AO11+365) -> 45669 | AO11: 45304 | AP11: A2 | AQ11: 48947 | AR11: =IF(AQ11>TODAY(),"Vigente","No Vigente") -> Vigente | AU11: No tiene multas. | BC11: Tiene licencia B1 (31/1/2032) | BD11: Se actualiza manualmente información.
A12: 9 | D12: 1085549105 | E12: Anchico Micolta Hember Alonso | F12: 35383 | G12: MASCULINO | I12: =(CC$1-F12)/365 -> 29.39726 | J12: Casado | K12: Auxiliar Operativo - Seguridad | L12: Financiero | M12: 44886 | N12: =(CC$1-M12)/365 -> 3.3616438 | O12: 323 286 0404 | P12: MOTOCICLETA | Q12: A2 | R12: 47436 | S12: Vigente | T12: 0 | U12: 0 | V12: HMT63F | W12: 9FLA37CY9LAL22705 | X12: JEZWKD24761 | Y12: 2020 | Z12: Bajaj | AA12: 124 | AC12: 43803 | AD12: Moto | AE12: Si | AH12: 0.5 | AI12: 1 | AJ12: =IF(AK12>TODAY(),"Vigente","No Vigente") -> No Vigente | AK12: 45762 | AL12: 45000 | AM12: Vigente | AN12: 45647 | AO12: 45282 | AP12: A2 | AQ12: 47436 | AR12: =IF(AQ12>TODAY(),"Vigente","No Vigente") -> Vigente | AU12: Actualmente no tiene multas | BD12: Retirado
A13: 10 | D13: 2518120 | E13: Angel Palacio Ariel | F13: 24197 | G13: MASCULINO | I13: =(CC$1-F13)/365 -> 60.043836 | J13: Unión Libre | K13: Auxiliar Operativo de Recaudo | L13: Financiero | M13: 39476 | N13: =(CC$1-M13)/365 -> 18.183562 | O13: 318 682 7886 | P13: MOTOCICLETA | Q13: A2 | R13: 45454 | S13: Vigente | T13: 0 | U13: 0 | V13: XBM53F | W13: 9GJA37JE8NT007809 | X13: JEXWML38080 | Y13: 2022 | Z13: Bajaj | AA13: 125 | AC13: 44433 | AD13: Moto | AE13: Si | AH13: 0.5 | AI13: 1 | AJ13: =IF(AK13>TODAY(),"Vigente","No Vigente") -> No Vigente | AK13: 45901 | AL13: 45536 | AM13: =IF(AN13>TODAY(),"Vigente","No Vigente") -> No Vigente | AN13: 45898 | AO13: 45534 | AP13: A2 | AQ13: 45454 | AR13: =IF(AQ13>TODAY(),"Vigente","No Vigente") -> No Vigente | AU13: Actualmente no tiene multas | BC13: Le renovaron la licencia de conducción por un año por criterio médico (Se vence el 11 Junio 2024) | BD13: Se actualiza manualmente información.
A14: 11 | D14: 16926534 | E14: Angulo Angel Fernando | F14: 29457 | G14: MASCULINO | H14: Tecnologo Industrial | I14: =(CC$1-F14)/365 -> 45.632877 | J14: Unión Libre | K14: Auxiliar Operativo - Logistica (Mantenimiento) | L14: Administrativo | M14: 44175 | N14: =(CC$1-M14)/365 -> 5.309589 | O14: 3113313059 | P14: AUTOMOVIL | Q14: C1 | R14: 46096 | S14: Vigente | T14: 0 | U14: 0 | V14: LII59E | W14: 9FLA66DZ4HBM11480 | X14: JEZCFF50590 | Y14: 2017 | Z14: Bajaj | AA14: 149 | AC14: 42803 | AD14: Moto | AE14: Si | AH14: NO APLICA | AI14: NO APLICA | AJ14: Vigente | AK14: 45725 | AL14: 45360 | AM14: =IF(AN14>TODAY(),"Vigente","No Vigente") -> No Vigente | AN14: 45724 | AO14: 45360 | AP14: C1 | AQ14: 46096 | AR14: =IF(AQ14>TODAY(),"Vigente","No Vigente") -> No Vigente | AU14: Actualmente no tiene multas | BC14: Tiene licencia B1 (29/11/2036) Inactiva Tiene Licencia A2 (20/06/2023) Inactiva | BD14: Se actualiza manualmente información.
A15: 12 | D15: 1130654473 | E15: Arango Loaiza Pedro Julio | F15: 32026 | G15: MASCULINO | I15: =(CC$1-F15)/365 -> 38.594521 | K15: Auxiliar Operativo de Recaudo | L15: Financiero | M15: 44991 | N15: =(CC$1-M15)/365 -> 3.0739726 | O15: 3186827854 | P15: MOTOCICLETA | Q15: A2 | R15: 48759 | S15: Vigente | T15: 0 | U15: 0 | V15: NJI21F | W15: 9FMJA259XMF017096 | X15: JA25E-4650054 | Y15: 2021 | Z15: Honda | AA15: 124 | AC15: 44153 | AD15: Moto | AE15: Si | AH15: 0.5 | AI15: 1 | AJ15: =IF(AK15>TODAY(),"Vigente","No Vigente") -> Vigente | AK15: 11/18/2024 | AL15: 45248 | AM15: =IF(AN15>TODAY(),"Vigente","No Vigente") -> No Vigente | AN15: 45614 | AO15: 45249 | AP15: A2 | AQ15: 48759 | AR15: =IF(AQ15>TODAY(),"Vigente","No Vigente") -> Vigente | AU15: Actualmente no tiene multas | BD15: Se actualiza manualmente información.
A16: 13 | D16: 1144126097 | E16: Aranzalez Lasso Estiven | F16: 32757 | G16: MASCULINO | I16: =(CC$1-F16)/365 -> 36.591781 | J16: Unión Libre | K16: Lider de Ventas | L16: Comercial | M16: 38914 | N16: =(CC$1-M16)/365 -> 19.723288 | O16: 315 799 9658 | P16: AUTOMOVIL-MOTOCICLETA- CAMIONETA - MICROBUS | Q16: A2 - B1 - C1 | R16: A2 (23/06/2033) B1 (13-02-2034) C1 (13-02-2027) | S16: Vigente | T16: 0 | U16: 0 | V16: LII10E | W16: 9FLA18AZ6HAB84137 | X16: DUZWGH12096 | Y16: 2017 | Z16: BAJAJ | AA16: 99 | AC16: 28/02/2017 | AD16: Moto | AE16: No | AF16: OLGA YANETH ARANZALEZ LASSO | AG16: 29113571 | AH16: 0.25 | AI16: 0.5 | AJ16: =IF(AK16>TODAY(),"Vigente","No Vigente") -> No Vigente | AK16: 45707 | AL16: 45341 | AM16: =IF(AN16>TODAY(),"Vigente","No Vigente") -> No Vigente | AN16: =(AO16+365) -> 45725 | AO16: 45360 | AP16: A2, B1, C1 | AQ16: A2 (23/06/2033) B1 (13-02-2034) C1 (13-02-2027) | AR16: =IF(AQ16>TODAY(),"Vigente","No Vigente") -> Vigente | AU16: Actualmente no tiene multas | BD16: Se actualiza manualmente información.
A17: 14 | D17: 16721232 | E17: Arboleda Valencia Leon Angel | F17: 24113 | G17: MASCULINO | H17: Bachiller Tecnico | I17: =(CC$1-F17)/365 -> 60.273973 | J17: Unión Libre | K17: Supervisor | L17: Comercial | M17: 38877 | N17: =(CC$1-M17)/365 -> 19.824658 | O17: 318 682 7848 | P17: MOTOCICLETA | Q17: A2 | R17: 48043 | S17: Vigente | T17: 0 | U17: 0 | V17: LAQ90C | W17: 9F2B11252CE214096 | X17: 157FMIJE355749 | Y17: 2013 | Z17: AKT | AA17: 124 | AC17: 41038 | AD17: Moto | AE17: No | AF17: José Edwin Alzate Rengifo | AG17: 1112470502 | AH17: NO APLICA | AI17: NO APLICA | AJ17: =IF(AK17>TODAY(),"Vigente","No Vigente") -> No Vigente | AK17: 45574 | AL17: 45208 | AM17: =IF(AN17>TODAY(),"Vigente","No Vigente") -> No Vigente | AN17: 45714 | AO17: 45349 | AP17: A2 | AQ17: 48043 | AR17: =IF(AQ17>TODAY(),"Vigente","No Vigente") -> Vigente | AU17: Actualmente no tiene multas | BD17: Se actualiza manualmente información.
A18: 15 | D18: 16797984 | E18: Arias Diego Alejandro | F18: 26291 | G18: MASCULINO | H18: Auxiliar de refrigeración - Tecnico electricista y residencial | I18: =(CC$1-F18)/365 -> 54.306849 | J18: Unión Libre | K18: Auxiliar Operativo - Logistica (Mantenimiento) | L18: Administrativo | M18: 42816 | N18: =(CC$1-M18)/365 -> 9.0328767 | O18: 310 400 8182 | P18: MOTOCICLETA | Q18: A2 | R18: 48788 | S18: Vigente | T18: 0 | U18: 0 | V18: OCR55D | W18: 9FKKG0625F2032813 | X18: 1SV1032813 | Y18: 2015 | Z18: Yamaha | AA18: 153 | AC18: 41885 | AD18: Moto | AE18: No | AF18: Maria Lucenid Gonzalez Bustamante | AG18: 31220075 | AH18: 0.5 | AI18: 1 | AJ18: =IF(AK18>TODAY(),"Vigente","No Vigente") -> No Vigente | AK18: =(AL18+365) -> 45821 | AL18: 45456 | AM18: =IF(AN18>TODAY(),"Vigente","No Vigente") -> No Vigente | AN18: =(AO18+365) -> 45916 | AO18: 45551 | AP18: A2 | AQ18: 48788 | AR18: =IF(AQ18>TODAY(),"Vigente","No Vigente") -> Vigente | AU18: Actualmente no tiene multas | BD18: Se actualiza manualmente información.
A19: 16 | D19: 1143838364 | E19: Arteaga Henao Jesus David | F19: 33408 | G19: MASCULINO | I19: =(CC$1-F19)/365 -> 34.808219 | K19: Auxiliar De Ventas (Tangibles) | L19: Comercial | M19: 45006 | N19: =(CC$1-M19)/365 -> 3.0328767 | O19: 3042174916 | V19: MMB15G | W19: 9FKUE1614R2080366 | X19: E3S9E0080366 | Y19: 2024 | Z19: Yamaha | AA19: 114 | AC19: 44972 | AD19: Moto | AE19: Si | AH19: 0.5 | AI19: 1 | AJ19: =IF(AK19>TODAY(),"Vigente","No Vigente") -> No Vigente | AK19: =(AL19+365) -> 45337 | AL19: 44972 | AM19: =IF(AN19>TODAY(),"Vigente","No Vigente") -> No Vigente | AN19: =(AO19+365) -> 45337 | AO19: 44972 | AP19: A2 | AQ19: 48616 | AR19: =IF(AQ19>TODAY(),"Vigente","No Vigente") -> Vigente | AU19: No tiene multas. | BD19: Retirado
A20: 17 | D20: 1144176714 | E20: Artiaga Gomez Jairo Alejandro | F20: 34368 | G20: MASCULINO | I20: =(CC$1-F20)/365 -> 32.178082 | J20: Unión Libre | K20: Auxiliar de ventas (Tangibles) | L20: Comercial | M20: 44474 | N20: =(CC$1-M20)/365 -> 4.490411 | O20: 321 827 2487 | P20: MOTOCICLETA | Q20: A2 | R20: 45644 | S20: Vigente | T20: 0 | U20: 0 | V20: LKA36E | W20: 9FMKC2313HF000948 | X20: KC23E-7-3001472 | Y20: 2017 | Z20: Honda | AA20: 162 | AC20: 42891 | AD20: Moto | AE20: No | AF20: Beatriz Elena Gomez Mejia | AG20: 31904462 | AH20: 0.5 | AI20: 1 | AJ20: =IF(AK20>TODAY(),"Vigente","No Vigente") -> No Vigente | AK20: 45639 | AL20: 45273 | AM20: =IF(AN20>TODAY(),"Vigente","No Vigente") -> No Vigente | AN20: 45582 | AO20: 45217 | AP20: A2 | AQ20: 45644 | AR20: =IF(AQ20>TODAY(),"Vigente","No Vigente") -> No Vigente | AU20: Actualmente no tiene multas | BD20: Se actualiza manualmente información.
A21: 18 | D21: 1114089773 | E21: Atehortua Arcila Daniel Alberto | F21: 32122 | G21: MASCULINO | H21: Tecnico en dibujo tecnico | I21: =(CC$1-F21)/365 -> 38.331507 | J21: Soltero | K21: Auxiliar Operativo de Recaudo | L21: Financiero | M21: 43328 | N21: =(CC$1-M21)/365 -> 7.630137 | O21: 316 877 2706 | P21: AUTOMOVIL-MOTOCICLETA- CAMIONETA - MICROBUS | Q21: A2, B1, C1 | R21: A2 (06/02/2034) B1 (04/03/2034) C1 (04/03/2027) | S21: Vigente | T21: 0 | U21: 0 | V21: HXJ16E | W21: 9FLA55FZ7HBH00821 | X21: JLZCGA26252 | Y21: 2017 | Z21: BAJAJ | AA21: 199 | AB21: 44143 | AC21: 42625 | AD21: Moto | AE21: SI | AH21: 0.5 | AI21: 1 | AJ21: =IF(AK21>TODAY(),"Vigente","No Vigente") -> No Vigente | AK21: 45776 | AL21: 45411 | AM21: =IF(AN21>TODAY(),"Vigente","No Vigente") -> No Vigente | AN21: 45766 | AO21: 45402 | AP21: A2, B1, C1 | AQ21: A2 (06/02/2034) B1 (04/03/2034) C1 (04/03/2027) | AR21: =IF(AQ21>TODAY(),"Vigente","No Vigente") -> Vigente | AU21: Actualmente no tiene multas | BC21: Licencia A2 (06/02/2034) Licencia B1 (04/03/2034) Licencia C1 (04/03/2027) | BD21: Se actualiza manualmente información.
A22: 19 | D22: 1118289579 | E22: Ayala Moreno Jhojan Stiven | F22: 32216 | G22: MASCULINO | H22: Bachiller Tecnico | I22: =(CC$1-F22)/365 -> 38.073973 | J22: Casado | K22: Auxiliar Operativo (Mantenimiento) | L22: Administrativo | M22: 40759 | N22: =(CC$1-M22)/365 -> 14.668493 | O22: 315 670 2501 | P22: MOTOCICLETA | Q22: A2 | R22: 45849 | S22: Vigente | T22: 0 | U22: 0 | V22: LJW27E | W22: 9FLA18AZ2JCE97258 | X22: DUZWGH28765 | Y22: 2018 | Z22: Bajaj | AA22: 99 | AC22: 42892 | AD22: Moto | AE22: Si | AH22: 0.5 | AI22: 1 | AJ22: =IF(AK22>TODAY(),"Vigente","No Vigente") -> No Vigente | AK22: 45815 | AL22: 45450 | AM22: =IF(AN22>TODAY(),"Vigente","No Vigente") -> No Vigente | AN22: 45831 | AO22: 45467 | AP22: A2 | AQ22: 45849 | AR22: =IF(AQ22>TODAY(),"Vigente","No Vigente") -> No Vigente | AU22: Actualmente no tiene multas | BD22: Se actualiza manualmente información.
A23: 20 | D23: 16733826 | E23: Barco Cárdenas Rodrigo | F23: 24453 | G23: MASCULINO | H23: Bachiller | I23: =(CC$1-F23)/365 -> 59.342466 | J23: Casado | K23: Auxiliar Operativo de Recaudo | L23: Financiero | M23: 39995 | N23: =(CC$1-M23)/365 -> 16.761644 | O23: 318 682 7894 | P23: AUTOMOVIL-MOTOCICLETA- CAMIONETA - MICROBUS | Q23: A2, B1, C1 | R23: A2 (21/12/2031) B1 (14/12/2027) C1 (14/12/2020) | S23: Vigente Licencia A2 - B1 | T23: 0 | U23: 0 | V23: KLY71E | W23: 9FLA64CZ5HAC31407 | X23: JEZWGH23872 | Y23: 2017 | Z23: Bajaj | AA23: 144 | AC23: 42836 | AD23: Moto | AE23: Si | AH23: 0.5 | AI23: 1 | AJ23: =IF(AK23>TODAY(),"Vigente","No Vigente") -> No Vigente | AK23: 45825 | AL23: 45460 | AM23: =IF(AN23>TODAY(),"Vigente","No Vigente") -> No Vigente | AN23: 45875 | AO23: 45511 | AP23: A2, B1, C1 | AQ23: A2 (21/12/2031) B1 (14/12/2027) C1 (14/12/2020) | AR23: =IF(AQ23>TODAY(),"Vigente","No Vigente") -> Vigente | AU23: Actualmente no tiene multas | BC23: Licencia A2 (21/12/2031) Licencia B1 (14/12/2027) Licencia VencidaC1 (14/12/2020) | BD23: Se actualiza manualmente información.
A24: 21 | D24: 1107102033 | E24: Barco Montoya Alexander | F24: 35326 | G24: MASCULINO | I24: =(CC$1-F24)/365 -> 29.553425 | K24: Asistente Auditoria Financiera Administrativa | L24: Auditoria | M24: 43906 | N24: =(CC$1-M24)/365 -> 6.0465753 | AD24: Moto | AH24: 0.5 | AI24: 1 | AJ24: =IF(AK24>TODAY(),"Vigente","No Vigente") -> No Vigente | AK24: =(AL24+365) -> 365 | AM24: =IF(AN24>TODAY(),"Vigente","No Vigente") -> No Vigente | AN24: =(AO24+365) -> 365 | AP24: A2 | AQ24: 47135 | AR24: =IF(AQ24>TODAY(),"Vigente","No Vigente") -> Vigente | BD24: Retirado
A25: 22 | D25: 1143958390 | E25: Barrera Rua Jhon Freddy | F25: 34197 | G25: MASCULINO | I25: =(CC$1-F25)/365 -> 32.646575 | K25: Auxiliar Operativo - Comercial (Tangibles) | L25: Comercial | M25: 44991 | N25: =(CC$1-M25)/365 -> 3.0739726 | O25: 3187234904 | V25: XCF28F | W25: 9F2C91258N5007633 | X25: ZS154FMI-38N104404 | Y25: 2022 | Z25: AKT | AA25: 124 | AC25: 44505 | AD25: Moto | AE25: Si | AH25: 0.5 | AI25: 1 | AJ25: =IF(AK25>TODAY(),"Vigente","No Vigente") -> No Vigente | AK25: =(AL25+365) -> 45700 | AL25: 45335 | AM25: =IF(AN25>TODAY(),"Vigente","No Vigente") -> No Vigente | AN25: =(AO25+365) -> 45700 | AO25: 45335 | AP25: A2 | AQ25: 48244 | AR25: =IF(AQ25>TODAY(),"Vigente","No Vigente") -> Vigente | AU25: Actualmente tiene una multa por no detenerse ante una luz roja o amarilla de semaforo (D04) conduciendo la moto XCF28F. | BD25: Se recibe por correo Actualización.
A26: 23 | D26: 31954628 | E26: Barrera Vargas Ligia | G26: FEMENINO | I26: =(CC$1-F26)/365 -> 126.33699 | K26: Lider de Ventas | L26: Comercial | M26: 39220 | N26: =(CC$1-M26)/365 -> 18.884932 | O26: 318 682 7911 | V26: QOJ90E | W26: 9FMJA3725JF003057 | X26: JA37E3823362 | Y26: 2018 | Z26: Honda | AA26: 109 | AC26: 43125 | AD26: Moto | AE26: Si | AH26: 0.5 | AI26: 1 | AJ26: =IF(AK26>TODAY(),"Vigente","No Vigente") -> No Vigente | AK26: =(AL26+365) -> 45682 | AL26: 45317 | AM26: =IF(AN26>TODAY(),"Vigente","No Vigente") -> No Vigente | AN26: =(AO26+365) -> 45684 | AO26: 45319 | AP26: A2 | AQ26: 48175 | AR26: =IF(AQ26>TODAY(),"Vigente","No Vigente") -> Vigente | AU26: No tiene multas. | BC26: Licencia B1 (23/11/2031) | BD26: No ha enviado información.
A27: 24 | D27: 1130651160 | E27: Benavides Araujo Yenny Fernanda | F27: 44630 | G27: FEMENINO | I27: =(CC$1-F27)/365 -> 4.0630137 | K27: Entrenador Comercial | L27: Comercial | M27: 44630 | N27: =(CC$1-M27)/365 -> 4.0630137 | O27: Is | AD27: Moto | AH27: 0.5 | AI27: 1 | AJ27: =IF(AK27>TODAY(),"Vigente","No Vigente") -> No Vigente | AK27: =(AL27+365) -> 365 | AM27: =IF(AN27>TODAY(),"Vigente","No Vigente") -> No Vigente | AN27: =(AO27+365) -> 365 | AP27: A1 | AQ27: 48630 | AR27: =IF(AQ27>TODAY(),"Vigente","No Vigente") -> Vigente | AU27: No tiene multas. | BC27: Licencia B1 (20/02/2033) | BD27: No ha enviado información.
A28: 25 | D28: 1130588900 | E28: Bermúdez Vasquez Marco Antonio | F28: 31725 | G28: MASCULINO | I28: =(CC$1-F28)/365 -> 39.419178 | K28: Lider de Ventas - Baloto | L28: Comercial | M28: 43314 | N28: =(CC$1-M28)/365 -> 7.6684932 | O28: 318 682 7856 | V28: PAH79C | W28: 9FLJDC1Z2CCJ27440 | X28: JEGBUC22317 | Y28: 2012 | Z28: Bajaj | AA28: 134 | AC28: 40841 | AD28: Moto | AE28: Si | AH28: 0.5 | AI28: 1 | AJ28: =IF(AK28>TODAY(),"Vigente","No Vigente") -> No Vigente | AK28: =(AL28+365) -> 45653 | AL28: 45288 | AM28: =IF(AN28>TODAY(),"Vigente","No Vigente") -> No Vigente | AN28: =(AO28+365) -> 45646 | AO28: 45281 | AP28: A2 | AQ28: 48730 | AR28: =IF(AQ28>TODAY(),"Vigente","No Vigente") -> Vigente | AU28: No tiene multas. | BC28: Licencia B1 (31/05/2033) y C1 (31/05/2026) | BD28: Se recibe por correo Actualización.
A29: 26 | D29: 1130586525 | E29: Betancourt Maturana Jose Luis | G29: MASCULINO | I29: =(CC$1-F29)/365 -> 126.33699 | K29: Lider de Ventas | L29: Comercial | M29: 43542 | N29: =(CC$1-M29)/365 -> 7.0438356 | O29: 323 568 4993 | V29: ELJ76E | W29: MD634KE66H2A38256 | X29: 0E6AH2104969 | Y29: 2017 | Z29: TVS | AA29: 180 | AC29: 42683 | AD29: Moto | AE29: Si | AH29: 0.25 | AI29: 0.5 | AJ29: =IF(AK29>TODAY(),"Vigente","No Vigente") -> No Vigente | AK29: =(AL29+365) -> 45307 | AL29: 44942 | AM29: =IF(AN29>TODAY(),"Vigente","No Vigente") -> No Vigente | AN29: =(AO29+365) -> 45667 | AO29: 45302 | AP29: A2 | AQ29: 48792 | AR29: =IF(AQ29>TODAY(),"Vigente","No Vigente") -> Vigente | AU29: Actualmente tiene 3 multas: No realizar la revisión tecnico- mecanica en el plazo legal establecido (C35) el día 05/05/2023 en el vehículo DOK955, No realizar la revisión tecnico- mecanica en el plazo legal establecido (C35) el día 23/06/2023 en el vehículo DOK955, No realizar la revisión tecnico- mecanica en el plazo legal establecido (C35) el día 26/06/2023 en el vehículo DOK955, | BC29: Licencia B1 (31/07/2027) y C1 (31/07/2020) | BD29: Retirado
A30: 27 | D30: 94521193 | E30: Bolaños Niño Joaquin Geovanny | F30: 28380 | G30: MASCULINO | I30: =(CC$1-F30)/365 -> 48.583562 | K30: Supervisor | L30: Comercial | M30: 38875 | N30: =(CC$1-M30)/365 -> 19.830137 | O30: 318 682 7905 | V30: HDE59A | W30: MD34E7700010 | X30: MD34E7700010 | Y30: 2007 | Z30: Honda | AA30: 249 | AC30: 39291 | AD30: Moto | AE30: Si | AH30: 0.5 | AI30: 1 | AJ30: =IF(AK30>TODAY(),"Vigente","No Vigente") -> No Vigente | AK30: =(AL30+365) -> 45687 | AL30: 45322 | AM30: =IF(AN30>TODAY(),"Vigente","No Vigente") -> No Vigente | AN30: =(AO30+365) -> 45684 | AO30: 45319 | AP30: A2 | AQ30: 45097 | AR30: =IF(AQ30>TODAY(),"Vigente","No Vigente") -> No Vigente | AU30: No tiene multas. | BC30: Licencia B1 (18/03/2024) Conducir con lentes | BD30: No ha enviado información
A31: 28 | D31: 16750197 | E31: Builes Caicedo Martin Emilio | F31: 24869 | G31: MASCULINO | I31: =(CC$1-F31)/365 -> 58.20274 | K31: Auxiliar Operativo de Recaudo | L31: Financiero | M31: 41778 | N31: =(CC$1-M31)/365 -> 11.876712 | O31: 318 775 9496 | V31: JBW42G | W31: 9GFJCKLH9PHF23965 | X31: ZS157FMJ25N112674 | Y31: 2023 | Z31: Victory | AA31: 149 | AC31: 44792 | AD31: Moto | AE31: No | AF31: Angie Vanessa Builes Gonzalez | AG31: 1107531579 | AH31: 0.5 | AI31: 1 | AJ31: =IF(AK31>TODAY(),"Vigente","No Vigente") -> No Vigente | AK31: 45890 | AL31: 45525 | AM31: =IF(AN31>TODAY(),"Vigente","No Vigente") -> No Vigente | AN31: 45886 | AO31: 45522 | AP31: A2 | AQ31: 48640 | AR31: =IF(AQ31>TODAY(),"Vigente","No Vigente") -> Vigente | AU31: No tiene multas. | BC31: Licencia B1 (07/06/2033) | BD31: Se recibe por correo Actualización.
A32: 29 | D32: 15950628 | E32: Buitrago Toro Rigoberto | F32: 24422 | G32: MASCULINO | I32: =(CC$1-F32)/365 -> 59.427397 | K32: Auxiliar Operativo de Recaudo | L32: Financiero | M32: 39226 | N32: =(CC$1-M32)/365 -> 18.868493 | O32: 318 682 7908 | V32: QNS93E | W32: 9FKDE0920J2011032 | X32: E3Y2E011032 | Y32: 2018 | Z32: Yamaha | AA32: 125 | AC32: 43090 | AD32: Moto | AE32: Si | AH32: 0.25 | AI32: 0.5 | AJ32: =IF(AK32>TODAY(),"Vigente","No Vigente") -> No Vigente | AK32: =(AL32+365) -> 45235 | AL32: 44870 | AM32: =IF(AN32>TODAY(),"Vigente","No Vigente") -> No Vigente | AN32: =(AO32+365) -> 45237 | AO32: 44872 | AP32: A2 | AQ32: 48352 | AR32: =IF(AQ32>TODAY(),"Vigente","No Vigente") -> Vigente | AU32: Tiene 3 multas canceladas. | BC32: Licencia B1 (29/01/2030) y C1 (29/01/2023) | BD32: Se actualiza Manualmente Información.
A33: 30 | D33: 4816989 | E33: Caicedo Barco Pedro Antonio | F33: 28180 | G33: MASCULINO | I33: =(CC$1-F33)/365 -> 49.131507 | K33: Técnico de Soporte | L33: TIC´s | M33: 41397 | N33: =(CC$1-M33)/365 -> 12.920548 | O33: 318 661 9605 | V33: AXR48F | W33: 9FLA14AZ3KAE07704 | X33: JBZWHF83844 | Y33: 2019 | Z33: Bajaj | AA33: 100 | AC33: 43595 | AD33: Moto | AE33: Si | AH33: NO APLICA | AI33: NO APLICA | AJ33: =IF(AK33>TODAY(),"Vigente","No Vigente") -> No Vigente | AK33: =(AL33+365) -> 45648 | AL33: 45283 | AM33: =IF(AN33>TODAY(),"Vigente","No Vigente") -> No Vigente | AN33: =(AO33+365) -> 45649 | AO33: 45284 | AP33: A2 | AQ33: 45825 | AR33: =IF(AQ33>TODAY(),"Vigente","No Vigente") -> No Vigente | AU33: Actualmente tiene 4 multas:Conducir vehiculo sin llevar consigo la licencia de conducción (B01) el día 11/11/2020 en la moto AXR48F, no realizar la revisión técnico-mécanica en el plazo legal establecido (C35) en la moto YWQ02C el día 09/04/2021, conducir sin portal el Seguro obligatorio de accidentes de tránsito ordenado por la ley (D02) el día 09/04/2021 en la moto YWQ02C, conducir sin portal el Seguro obligatorio de accidentes de tránsito ordenado por la ley (D02) el día 21/02/2023 en la moto AXR48F. | BC33: Conducir con diseño especial de vehículos y modificaciones de espejos. | BD33: Se recibe por correo Actualización.
A34: 31 | D34: 1005894105 | E34: Caicedo Restrepo Cristhian Andres | F34: 37563 | G34: MASCULINO | I34: =(CC$1-F34)/365 -> 23.424658 | K34: Auxiliar Operativo - Alistamiento del Servicio | L34: Comercial | M34: 44684 | N34: =(CC$1-M34)/365 -> 3.9150685 | O34: 315 358 9383 - 301 647 5779 | U34: 45288 | V34: MMY03G | W34: 9G5HAH029PVNM0226 | X34: HA11EPN9G00853 | Y34: 2023 | Z34: Hero | AA34: 98 | AC34: 44988 | AD34: Moto | AE34: Si | AH34: 0.5 | AI34: 1 | AJ34: =IF(AK34>TODAY(),"Vigente","No Vigente") -> Vigente | AK34: NA | AL34: NA | AM34: =IF(AN34>TODAY(),"Vigente","No Vigente") -> No Vigente | AN34: 45717 | AO34: 45353 | AP34: A2 | AQ34: 48087 | AR34: =IF(AQ34>TODAY(),"Vigente","No Vigente") -> Vigente | AU34: No tiene multas. | BC34: Licencia B1 (03/06/2031) | BD34: Se recibe por correo Actualización.
A35: 32 | D35: 94525706 | E35: Camacho Castillo Jhon Jairo | F35: 28844 | G35: MASCULINO | I35: =(CC$1-F35)/365 -> 47.312329 | K35: Auxiliar Operativo de Recaudo | L35: Financiero | M35: 39476 | N35: =(CC$1-M35)/365 -> 18.183562 | O35: 318 682 7879 | V35: WUV83D | W35: 9FLA37CZ4GDG79922 | X35: JEZWFL17383 | Y35: 2016 | Z35: Bajaj | AA35: 125 | AC35: 42230 | AD35: Moto | AE35: Si | AH35: 0.5 | AI35: 1 | AJ35: =IF(AK35>TODAY(),"Vigente","No Vigente") -> No Vigente | AK35: =(AL35+365) -> 45845 | AL35: 45480 | AM35: =IF(AN35>TODAY(),"Vigente","No Vigente") -> No Vigente | AN35: =(AO35+365) -> 45794 | AO35: 45429 | AP35: A2 | AQ35: 48750 | AR35: =IF(AQ35>TODAY(),"Vigente","No Vigente") -> Vigente | AU35: No tiene multas. | BC35: Licencia B1 (22/12/2025) y C1 (22/12/2018) | BD35: Se actualiza manualmente información.
A36: 33 | D36: 1114812714 | E36: Camilo John Fernando | F36: 31031 | G36: MASCULINO | I36: =(CC$1-F36)/365 -> 41.320548 | K36: Auxiliar Operativo - Logistica (Mantenimiento) | L36: Administrativo | M36: 41660 | N36: =(CC$1-M36)/365 -> 12.2 | O36: 316 833 0944 | V36: TWW23C | W36: 9FMJC4021CF005935 | X36: JC40E-1009786 | Y36: 2012 | Z36: Honda | AA36: 125 | AC36: 41095 | AD36: Moto | AE36: Si | AH36: 0.5 | AI36: 1 | AJ36: =IF(AK36>TODAY(),"Vigente","No Vigente") -> No Vigente | AK36: =(AL36+365) -> 45801 | AL36: 45436 | AM36: =IF(AN36>TODAY(),"Vigente","No Vigente") -> No Vigente | AN36: =(AO36+365) -> 45910 | AO36: 45545 | AP36: A2 | AQ36: 48626 | AR36: =IF(AQ36>TODAY(),"Vigente","No Vigente") -> Vigente | AU36: No tiene multas. | BD36: Se recibe por correo Actualización.
A37: 34 | D37: 66920495 | E37: Campiño Cuetia Marisol | F37: 27408 | G37: FEMENINO | I37: =(CC$1-F37)/365 -> 51.246575 | J37: Soltera | K37: Auxiliar Operativo - Comercial (Tangibles) | L37: Comercial | M37: 44587 | N37: =(CC$1-M37)/365 -> 4.1808219 | O37: 300 407 9686 | V37: EMD51G | W37: 9G5HAH024PVNC0137 | X37: HA11EPM9L00592 | Y37: 2023 | Z37: Hero | AA37: 98 | AC37: 44680 | AD37: Moto | AE37: No | AF37: Campiño Cuetia Fernando | AG37: 16744158 | AH37: 0.5 | AI37: 1 | AJ37: =IF(AK37>TODAY(),"Vigente","No Vigente") -> No Vigente | AK37: =(AL37+365) -> 45774 | AL37: 45409 | AM37: =IF(AN37>TODAY(),"Vigente","No Vigente") -> No Vigente | AN37: =(AO37+365) -> 45776 | AO37: 45411 | AP37: A2 | AQ37: 47889 | AR37: =IF(AQ37>TODAY(),"Vigente","No Vigente") -> Vigente | BC37: Licencia B1(05/11/2030) Y C1(05/11/2023) | BD37: Se recibe por correo Actualización.
A38: 35 | D38: 60446946 | E38: Candela Agudelo Paola Andrea | F38: 31194 | G38: FEMENINO | I38: =(CC$1-F38)/365 -> 40.873973 | K38: Administrador de Zona | L38: Comercial | M38: 44519 | N38: =(CC$1-M38)/365 -> 4.3671233 | O38: 310 759 2998 - 301 580 5951 | V38: OLL42C | W38: 9FKKE1105C2233818 | X38: E3B6E233818 | Y38: 2012 | Z38: YAMAHA | AA38: 125 | AB38: 125 | AC38: 41039 | AD38: Moto | AE38: NO | AF38: YINET PATRICIA LOZADA GARCIA | AG38: 65700942 | AH38: 0.5 | AI38: 1 | AJ38: =IF(AK38>TODAY(),"Vigente","No Vigente") -> No Vigente | AK38: =(AL38+365) -> 45042 | AL38: 44677 | AM38: =IF(AN38>TODAY(),"Vigente","No Vigente") -> No Vigente | AN38: =(AO38+365) -> 45288 | AO38: 44923 | AP38: A2 | AQ38: 46019 | AR38: =IF(AQ38>TODAY(),"Vigente","No Vigente") -> No Vigente | AU38: No tiene multas. | BC38: Licencia B1 (15/07/2031) | BD38: Retirado
A39: 36 | D39: 1107093078 | E39: Carmona Bernal Charlie Andrés | G39: MASCULINO | I39: =(CC$1-F39)/365 -> 126.33699 | K39: Auxiliar Operativo de Recaudo | L39: Financiero | M39: 43412 | N39: =(CC$1-M39)/365 -> 7.4 | O39: 318 771 4484 | V39: XBS44F | W39: 9F2D51251N5021163 | X39: 157FMIUE086212 | Y39: 2022 | Z39: AKT | AA39: 125 | AC39: 44456 | AD39: Moto | AE39: No | AF39: Hilda Lucia Cuesta Salinas | AG39: 66847042 | AH39: 0.5 | AI39: 1 | AJ39: =IF(AK39>TODAY(),"Vigente","No Vigente") -> No Vigente | AK39: =(AL39+365) -> 45555 | AL39: 45190 | AM39: =IF(AN39>TODAY(),"Vigente","No Vigente") -> No Vigente | AN39: =(AO39+365) -> 45242 | AO39: 44877 | AP39: A2 | AQ39: 45406 | AR39: =IF(AQ39>TODAY(),"Vigente","No Vigente") -> No Vigente | AU39: Actualmente tiene 2 multas: No tener al dia la revisión tecnico mecanica (C35) del 30/09/2022 moto BMA83C y no tener vigente el SOAT (D02) del 30/09/2022 moto BMA83C. | BC39: Licencia B1 (14/12/2027) | BD39: Retirado
A40: 37 | D40: 1107099179 | E40: Carvajal Gallego Anthony | F40: 35222 | G40: MASCULINO | I40: =(CC$1-F40)/365 -> 29.838356 | K40: Técnico de Soporte | L40: TIC´s | M40: 44677 | N40: =(CC$1-M40)/365 -> 3.9342466 | O40: 319 673 7144 | P40: MOTOCICLETA | Q40: A2 | R40: 48191 | S40: Vigente | V40: JDH86G | W40: 9G5HAR028PVNG0520 | X40: HA11EPN9B00236 | Y40: 2023 | Z40: Hero | AA40: 100 | AC40: 44827 | AD40: Moto | AE40: Si | AH40: 0.5 | AI40: 1 | AJ40: =IF(AK40>TODAY(),"Vigente","No Vigente") -> No Vigente | AK40: =(AL40+365) -> 45917 | AL40: 45552 | AM40: =IF(AN40>TODAY(),"Vigente","No Vigente") -> No Vigente | AN40: =(AO40+365) -> 45933 | AO40: 45568 | AP40: A2 | AQ40: 48191 | AR40: =IF(AQ40>TODAY(),"Vigente","No Vigente") -> Vigente | AU40: Sin multas en simit. | BD40: Actualización enviada por correo
A41: 38 | D41: 1151963259 | E41: Castañeda Pérez Luis David | F41: 35688 | G41: MASCULINO | I41: =(CC$1-F41)/365 -> 28.561644 | K41: Auxiliar De Ventas (Tangibles) | L41: Comercial | M41: 44068 | N41: =(CC$1-M41)/365 -> 5.6027397 | O41: 316 207 8533 | V41: HES79A | X41: DUEBNL26215 | Y41: 2008 | Z41: Auteco | AA41: 98 | AC41: 39328 | AD41: Moto | AE41: No | AF41: Jairo Omar Gelvez | AG41: 88256249 | AH41: 0.5 | AI41: 1 | AJ41: =IF(AK41>TODAY(),"Vigente","No Vigente") -> No Vigente | AK41: =(AL41+365) -> 45554 | AL41: 45189 | AM41: =IF(AN41>TODAY(),"Vigente","No Vigente") -> No Vigente | AN41: =(AO41+365) -> 45574 | AO41: 45209 | AP41: A2 | AQ41: 47342 | AR41: =IF(AQ41>TODAY(),"Vigente","No Vigente") -> Vigente | AU41: No tiene multas. | BD41: Se recibe por correo Actualización
A42: 39 | D42: 94455878 | E42: Castaño Bedoya Mauricio | G42: MASCULINO | I42: =(CC$1-F42)/365 -> 126.33699 | K42: Lider de Ventas | L42: Comercial | M42: 44743 | N42: =(CC$1-M42)/365 -> 3.7534247 | O42: 305 330 2697 | V42: SFF36E | Y42: 2018 | Z42: Yamaha | AA42: 250 | AC42: 43468 | AD42: Moto | AE42: Si | AH42: 0.5 | AI42: 1 | AJ42: =IF(AK42>TODAY(),"Vigente","No Vigente") -> No Vigente | AK42: =(AL42+365) -> 45314 | AL42: 44949 | AM42: =IF(AN42>TODAY(),"Vigente","No Vigente") -> No Vigente | AN42: =(AO42+365) -> 45317 | AO42: 44952 | AP42: A2 | AQ42: 46736 | AR42: =IF(AQ42>TODAY(),"Vigente","No Vigente") -> Vigente | AU42: No tiene multas. | BC42: Licencia B1 (05/09/2024) y C1 (05/09/2017) | BD42: Retirado
A43: 40 | D43: 1107037482 | E43: Castillo Mana John Edisson | G43: MASCULINO | I43: =(CC$1-F43)/365 -> 126.33699 | K43: Lider de Ventas | L43: Comercial | M43: 44776 | N43: =(CC$1-M43)/365 -> 3.6630137 | O43: 312 854 5205 | AH43: 0.5 | AI43: 1 | AJ43: =IF(AK43>TODAY(),"Vigente","No Vigente") -> No Vigente | AK43: =(AL43+365) -> 365 | AM43: =IF(AN43>TODAY(),"Vigente","No Vigente") -> No Vigente | AN43: =(AO43+365) -> 365 | AR43: =IF(AQ43>TODAY(),"Vigente","No Vigente") -> No Vigente | BD43: Retirado
A44: 41 | D44: 67021671 | E44: Castillo Ortiz Isabel Cristina | F44: 30744 | G44: FEMENINO | I44: =(CC$1-F44)/365 -> 42.106849 | K44: Entrenador Comercial | L44: Comercial | M44: 44419 | N44: =(CC$1-M44)/365 -> 4.6410959 | O44: 320 504 6415 | V44: ZRP59G | W44: JA25E-4952819 | X44: 9FMJA2590SE001802 | Y44: 2025 | Z44: Honda | AA44: 125 | AC44: 45359 | AD44: Moto | AE44: Si | AH44: 0.5 | AI44: 1 | AJ44: =IF(AK44>TODAY(),"Vigente","No Vigente") -> No Vigente | AK44: =(AL44+365) -> 45724 | AL44: 45359 | AM44: =IF(AN44>TODAY(),"Vigente","No Vigente") -> No Vigente | AN44: =(AO44+365) -> 45724 | AO44: 45359 | AP44: A1 | AQ44: 45603 | AR44: =IF(AQ44>TODAY(),"Vigente","No Vigente") -> No Vigente | AU44: No tiene multas. | BD44: Se actualiza manualmente.
A45: 42 | D45: 94493287 | E45: Castro Concha Luis Fernando | F45: 27997 | G45: MASCULINO | I45: =(CC$1-F45)/365 -> 49.632877 | K45: Asesor de Ventas Tangibles | L45: Financiero | M45: 41821 | N45: =(CC$1-M45)/365 -> 11.758904 | O45: 316 696 5215 | P45: MOTOCICLETA | Q45: A2 | R45: 09/06/2033 | S45: Vigente | V45: EGL66D | W45: 9FLA37CZ6ECJ34143 | X45: JEZWDD43632 | Y45: 2014 | Z45: Bajaj | AA45: 125 | AC45: 41572 | AD45: Moto | AE45: Si | AH45: 0.5 | AI45: 1 | AJ45: =IF(AK45>TODAY(),"Vigente","No Vigente") -> No Vigente | AK45: =(AL45+365) -> 45958 | AL45: 45593 | AM45: =IF(AN45>TODAY(),"Vigente","No Vigente") -> No Vigente | AN45: =(AO45+365) -> 45958 | AO45: 45593 | AP45: A2 | AQ45: 48739 | AR45: =IF(AQ45>TODAY(),"Vigente","No Vigente") -> Vigente | AU45: Tiene 3 multas canceladas. | BD45: Se recibe por correo Actualización.
A46: 43 | D46: 1143935328 | E46: Castro Martínez Alex David | G46: MASCULINO | I46: =(CC$1-F46)/365 -> 126.33699 | K46: Técnico de Comunicaciones | L46: TIC´s | M46: 41117 | N46: =(CC$1-M46)/365 -> 13.687671 | O46: 318 370 6855 | V46: ISF05F | Y46: 2021 | Z46: AKT | AA46: 125 | AC46: 43867 | AD46: Moto | AE46: Si | AH46: 0.5 | AI46: 1 | AJ46: =IF(AK46>TODAY(),"Vigente","No Vigente") -> No Vigente | AK46: =(AL46+365) -> 45740 | AL46: 45375 | AM46: =IF(AN46>TODAY(),"Vigente","No Vigente") -> No Vigente | AN46: =(AO46+365) -> 45685 | AO46: 45320 | AP46: A2 | AQ46: 45301 | AR46: =IF(AQ46>TODAY(),"Vigente","No Vigente") -> No Vigente | AU46: No tiene multas. | BC46: Tiene licencia B1 (27/09/2032) y C1 (27/09/2025) | BD46: Se actualiza manualmente.
A47: 44 | D47: 94376628 | E47: Castro Ríos Wilmer | F47: 26592 | G47: MASCULINO | I47: =(CC$1-F47)/365 -> 53.482192 | K47: Auxiliar Operativo - Logística (Transporte) | L47: Administrativo | M47: 43046 | N47: =(CC$1-M47)/365 -> 8.4027397 | O47: 310 507 8692 | V47: HQC82A | X47: 152FMHXJ073538 | Y47: 2009 | Z47: AKT | AA47: 107 | AC47: 39721 | AD47: Moto | AE47: No | AF47: Dana Francely Romo Muñoz | AG47: 67008623 | AH47: NO APLICA | AI47: NO APLICA | AJ47: =IF(AK47>TODAY(),"Vigente","No Vigente") -> No Vigente | AK47: =(AL47+365) -> 45644 | AL47: 45279 | AM47: =IF(AN47>TODAY(),"Vigente","No Vigente") -> No Vigente | AN47: =(AO47+365) -> 45735 | AO47: 45370 | AP47: A2 | AQ47: 47346 | AR47: =IF(AQ47>TODAY(),"Vigente","No Vigente") -> Vigente | AU47: No tiene multas. | BC47: Licencia B2(11/08/2031) Y C2 (11/08/2024) Conducir con lentes. | BD47: Se actualiza manualmente.
A48: 45 | D48: 31582765 | E48: Causaya Peña Isabel Fernanda | F48: 29643 | G48: FEMENINO | I48: =(CC$1-F48)/365 -> 45.123288 | K48: Auxiliar De Ventas (Tangibles) | L48: Comercial | M48: 44470 | N48: =(CC$1-M48)/365 -> 4.5013699 | O48: 312 628 7186 | V48: IHT84D | W48: 9FMPCHK22FF002027 | X48: SDH1P50FMH-2*D5848515* | Y48: 2015 | Z48: Honda | AA48: 109 | AC48: 41837 | AD48: Moto | AE48: Si | AH48: 0.5 | AI48: 1 | AJ48: =IF(AK48>TODAY(),"Vigente","No Vigente") -> No Vigente | AK48: =(AL48+365) -> 45464 | AL48: 45099 | AM48: =IF(AN48>TODAY(),"Vigente","No Vigente") -> No Vigente | AN48: =(AO48+365) -> 45379 | AO48: 45014 | AP48: A2 | AQ48: 45488 | AR48: =IF(AQ48>TODAY(),"Vigente","No Vigente") -> No Vigente | AU48: No tiene multas. | BD48: Retirado
A49: 46 | D49: 1144082011 | E49: Cespedes Yesika Paola | F49: 34856 | G49: FEMENINO | I49: =(CC$1-F49)/365 -> 30.841096 | K49: Auxiliar Operativo de Recaudo | L49: Financiero | M49: 45026 | N49: =(CC$1-M49)/365 -> 2.9780822 | O49: 3187347678 | V49: JFP62E | W49: 9F2A61107H5003325 | X49: 152FMHPQ293054 | Y49: 2017 | Z49: AKT | AA49: 107 | AC49: 09/12/2016 | AD49: Moto | AE49: No | AF49: Robert Stiven Moreno Rodriguez | AG49: 1000120858 | AH49: 0.5 | AI49: 1 | AJ49: =IF(AK49>TODAY(),"Vigente","No Vigente") -> No Vigente | AK49: =(AL49+365) -> 45105 | AL49: 44740 | AM49: =IF(AN49>TODAY(),"Vigente","No Vigente") -> No Vigente | AN49: =(AO49+365) -> 45394 | AO49: 45029 | AP49: A2 | AQ49: 46153 | AR49: =IF(AQ49>TODAY(),"Vigente","No Vigente") -> Vigente | AU49: No tiene multas. | BD49: Se recibe por correo Actulaización.
A50: 47 | D50: 34327918 | E50: Chaguendo Ipia Yasmin Edilsa | F50: 22/12/1984 | G50: FEMENINO | I50: =(CC$1-F50)/365 -> 41.30137 | K50: Lider de Ventas | L50: Comercial | M50: 42254 | N50: =(CC$1-M50)/365 -> 10.572603 | O50: 318 517 8892 | U50: 44893 | V50: JEJ39G | W50: 9FMJA2593PF017459 | X50: JA25E-4923968 | Y50: 2023 | Z50: Honda | AA50: 124 | AC50: 29/10/2022 | AD50: Moto | AE50: SI | AH50: 0.25 | AI50: 0.5 | AJ50: =IF(AK50>TODAY(),"Vigente","No Vigente") -> No Vigente | AK50: =(AL50+365) -> 45966 | AL50: 45601 | AM50: =IF(AN50>TODAY(),"Vigente","No Vigente") -> No Vigente | AN50: =(AO50+364) -> 45998 | AO50: 45634 | AP50: A2 | AQ50: 13/03/2027 | AR50: =IF(AQ50>TODAY(),"Vigente","No Vigente") -> Vigente | AU50: No tiene multas. | BD50: Se recibe por correo Actulaización.
A51: 48 | D51: 14835814 | E51: Chantre Lopez Benhur | F51: 28975 | G51: MASCULINO | I51: =(CC$1-F51)/365 -> 46.953425 | K51: Asistente - Mercadeo | L51: Comercial | M51: 39645 | N51: =(CC$1-M51)/365 -> 17.720548 | O51: 312 602 1081 | T51: 44938 | V51: ZZK56E | W51: 9FLXCG7D0KCC21737 | X51: 1P50FMGJ1721049 | Y51: 2019 | Z51: Victory | AA51: 100 | AC51: 43540 | AD51: Moto | AE51: No | AF51: Claudia Lorena Cocoma Sanchez | AG51: 1130658439 | AH51: NO APLICA | AI51: NO APLICA | AJ51: =IF(AK51>TODAY(),"Vigente","No Vigente") -> No Vigente | AK51: =(AL51+365) -> 45408 | AL51: 45043 | AM51: =IF(AN51>TODAY(),"Vigente","No Vigente") -> No Vigente | AN51: =(AO51+365) -> 45390 | AO51: 45025 | AP51: A2 | AQ51: 48255 | AR51: =IF(AQ51>TODAY(),"Vigente","No Vigente") -> Vigente | AU51: No tiene multas. | BC51: Licencia B1 (11/02/2032) | BD51: Retirado
A52: 49 | D52: 16639522 | E52: Chaux Galeano Campo Elias | F52: 21245 | G52: MASCULINO | I52: =(CC$1-F52)/365 -> 68.131507 | K52: Auxiliar De Ventas (Tangibles) | L52: Comercial | M52: 39417 | N52: =(CC$1-M52)/365 -> 18.345205 | O52: 318 771 4482 | V52: FEV74B | X52: 06J27E03621 | Y52: 2007 | Z52: Honda | AA52: 100 | AC52: 39197 | AD52: Moto | AE52: Si | AH52: 0.5 | AI52: 1 | AJ52: =IF(AK52>TODAY(),"Vigente","No Vigente") -> No Vigente | AK52: =(AL52+365) -> 45142 | AL52: 44777 | AM52: =IF(AN52>TODAY(),"Vigente","No Vigente") -> No Vigente | AN52: =(AO52+365) -> 45135 | AO52: 44770 | AP52: A2 | AQ52: 45097 | AR52: =IF(AQ52>TODAY(),"Vigente","No Vigente") -> No Vigente | AU52: No tiene multas. | BC52: Licencia B1 (01/10/2025) y C1 (01/10/2021) | BD52: Retirado
A53: 50 | D53: 1144101426 | E53: Choco Popo Jhon Eider | F53: 35878 | G53: MASCULINO | I53: =(CC$1-F53)/365 -> 28.041096 | K53: Técnico de Soporte | L53: TIC´s | M53: 44587 | N53: =(CC$1-M53)/365 -> 4.1808219 | O53: 318 740 4870 | V53: HHT35G | W53: 9FMJA2596PF009775 | X53: JA25E-4910801 | Y53: 2023 | Z53: Honda | AA53: 124 | AC53: 44749 | AD53: Moto | AE53: Si | AH53: 0.5 | AI53: 1 | AJ53: =IF(AK53>TODAY(),"Vigente","No Vigente") -> No Vigente | AK53: =(AL53+365) -> 45840 | AL53: 45475 | AM53: =IF(AN53>TODAY(),"Vigente","No Vigente") -> No Vigente | AN53: =(AO53+365) -> 45845 | AO53: 45480 | AP53: A2 | AQ53: 47084 | AR53: =IF(AQ53>TODAY(),"Vigente","No Vigente") -> Vigente | AU53: No tiene multas. | BD53: Se recibe por correo Actualización.
A54: 51 | D54: 1144134137 | E54: Conde Solarte Mauricio | F54: 32889 | G54: MASCULINO | I54: =(CC$1-F54)/365 -> 36.230137 | K54: Lider de Ventas - Betplay | L54: Comercial | M54: 43264 | N54: =(CC$1-M54)/365 -> 7.8054795 | O54: 318 682 7912 | T54: 45049 | V54: HMJ68F | W54: 9FSNG4BDXLC312955 | X54: BGA1-631787 | Y54: 2020 | Z54: Suzuki | AA54: 150 | AC54: 43791 | AD54: Moto | AE54: Si | AH54: NO APLICA | AI54: NO APLICA | AJ54: =IF(AK54>TODAY(),"Vigente","No Vigente") -> No Vigente | AK54: =(AL54+365) -> 45249 | AL54: 44884 | AM54: =IF(AN54>TODAY(),"Vigente","No Vigente") -> No Vigente | AN54: =(AO54+365) -> 45250 | AO54: 44885 | AP54: A2 | AQ54: 48490 | AR54: =IF(AQ54>TODAY(),"Vigente","No Vigente") -> Vigente | AU54: No tiene multas. | BC54: Licencia B1 (03/10/2032) y C1 (03/10/2025) | BD54: Retirado
A55: 52 | D55: 1107068953 | E55: Cortes Juan Camilo | F55: 33602 | G55: MASCULINO | I55: =(CC$1-F55)/365 -> 34.276712 | K55: Asistente Jurídico Laboral | L55: Administrativo | M55: 44676 | N55: =(CC$1-M55)/365 -> 3.9369863 | O55: 317 696 4347 | V55: NIT64F | W55: 9F2D21254M5004378 | X55: 157FMISQ474196 | Y55: 2021 | Z55: AKT | AA55: 125 | AC55: 44103 | AD55: Moto | AE55: Si | AH55: 0.5 | AI55: 1 | AJ55: =IF(AK55>TODAY(),"Vigente","No Vigente") -> No Vigente | AK55: =(AL55+365) -> 45927 | AL55: 45562 | AM55: =IF(AN55>TODAY(),"Vigente","No Vigente") -> No Vigente | AN55: =(AO55+365) -> 45930 | AO55: 45565 | AP55: A2 | AQ55: 14/02/2033 | AR55: =IF(AQ55>TODAY(),"Vigente","No Vigente") -> Vigente | BC55: Licencia B1 (16/06/2027) y C1 (16/06/2020)
A56: 53 | D56: 29361944 | E56: Cruz Valencia Carol Elena | F56: 32595 | G56: FEMENINO | I56: =(CC$1-F56)/365 -> 37.035616 | K56: Lider de Ventas | L56: Comercial | M56: 41130 | N56: =(CC$1-M56)/365 -> 13.652055 | O56: 317 893 9579 | V56: NJP17F | W56: 9FMJA3727MF002304 | X56: JA37E3930407 | Y56: 2021 | Z56: Honda | AA56: 109 | AC56: 44184 | AD56: Moto | AE56: No | AF56: Gurrute Cruz Linda Yulieth | AG56: 1005977639 | AH56: 0.5 | AI56: 1 | AJ56: =IF(AK56>TODAY(),"Vigente","No Vigente") -> No Vigente | AK56: =(AL56+365) -> 45366 | AL56: 45001 | AM56: =IF(AN56>TODAY(),"Vigente","No Vigente") -> No Vigente | AN56: =(AO56+365) -> 45681 | AO56: 45316 | AP56: A2 | AQ56: 45912 | AR56: =IF(AQ56>TODAY(),"Vigente","No Vigente") -> No Vigente | BD56: Retirado
A57: 54 | D57: 1113531156 | E57: Cuatin Larrahondo Cristhian Fernando | F57: 34595 | G57: MASCULINO | I57: =(CC$1-F57)/365 -> 31.556164 | K57: Auxiliar De Ventas (Tangibles) | L57: Comercial | M57: 44266 | N57: =(CC$1-M57)/365 -> 5.060274 | O57: 300 485 8356 | V57: WDU57F | W57: 9FL37ET12NEH00804 | X57: DT1AN27L3106 | Y57: 2022 | Z57: TVS | AA57: 197 | AC57: 44448 | AD57: Moto | AE57: Si | AH57: 0.5 | AI57: 1 | AJ57: =IF(AK57>TODAY(),"Vigente","No Vigente") -> No Vigente | AK57: =(AL57+365) -> 45910 | AL57: 45545 | AM57: =IF(AN57>TODAY(),"Vigente","No Vigente") -> No Vigente | AN57: =(AO57+365) -> 45677 | AO57: 45312 | AP57: A2 | AQ57: 45676 | AR57: =IF(AQ57>TODAY(),"Vigente","No Vigente") -> No Vigente | AU57: Sin multas. | BD57: Se recibe por correo Actualización.
A58: 55 | D58: 1089000113 | E58: Cuero Minota Miguel Angel | F58: 33984 | G58: MASCULINO | I58: =(CC$1-F58)/365 -> 33.230137 | K58: Auxiliar De Ventas (Tangibles) | L58: Comercial | M58: 44734 | N58: =(CC$1-M58)/365 -> 3.7780822 | O58: 320 569 9659 | V58: AJI35E | W58: 9F2B91255GA001987 | X58: 157FMINQ127718 | Y58: 2016 | Z58: AKT | AA58: 125 | AC58: 42312 | AD58: Moto | AE58: SI | AH58: 0.5 | AI58: 1 | AJ58: =IF(AK58>TODAY(),"Vigente","No Vigente") -> No Vigente | AK58: =(AL58+365) -> 45462 | AL58: 45097 | AM58: =IF(AN58>TODAY(),"Vigente","No Vigente") -> No Vigente | AN58: =(AO58+365) -> 45464 | AO58: 45099 | AP58: A2 | AQ58: 45252 | AR58: =IF(AQ58>TODAY(),"Vigente","No Vigente") -> No Vigente | AU58: Sin multas | BD58: Retirado
A59: 56 | D59: 1004614499 | E59: Cuero Palermo Miguel | F59: 34268 | G59: MASCULINO | I59: =(CC$1-F59)/365 -> 32.452055 | K59: Técnico de Soporte | L59: TIC´s | M59: 44914 | N59: =(CC$1-M59)/365 -> 3.2849315 | O59: 300 733 4762 | V59: FUD89F | W59: 9FLA37CY6LAJ20727 | X59: JEZWKC22287 | Y59: 2020 | Z59: Bajaj | AA59: 124 | AC59: 43790 | AD59: Moto | AE59: Si | AH59: 0.5 | AI59: 1 | AJ59: =IF(AK59>TODAY(),"Vigente","No Vigente") -> No Vigente | AK59: =(AL59+365) -> 45807 | AL59: 45442 | AM59: =IF(AN59>TODAY(),"Vigente","No Vigente") -> No Vigente | AN59: =(AO59+365) -> 45815 | AO59: 45450 | AP59: A2 | AQ59: 48333 | AR59: =IF(AQ59>TODAY(),"Vigente","No Vigente") -> Vigente | AU59: No tiene multas. | BD59: Se recibe por correo Actualización.
A60: 57 | D60: 1144213344 | E60: Davila Corrales Valeria | F60: 36549 | G60: FEMENINO | I60: =(CC$1-F60)/365 -> 26.20274 | K60: Auxiliar De Ventas (Tangibles) | L60: Comercial | M60: 44447 | N60: =(CC$1-M60)/365 -> 4.5643836 | O60: 317 251 2521 | V60: KNR24G | W60: 9GFXCJTC7PCJ09747 | X60: 1P53FMIHP1003568 | Y60: 2023 | Z60: Victory | AA60: 124 | AC60: 44931 | AD60: Moto | AE60: Si | AH60: 0.5 | AI60: 1 | AJ60: =IF(AK60>TODAY(),"Vigente","No Vigente") -> Vigente | AK60: NA | AL60: NA | AM60: =IF(AN60>TODAY(),"Vigente","No Vigente") -> No Vigente | AN60: =(AO60+365) -> 45665 | AO60: 45300 | AP60: A2 | AQ60: 47852 | AR60: =IF(AQ60>TODAY(),"Vigente","No Vigente") -> Vigente | AU60: No tiene multas. | BC60: Licencia B1 (04/01/2031) | BD60: Se recibe por correo Actualización.
A61: 58 | D61: 1107077828 | E61: De Jesus Tasama Sergio Andres | F61: 34177 | G61: MASCULINO | I61: =(CC$1-F61)/365 -> 32.70137 | K61: Auxiliar De Ventas (Tangibles) | L61: Comercial | M61: 44718 | N61: =(CC$1-M61)/365 -> 3.8219178 | O61: 316 221 3324 | U61: 44884 | V61: AJQ05E | W61: 9FLA76AZ1GAJ00806 | X61: PFZWFC04810 | Y61: 2016 | Z61: Bajaj | AA61: 100 | AC61: 42335 | AD61: Moto | AE61: No | AF61: Alfredo de Jesus Ceron | AG61: 16722471 | AH61: 0.25 | AI61: 0.5 | AJ61: =IF(AK61>TODAY(),"Vigente","No Vigente") -> No Vigente | AK61: =(AL61+365) -> 45932 | AL61: 45567 | AM61: =IF(AN61>TODAY(),"Vigente","No Vigente") -> No Vigente | AN61: =(AO61+364) -> 45977 | AO61: 45613 | AP61: A2 | AQ61: 45998 | AR61: =IF(AQ61>TODAY(),"Vigente","No Vigente") -> No Vigente | AU61: No tiene multas. | BC61: Licencia B1 (21/06/2031) y C1 (21/06/2024) | BD61: Se actualiza manualmente.
A62: 59 | D62: 16796200 | E62: Delgado López Arlex Alexander | F62: 26265 | G62: MASCULINO | I62: =(CC$1-F62)/365 -> 54.378082 | K62: Auxiliar Operativo de Recaudo | L62: Financiero | M62: 38869 | N62: =(CC$1-M62)/365 -> 19.846575 | O62: 315 670 2530 | V62: FRI62F | W62: 9FLA37CYXLAH19004 | X62: JEZWKB20014 | Y62: 2020 | Z62: Bajaj | AA62: 125 | AC62: 43794 | AD62: Moto | AE62: No | AF62: Paola Rendón | AG62: 29178103 | AH62: 0.5 | AI62: 1 | AJ62: =IF(AK62>TODAY(),"Vigente","No Vigente") -> No Vigente | AK62: =(AL62+365) -> 45982 | AL62: 45617 | AM62: =IF(AN62>TODAY(),"Vigente","No Vigente") -> No Vigente | AN62: =(AO62+365) -> 45673 | AO62: 45308 | AP62: A2 | AQ62: 45097 | AR62: =IF(AQ62>TODAY(),"Vigente","No Vigente") -> No Vigente | AU62: No tiene multas. | BC62: Licencia B2 (19/01/2027) y C2 (19/01/2020) Restriccion conducir con lentes y modificación de espejos. | BD62: Se recibe por correo Actualización.
A63: 60 | D63: 14802081 | E63: Devia Guevara Luis Eduardo | F63: 31315 | G63: MASCULINO | I63: =(CC$1-F63)/365 -> 40.542466 | K63: Auxiliar Operativo de Recaudo | L63: Financiero | M63: 43361 | N63: =(CC$1-M63)/365 -> 7.539726 | O63: 318 312 1329 | V63: NWA87E | W63: 9FKDE0910J2067589 | X63: E3L5E067589 | Y63: 2018 | Z63: Yamaha | AA63: 125 | AC63: 42940 | AD63: Moto | AE63: No | AF63: Tomas Antonio Quiñones Arias | AG63: 12911837 | AH63: 0.5 | AI63: 1 | AJ63: =IF(AK63>TODAY(),"Vigente","No Vigente") -> No Vigente | AK63: =(AL63+365) -> 45909 | AL63: 45544 | AM63: =IF(AN63>TODAY(),"Vigente","No Vigente") -> No Vigente | AN63: =(AO63+365) -> 45793 | AO63: 45428 | AP63: A2 | AQ63: 45788 | AR63: =IF(AQ63>TODAY(),"Vigente","No Vigente") -> No Vigente | AU63: No tiene multas. | BC63: Licencia C1 (07/05/2021) y B1 (07/05/2028) | BD63: Se recibe por correo Actualización.
A64: 61 | D64: 1151954842 | E64: Diaz Barreneche Rigoberto | F64: 34347 | G64: MASCULINO | I64: =(CC$1-F64)/365 -> 32.235616 | K64: Auxiliar De Ventas (Tangibles) | L64: Comercial | M64: 44764 | N64: =(CC$1-M64)/365 -> 3.6958904 | O64: 314 864 4599 | V64: CGO68C | W64: 9FKKG0340A2008613 | X64: 45D1008613 | Y64: 2010 | Z64: Yamaha | AA64: 153 | AC64: 40332 | AD64: Moto | AE64: No | AF64: Rogoberto Díaz Marín | AG64: 16745044 | AH64: 0.5 | AI64: 1 | AJ64: =IF(AK64>TODAY(),"Vigente","No Vigente") -> No Vigente | AK64: =(AL64+365) -> 45834 | AL64: 45469 | AM64: =IF(AN64>TODAY(),"Vigente","No Vigente") -> No Vigente | AN64: =(AO64+365) -> 45703 | AO64: 45338 | AP64: A2 | AQ64: 45494 | AR64: =IF(AQ64>TODAY(),"Vigente","No Vigente") -> No Vigente | AU64: No tiene multas. | BC64: Licencia B2 (23/07/2034) | BD64: Se recibe por correo Actualización.
A65: 62 | D65: 1144169741 | E65: Diaz Castro Maira Alejandra | G65: FEMENINO | I65: =(CC$1-F65)/365 -> 126.33699 | K65: Entrenador Comercial | L65: Comercial | M65: 41649 | N65: =(CC$1-M65)/365 -> 12.230137 | O65: 315 689 1795 | V65: ROU29C | Y65: 2012 | Z65: AKT | AA65: 125 | AC65: 40922 | AD65: Moto | AE65: No | AF65: Edinson Giovanny Solarte Bolaños | AG65: 1130610087 | AH65: 0.5 | AI65: 1 | AJ65: =IF(AK65>TODAY(),"Vigente","No Vigente") -> No Vigente | AK65: =(AL65+365) -> 45175 | AL65: 44810 | AM65: =IF(AN65>TODAY(),"Vigente","No Vigente") -> No Vigente | AN65: =(AO65+365) -> 45153 | AO65: 44788 | AP65: A2 | AQ65: 46261 | AR65: =IF(AQ65>TODAY(),"Vigente","No Vigente") -> Vigente | BD65: Retirado
A66: 63 | D66: 1151941373 | E66: Diaz Vivas Heidy Brigitte | F66: 33397 | G66: FEMENINO | I66: =(CC$1-F66)/365 -> 34.838356 | K66: Auxiliar Administrativo de Mantenimiento | L66: Administrativo | M66: 45040 | N66: =(CC$1-M66)/365 -> 2.939726 | O66: 3218798835 | AD66: Moto | AJ66: =IF(AK66>TODAY(),"Vigente","No Vigente") -> No Vigente | AK66: =(AL66+365) -> 365 | AM66: =IF(AN66>TODAY(),"Vigente","No Vigente") -> No Vigente | AN66: =(AO66+365) -> 365 | AR66: =IF(AQ66>TODAY(),"Vigente","No Vigente") -> No Vigente | BD66: No datos / Cargo Administrativo
A67: 64 | D67: 1005878062 | E67: Dossman Rosero Juan Esteban | F67: 37223 | G67: MASCULINO | I67: =(CC$1-F67)/365 -> 24.356164 | K67: Auxiliar De Ventas (Tangibles) | L67: Comercial | M67: 44566 | N67: =(CC$1-M67)/365 -> 4.2383562 | O67: 319 523 1540 | V67: MMV69G | W67: 9FKDG3611P2091845 | X67: G3L1E091845 | Y67: 2023 | Z67: Yamaha | AA67: 149 | AC67: 45013 | AD67: Moto | AE67: No | AF67: Harold Rosas Guerrero | AG67: 16682334 | AH67: 0.5 | AI67: 1 | AJ67: =IF(AK67>TODAY(),"Vigente","No Vigente") -> No Vigente | AK67: =(AL67+365) -> 45378 | AL67: 45013 | AM67: =IF(AN67>TODAY(),"Vigente","No Vigente") -> No Vigente | AN67: =(AO67+365) -> 45377 | AO67: 45012 | AP67: A2 | AQ67: 48171 | AR67: =IF(AQ67>TODAY(),"Vigente","No Vigente") -> Vigente | AU67: Tiene 1 multa por transitar por sitios restringidos o en horas prohibidas por la autoridad competente (C14) conduciendo la moto ZFM18F. | BD67: Retirado
A68: 65 | D68: 1143924317 | E68: Duque Agudelo Ingrid Vannesa | F68: 32593 | G68: MASCULINO | I68: =(CC$1-F68)/365 -> 37.041096 | K68: Supervisor | L68: Comercial | M68: 40976 | N68: =(CC$1-M68)/365 -> 14.073973 | O68: 318 661 9608 | T68: 45146 | V68: OGX66C | W68: MH8BE4DUADJ106779 | X68: E470-ID910720 | Y68: 2013 | Z68: Suzuki | AA68: 113 | AC68: 41380 | AD68: Moto | AE68: Si | AH68: NO APLICA | AI68: NO APLICA | AJ68: =IF(AK68>TODAY(),"Vigente","No Vigente") -> No Vigente | AK68: =(AL68+365) -> 45447 | AL68: 45082 | AM68: =IF(AN68>TODAY(),"Vigente","No Vigente") -> No Vigente | AN68: =(AO68+365) -> 45402 | AO68: 45037 | AP68: A2 | AQ68: 48661 | AR68: =IF(AQ68>TODAY(),"Vigente","No Vigente") -> Vigente | AU68: No tiene multas. | BD68: Se recibe por correo Actualización.
